Workbook

Sheet 使い方
A1: 使い方：カンツギ 事業計画書「計算詳細版」の数字の裏取り
A2: このブックは、計算詳細版の数字が計算モデル（deck/tora_v2.js）と同じ式で出ることを、すべての計算過程が追える形で示すためのもの。入力は「前提」だけにあり、他のシートはすべて式。最後の「照合」で、Excel の結果と tora_v2.js の値が一致することを確かめている。
A4: シートの一覧
A5: シート | B5: 中身 | C5: 計算詳細版のページ | D5: tora_v2.js の対応
A6: 前提 | B6: 入力をすべて集めた（青字）。確度と出典を付けた。年ごとの項目は1〜10年目 | C6: p.4・16・17・32 | D6: WAGE・PLAN・SAVE・CLOUD・SETUP_TASKS・ROLES・EXT・GROWTH・LOAD・RECRUIT_RATE・ADVISORS
A7: 時給 | B7: 職長・施工管理者の1時間の人件費＝年収×会社負担÷年間総実労働時間 | C7: p.5 | D7: H（hourly）
A8: お客様の効果 | B8: 1台1日の効果、年の効果、支払い、倍率、元が取れる分、感度表、手戻り（参考） | C8: p.6・7・8 | D8: customerValue()
A9: 値段と原価 | B9: 1拠点の売上、1台の原価の内訳と検算、粗利率、広い原価の粗利率、台数と使い方、追加料金の案 | C9: p.9・10・11・12 | D9: priceSite・CLOUD・cloudPerDevice・cogsSite・marginSite
A10: 導入支援 | B10: 6つの作業×人日、日額、原価・値段・粗利、お客様の1年目の支払い | C10: p.13 | D10: SETUP_TASKS・setupDays・CSDAY・setupTravel
A11: 体制と人件費 | B11: 8つの役割の年収×人数、人件費、採用費、つまみの反映、導入コンサルタントの上限 | C11: p.17 | D11: ROLES・EXT.heads・team()
A12: 拠点と売上 | B12: 期首・解約・新規・期末、既存と新規の利用料、導入支援、個社設定、売上 | C12: p.14・15 | D12: run() の拠点と売上
A13: 損益と現金 | B13: 原価、粗利、販管費、営業利益、累計、現金。黒字化の年・累計回収の年・最低の現金 | C13: p.3・18・30 | D13: run() の損益と現金
A14: 黒字ライン | B14: 損益分岐点売上、社員1人あたりの拠点、黒字に必要な拠点、5年目に要る台数 | C14: p.19・22 | D14: run() の bep・sitesPerStaff
A15: LTV・CAC | B15: LTV（3・5・7・10年）、CAC、回収月数 | C15: p.20 | D15: unit()
A16: 崩れたとき | B16: 前提を一つずつ崩した結果（tora_v2.js の値を貼った）と、Excel で再現する方法 | C16: p.21・22 | D16: run(o)・shortfall()
... A19: 照合 | B19: Excel の主な結果と tora_v2.js の値を並べ、差がゼロ（丸め誤差）であることを示す | C19: ─ | D19: node で出した値
A21: 色の見方
A22: 青字 | B22: 入力。前提シートだけにある。ここを書き換えると全部のシートが計算し直される
A23: 黒字 | B23: 計算（式）
A24: 赤字（▲） | B24: マイナスの数字（赤字の金額など）
A25: 緑字 | B25: 黒字化の年。損益と現金の営業利益の行では、初めて黒字になる年を緑で示す
A26: 灰色の数字 | B26: tora_v2.js を node で計算して貼った値（崩れたとき・照合の数字の列）。式ではない
A27: 紺の行 | B27: 見出し
A29: 確度の見方（前提シートの「確度」の列）
A30: 統計 | B30: 国の統計（賃金構造基本統計調査、毎月勤労統計調査、建設業許可業者数調査など）
A31: 制度 | B31: 法律や保険料率など、制度で決まる値（社会保険料の会社負担、残業の割増）
A32: 公表 | B32: メーカー・クラウド・AIの公表価格
A33: 見積 | B33: 社内の見積（値段、台数、人数、年収、経費など）
A34: 仮説 | B34: 実証で測るもの（削減時間、手戻りの削減、会える率・成約率など）
A35: 仮定 | B35: 計算のために置いた値（為替、シナリオのつまみ、参考の表の軸など）
A36: 換算 | B36: 単位の換算（60分＝1時間など）。前提ではないが、式の中に数字を書かないために置いた
A38: 決まりと注意
A39: ・金額は、ことわりがなければ万円。各行に単位を書き、右の列に式（言葉）を書いた。
A40: ・前提のつまみ（8-1〜8-6）が初期値のとき、tora_v2.js の計画（run({years:10})）と一致する。5年目までの値は run()（5年）と同じ。
A41: ・つまみを変えれば、崩れたときのシナリオを Excel で再現できる（崩れたときシートの右の列）。
A42: ・このモデルは運転資本・税・償却を含まない簡易計算。
A43: ・元のファイル：deck/tora_v2.js（計算モデル）、deck/tora_market.js（市場規模）、deck/build_tora_detail.js（計算詳細版の作り）。モデルと資料のファイルは書き換えていない。
A44: ・フォントは BIZ UDPゴシック を指定している（無い環境では別のフォントで表示される）。PDF は BIZ UDPゴシック の無い環境で書き出したので IPA Pゴシック で表示している。

Sheet 前提
A1: 前提：入力はこのシートだけ
A2: 青字＝入力（ここだけを書き換える）、黒字＝計算。他のシートはすべてこのシートを参照する式。年ごとの項目は「値」の列が1年目で、右へ2〜10年目。1〜5年目は tora_v2.js の ROLES・GROWTH、6〜10年目は EXT の値。確度：統計＝公的統計／制度＝法律・料率など制度で決まる値／公表＝メーカー・クラウドの公表価格／見積＝社内見積／仮説＝実証で測る／仮定＝計算のために置いた値／換算＝単位の換算。
A3: 番号 | B3: 項目 | C3: 単位 | D3: 確度 | E3: 値（年ごとは1年目） | F3: 2年目 | G3: 3年目 | H3: 4年目 | I3: 5年目 | J3: 6年目 | K3: 7年目 | L3: 8年目 | M3: 9年目 | N3: 10年目 | O3: 出典・メモ
A4: 0. 単位の換算（前提ではなく、式の中に数字を書かないために置く）
A5: 0-1 | B5: 1時間の分 | C5: 分/時間 | D5: 換算 | E5: 60
A6: 0-2 | B6: 1年の月数 | C6: か月/年 | D6: 換算 | E6: 12
A7: 0-3 | B7: 1万円の円 | C7: 円/万円 | D7: 換算 | E7: 10000
A8: 0-4 | B8: 1年の日数 | C8: 日/年 | D8: 換算 | E8: 365
A9: 0-5 | B9: 1億円の万円 | C9: 万円/億円 | D9: 換算 | E9: 10000
A10: 0-6 | B10: AIの単価の基準（100万トークン） | C10: トークン | D10: 換算 | E10: 1000000 | O10: AIの単価は100万トークンあたりのドルで書く
A11: 1. 時給（お客様の1時間の人件費）
A12: 1-1 | B12: 職長（電気工事従事者）の年収 | C12: 万円/年 | D12: 統計 | E12: 551 | O12: 厚生労働省「賃金構造基本統計調査」令和5年 電気工事従事者：きまって支給する給与 月36.74万円×12＋賞与等110.06万円＝550.94万円（残業代を含む）。令和6年も約548〜551万円
A13: 1-2 | B13: 施工管理者の年収 | C13: 万円/年 | D13: 統計 | E13: 620 | O13: 同調査で代用：建築技術者 約642万円（令和6年）と土木技術者 約604万円（令和5年）の間。施工管理技士は標本が少ないので使わない
A14: 1-3 | B14: 会社負担（社会保険料）を含める倍率 | C14: 倍 | D14: 制度 | E14: 1.17 | O14: 会社負担 約17%：健康保険 約5.0%＋厚生年金9.15%＋雇用保険（建設）1.1%＋子ども・子育て拠出金0.36%＋労災 約1.2%
A15: 1-4 | B15: 建設業の月の総実労働時間（残業を含む） | C15: 時間/月 | D15: 統計 | E15: 161.5 | O15: 厚生労働省「毎月勤労統計調査」令和6年 建設業の総実労働時間（所定内＋所定外）
A16: 1-5 | B16: 年間総実労働時間 | C16: 時間/年 | D16: 統計 | E16: =E15*$E$6 -> 1938 | O16: 月161.5時間×12＝1,938時間（tora_v2.js の annualHours）
A17: 1-6 | B17: 残業の割増 | C17: 倍 | D17: 制度 | E17: 1.25 | O17: 労働基準法：時間外労働は25%以上の割増。参考の計算だけに使い、計画には入れない
A18: 1-7 | B18: 参考：所定の1日の時間 | C18: 時間/日 | D18: 仮定 | E18: 8 | O18: 所定の目安（1日8時間）。参考の比較だけに使う
A19: 1-8 | B19: 参考：所定の年の日数（目安） | C19: 日/年 | D19: 仮定 | E19: 244 | O19: 所定の目安（年約244日）。8時間×244日＝1,952時間は所定の目安で、実績ではない
A20: 2. 端末と値段（1拠点）
A21: 2-1 | B21: 1拠点の台数 | C21: 台/拠点 | D21: 見積 | E21: 10 | O21: 1班に1台、職長が掛ける。5現場×2班（計算詳細版 p.10）
A22: 2-2 | B22: 端末を使う日数 | C22: 日/年 | D22: 見積 | E22: 240 | O22: 上限に近い想定。現場の稼働日数で減る
A23: 2-3 | B23: 基盤の利用料 | C23: 万円/年/拠点 | D23: 見積 | E23: 60 | O23: 月5万円×12
A24: 2-4 | B24: 端末ライセンス | C24: 万円/年/台 | D24: 見積 | E24: 24 | O24: 月2万円×12。録画は端末に無制限、AIで解析する場面に月の上限
A25: 2-5 | B25: 導入支援（初年度のみ） | C25: 万円/拠点 | D25: 見積 | E25: 200 | O25: 42人日の原価141万円の約1.4倍（他社の相場は未確認）
A26: 2-6 | B26: カメラ付きAIグラスの本体 | C26: 万円/台 | D26: 公表 | E26: 8 | O26: Ray-Ban Meta 7.4〜8.9万円
A27: 2-7 | B27: 表示付きARグラスの本体 | C27: 万円/台 | D27: 公表 | E27: 12 | O27: Meta Ray-Ban Display $799
A28: 2-8 | B28: リースの月額料率（3年リース） | C28: 割合/月 | D28: 見積 | E28: 0.03 | O28: 3年リースの料率 約3%／月。リース会社の見積で確認する
A29: 2-9 | B29: 構成：カメラ付きAIグラス | C29: 台/拠点 | D29: 見積 | E29: 8 | O29: 記録用
A30: 2-10 | B30: 構成：表示付きARグラス | C30: 台/拠点 | D30: 見積 | E30: 2 | O30: 手元に図面を出す班
A31: 2-11 | B31: リースの年額：カメラ付き | C31: 万円/年/台 | D31: 公表 | E31: =$E$26*$E$28*$E$6 -> 2.88 | O31: 本体8万円×月額料率3%×12か月
A32: 2-12 | B32: リースの年額：表示付き | C32: 万円/年/台 | D32: 公表 | E32: =$E$27*$E$28*$E$6 -> 4.32 | O32: 本体12万円×月額料率3%×12か月
A33: 2-13 | B33: 構成の台数の合計（確認） | C33: 台/拠点 | D33: 見積 | E33: =$E$29+$E$30 -> 10 | O33: 2-1の台数と同じであること。リースはお客様の支払いだけに効き、当社の売上・原価には入らない
A34: 3. 削減時間（1台1日）と手戻り（参考）
A35: 3-1 | B35: 職長の削減（日報・撮影・黒板） | C35: 分/台/日 | D35: 仮説 | E35: 15 | O35: 実証で導入前2週間と導入後4週間を比べて測る
A36: 3-2 | B36: 施工管理者の削減（写真整理・写真台帳） | C36: 分/台/日 | D36: 仮説 | E36: 20 | O36: 同上
A37: 3-3 | B37: 参考：お客様の完成工事高 | C37: 万円/年 | D37: 仮定 | E37: 300000 | O37: 中堅100人規模の目安30億円。計画に入れない
A38: 3-4 | B38: 参考：手戻りが工事費に占める割合 | C38: 割合 | D38: 仮定 | E38: 0.02 | O38: 海外研究の範囲0.4〜6%、RC造の事例1.85〜2.1%から控えめに
A39: 3-5 | B39: 参考：ARが効く対象工種の割合 | C39: 割合 | D39: 仮説 | E39: 0.3
A40: 3-6 | B40: 参考：手戻りの削減率 | C40: 割合 | D40: 仮説 | E40: 0.2
B41: 感度表の軸 | E41: 1 | F41: 2 | G41: 3 | H41: 4
A42: 3-7 | B42: 感度表：使う日数 | C42: 日/年 | D42: 見積 | E42: 180 | F42: 200 | G42: 220 | H42: 240 | O42: 240日は上限に近い。現場の稼働で減る場合を見る
A43: 3-8 | B43: 感度表：職長の削減（25分・35分・60分の内訳） | C43: 分/台/日 | D43: 仮説 | E43: 10 | F43: 15 | G43: 25 | O43: tora_v2.js の感度表と同じ内訳（10＋15、15＋20、25＋35）
A44: 3-9 | B44: 感度表：施工管理者の削減（同上） | C44: 分/台/日 | D44: 仮説 | E44: 15 | F44: 20 | G44: 35
A45: 4. AI・保存の原価（1台・月）とデータ基盤
A46: 4-1 | B46: 為替 | C46: 円/ドル | D46: 仮定 | E46: 150 | O46: $1＝150円
A47: 4-2 | B47: 1日の録画時間 | C47: 時間/日 | D47: 見積 | E47: 4
A48: 4-3 | B48: 1か月の稼働日 | C48: 日/月 | D48: 見積 | E48: 20
A49: 4-4 | B49: 音声の文字起こしの単価 | C49: ドル/分 | D49: 公表 | E49: 0.003 | O49: クラウドの文字起こしの公表単価の目安（多めに見た上限）
A50: 4-5 | B50: 大事な場面の画像 | C50: 枚/台/月 | D50: 見積 | E50: 3000 | O50: 録画は端末に全部残し、選んだ場面だけを送る
A51: 4-6 | B51: モデルの置き方：画像1枚のトークン | C51: トークン/枚 | D51: 仮定 | E51: 1000 | O51: tora_v2.js の CLOUD.vision（3,000枚×約1,000トークンで月1,000円）
A52: 4-7 | B52: 画像の幅 | C52: ピクセル | D52: 公表 | E52: 1280 | O52: 開発者向けの映像は720p（計算詳細版 p.26）
A53: 4-8 | B53: 画像の高さ | C53: ピクセル | D53: 公表 | E53: 720
A54: 4-9 | B54: 画像のトークン数の換算（幅×高さ÷この値） | C54: ピクセル/トークン | D54: 公表 | E54: 750 | O54: Claude の画像のトークン数の目安＝幅×高さ÷750
A55: 4-10 | B55: 画像1枚あたりの指示文 | C55: トークン/枚 | D55: 見積 | E55: 300
A56: 4-11 | B56: 画像1枚あたりの出力 | C56: トークン/枚 | D56: 見積 | E56: 150
A57: 4-12 | B57: Claude Haiku 5.5 の入力単価 | C57: ドル/100万トークン | D57: 公表 | E57: 0.1 | O57: Anthropic の API 価格（10万トークン以下の要求）
A58: 4-13 | B58: Claude Haiku 5.5 の出力単価 | C58: ドル/100万トークン | D58: 公表 | E58: 0.5 | O58: 同上
A59: 4-14 | B59: Claude Sonnet 5.5 の入力単価 | C59: ドル/100万トークン | D59: 公表 | E59: 2 | O59: Anthropic の API 価格
A60: 4-15 | B60: Claude Sonnet 5.5 の出力単価 | C60: ドル/100万トークン | D60: 公表 | E60: 10 | O60: 同上
A61: 4-16 | B61: 報告書の件数 | C61: 件/台/日 | D61: 見積 | E61: 1 | O61: 1日1件
A62: 4-17 | B62: 報告書1件の入力 | C62: トークン/件 | D62: 見積 | E62: 20000 | O62: Sonnet 5.5 で作るとして検算する
A63: 4-18 | B63: 報告書1件の出力 | C63: トークン/件 | D63: 見積 | E63: 2000
A64: 4-19 | B64: クラウドへ送る切り出し動画 | C64: GB/台/月 | D64: 見積 | E64: 10 | O64: 1日4時間の録画そのものは端末に残し、送らない
A65: 4-20 | B65: クラウドの保存期間 | C65: か月 | D65: 見積 | E65: 36 | O65: 3年保存
A66: 4-21 | B66: 保存の単価（Amazon S3 相当） | C66: ドル/GB・月 | D66: 公表 | E66: 0.025
A67: 4-22 | B67: モデルの値：音声の文字起こし | C67: 円/台/月 | D67: 見積 | E67: 2200 | O67: tora_v2.js CLOUD.transcribe
A68: 4-23 | B68: モデルの値：画像解析 | C68: 円/台/月 | D68: 見積 | E68: 1000 | O68: tora_v2.js CLOUD.vision
A69: 4-24 | B69: モデルの値：報告書の生成 | C69: 円/台/月 | D69: 見積 | E69: 200 | O69: tora_v2.js CLOUD.report
A70: 4-25 | B70: モデルの値：動画の保存 | C70: 円/台/月 | D70: 見積 | E70: 700 | O70: tora_v2.js CLOUD.storage（3年間の平均で置いた値）
A71: 4-26 | B71: モデルの値：転送・監視・バックアップ・端末管理（MDM）・余裕 | C71: 円/台/月 | D71: 見積 | E71: 1900 | O71: tora_v2.js CLOUD.ops
A72: 4-27 | B72: 全編を送り毎秒解析した場合の原価 | C72: 円/台/月 | D72: 見積 | E72: 50000 | O72: tora_v2.js FULL_UPLOAD_PER_DEVICE（5万円×12）。動画1日4時間・毎秒1枚の解析と保存
A73: 4-28 | B73: データ基盤（会社ごとの保管庫） | C73: 万円/月/拠点 | D73: 見積 | E73: 1 | O73: tora_v2.js siteInfra（年12万円）
A74: 4-29 | B74: データ基盤の年額 | C74: 万円/年/拠点 | D74: 見積 | E74: =E73*$E$6 -> 12 | O74: 月1万円×12
A75: 4-30 | B75: 追加料金＝原価の何倍か | C75: 倍 | D75: 仮定 | E75: 3 | O75: 解析量のプラン案（参考）だけに使う
A76: 4-31 | B76: 追加の単位：画像 | C76: 枚 | D76: 仮定 | E76: 1000
A77: 4-32 | B77: 追加の単位：保存 | C77: GB/台/月 | D77: 仮定 | E77: 10
A78: 4-33 | B78: 追加料金の丸めの単位 | C78: 円 | D78: 仮定 | E78: 1000
B79: 粗利率の表の軸 | E79: 1 | F79: 2 | G79: 3
A80: 4-34 | B80: 粗利率の表：1拠点の台数 | C80: 台/拠点 | D80: 仮定 | E80: 5 | F80: 10 | G80: 25 | O80: 計算詳細版 p.12
A81: 5. 導入支援の作業（1拠点）
A82: 5-1 | B82: 現状調査・業務の流れの整理 | C82: 人日/拠点 | D82: 見積 | E82: 5 | O82: tora_v2.js SETUP_TASKS
A83: 5-2 | B83: 端末の設定・アカウント・端末管理 | C83: 人日/拠点 | D83: 見積 | E83: 3 | O83: tora_v2.js SETUP_TASKS
A84: 5-3 | B84: 図面・手順・報告書の型の登録 | C84: 人日/拠点 | D84: 見積 | E84: 10 | O84: tora_v2.js SETUP_TASKS
A85: 5-4 | B85: 職長・施工管理者への研修（2回） | C85: 人日/拠点 | D85: 見積 | E85: 4 | O85: tora_v2.js SETUP_TASKS
A86: 5-5 | B86: 現場での立ち会い・初期の手直し（週2日×8週） | C86: 人日/拠点 | D86: 見積 | E86: 16 | O86: tora_v2.js SETUP_TASKS
A87: 5-6 | B87: 導入前後の効果測定レポート | C87: 人日/拠点 | D87: 見積 | E87: 4 | O87: tora_v2.js SETUP_TASKS
A88: 5-7 | B88: 導入支援の交通費 | C88: 万円/拠点 | D88: 見積 | E88: 15 | O88: 16回訪問×約1万円
A89: 5-8 | B89: 導入コンサルタントの年間稼働日 | C89: 日/年 | D89: 見積 | E89: 240 | O89: 日額＝年収600万円×1.2÷240日（tora_v2.js CSDAY）
A90: 5-9 | B90: 導入コンサルタント1人が回せる新規拠点 | C90: 拠点/人/年 | D90: 見積 | E90: 6 | O90: 2か月で1拠点（tora_v2.js GROWTH.newSites の注）
A91: 6. 体制（年収と期末の人数。1〜5年目＝ROLES、6〜10年目＝EXT.heads）
B92: 役割 | E92: 1年目 | F92: 2年目 | G92: 3年目 | H92: 4年目 | I92: 5年目 | J92: 6年目 | K92: 7年目 | L92: 8年目 | M92: 9年目 | N92: 10年目
A93: 6-1 | B93: 年収：代表（創業者） | C93: 万円/年 | D93: 見積 | E93: 480 | F93: 600 | G93: 720 | H93: 720 | I93: 720 | J93: =I93 -> 720 | K93: =J93 -> 720 | L93: =K93 -> 720 | M93: =L93 -> 720 | N93: =M93 -> 720 | O93: 見積。段階的に上げ、6年目以降は5年目と同じ
A94: 6-2 | B94: 年収：CTO | C94: 万円/年 | D94: 見積 | E94: 1000 | F94: =E94 -> 1000 | G94: =F94 -> 1000 | H94: =G94 -> 1000 | I94: =H94 -> 1000 | J94: =I94 -> 1000 | K94: =J94 -> 1000 | L94: =K94 -> 1000 | M94: =L94 -> 1000 | N94: =M94 -> 1000 | O94: 見積（相場は要確認）。2年目以降は前の年を参照
A95: 6-3 | B95: 年収：エンジニア | C95: 万円/年 | D95: 見積 | E95: 800 | F95: =E95 -> 800 | G95: =F95 -> 800 | H95: =G95 -> 800 | I95: =H95 -> 800 | J95: =I95 -> 800 | K95: =J95 -> 800 | L95: =K95 -> 800 | M95: =L95 -> 800 | N95: =M95 -> 800 | O95: 見積（相場は要確認）。2年目以降は前の年を参照
A96: 6-4 | B96: 年収：現場監修（施工管理経験者） | C96: 万円/年 | D96: 見積 | E96: 650 | F96: =E96 -> 650 | G96: =F96 -> 650 | H96: =G96 -> 650 | I96: =H96 -> 650 | J96: =I96 -> 650 | K96: =J96 -> 650 | L96: =K96 -> 650 | M96: =L96 -> 650 | N96: =M96 -> 650 | O96: 見積（相場は要確認）。2年目以降は前の年を参照
A97: 6-5 | B97: 年収：導入コンサルタント | C97: 万円/年 | D97: 見積 | E97: 600 | F97: =E97 -> 600 | G97: =F97 -> 600 | H97: =G97 -> 600 | I97: =H97 -> 600 | J97: =I97 -> 600 | K97: =J97 -> 600 | L97: =K97 -> 600 | M97: =L97 -> 600 | N97: =M97 -> 600 | O97: 見積（相場は要確認）。2年目以降は前の年を参照
A98: 6-6 | B98: 年収：営業（技術営業） | C98: 万円/年 | D98: 見積 | E98: 650 | F98: =E98 -> 650 | G98: =F98 -> 650 | H98: =G98 -> 650 | I98: =H98 -> 650 | J98: =I98 -> 650 | K98: =J98 -> 650 | L98: =K98 -> 650 | M98: =L98 -> 650 | N98: =M98 -> 650 | O98: 見積（相場は要確認）。2年目以降は前の年を参照
A99: 6-7 | B99: 年収：管理（人事・経理・総務） | C99: 万円/年 | D99: 見積 | E99: 550 | F99: =E99 -> 550 | G99: =F99 -> 550 | H99: =G99 -> 550 | I99: =H99 -> 550 | J99: =I99 -> 550 | K99: =J99 -> 550 | L99: =K99 -> 550 | M99: =L99 -> 550 | N99: =M99 -> 550 | O99: 見積（相場は要確認）。2年目以降は前の年を参照
A100: 6-8 | B100: 年収：戦略企画 | C100: 万円/年 | D100: 見積 | E100: 700 | F100: =E100 -> 700 | G100: =F100 -> 700 | H100: =G100 -> 700 | I100: =H100 -> 700 | J100: =I100 -> 700 | K100: =J100 -> 700 | L100: =K100 -> 700 | M100: =L100 -> 700 | N100: =M100 -> 700 | O100: 見積（相場は要確認）。2年目以降は前の年を参照
...

Sheet 時給
A1: 時給：お客様の1時間の人件費
A2: 1時間の人件費＝年収×会社負担÷年間総実労働時間。年収も総実労働時間も残業を含むので、分子と分母がそろっている（計算詳細版 p.5）。
A3: 項目 | B3: 職長（電工） | C3: 施工管理者 | D3: 単位 | E3: 式（言葉）
A4: 年収（残業代・賞与を含む） | B4: ='前提'!$E$12 -> 551 | C4: ='前提'!$E$13 -> 620 | D4: 万円/年 | E4: 賃金構造基本統計調査（前提1-1・1-2）
A5: 会社負担を含める倍率 | B5: ='前提'!$E$14 -> 1.17 | C5: ='前提'!$E$14 -> 1.17 | D5: 倍 | E5: 社会保険料の会社負担 約17%（前提1-3）
A6: 会社負担込みの年の人件費 | B6: =$B$4*$B$5 -> 644.67 | C6: =$C$4*$C$5 -> 725.4 | D6: 万円/年 | E6: 年収×会社負担
A7: 年間総実労働時間（残業を含む） | B7: ='前提'!$E$16 -> 1938 | C7: ='前提'!$E$16 -> 1938 | D7: 時間/年 | E7: 毎月勤労統計 建設業 月161.5時間×12（前提1-5）
A8: 1時間の人件費 | B8: =$B$6/$B$7 -> 0.33264706 | C8: =$C$6/$C$7 -> 0.37430341 | D8: 万円/時間 | E8: 年収×会社負担÷年間総実労働時間
A9: 1時間の人件費（円） | B9: =$B$8*'前提'!$E$7 -> 3326.4706 | C9: =$C$8*'前提'!$E$7 -> 3743.0341 | D9: 円/時間 | E9: 上の万円×10,000
A10: 1分の人件費 | B10: =$B$9/'前提'!$E$5 -> 55.441176 | C10: =$C$9/'前提'!$E$5 -> 62.383901 | D10: 円/分 | E10: 1時間の人件費÷60
A11: 参考（計画には入れない）
A12: 削った時間がすべて残業だった場合の1時間の価値 | B12: =$B$9*'前提'!$E$17 -> 4158.0882 | C12: =$C$9*'前提'!$E$17 -> 4678.7926 | D12: 円/時間 | E12: 1時間の人件費×残業の割増1.25
A13: そのときのお客様の効果（1拠点） | B13: ='お客様の効果'!$C$14*'前提'!$E$17 -> 623.7887 | D13: 万円/年 | E13: お客様の効果（年約499万円）×1.25。計画には入れない
A14: 参考：所定の目安の時間（1日8時間×244日） | B14: ='前提'!$E$18*'前提'!$E$19 -> 1952 | C14: ='前提'!$E$18*'前提'!$E$19 -> 1952 | D14: 時間/年 | E14: 1日8時間×約244日。所定の目安で、実績ではない
A15: 参考：所定の目安で割った1時間 | B15: =$B$6/$B$14*'前提'!$E$7 -> 3302.6127 | C15: =$C$6/$C$14*'前提'!$E$7 -> 3716.1885 | D15: 円/時間 | E15: 年収×会社負担÷1,952時間。値は近いが意味が違うので使わない
A17: 注1：総実労働時間は毎月勤労統計の「総実労働時間」で、所定外（残業）を含む実績。
A18: 注2：年収（賃金構造基本統計調査）も、きまって支給する給与（残業代を含む）と賞与の合計。分子にも分母にも残業が入っている。
A19: 注3：残業を除いた所定内の時間で割ると、分母だけが小さくなり単価が高く出るので使わない。「1日8時間×約244日＝1,952時間」は所定の目安で実績ではない（値は1,938時間に近いが意味が違う）。
A20: 注4：削った時間がすべて残業なら、割増1.25倍の分だけ効果は大きくなる（年約624万円）。計画には入れない。お客様の効果は控えめに見ている。当社の売上と利益は、この単価には左右されない。

Sheet お客様の効果
A1: お客様の効果：1拠点10台で年約499万円、支払いの約1.5倍
A2: 効果はAIグラスを掛けた班の分だけで数える（社員全員が減るとは数えない）。お客様の支払いは当社への利用料とグラスのリース。tora_v2.js の customerValue() と同じ式（計算詳細版 p.6〜8）。
A3: 項目 | B3: 単位 | C3: 値 | F3: 式（言葉）
A4: 1台1日の効果
A5: 職長の削減 | B5: 分/台/日 | C5: ='前提'!$E$35 -> 15 | D5: 日報・撮影・黒板（前提3-1・仮説）
A6: 施工管理者の削減 | B6: 分/台/日 | C6: ='前提'!$E$36 -> 20 | D6: 写真整理・写真台帳（前提3-2・仮説）
A7: 職長の1時間の人件費 | B7: 円/時間 | C7: ='時給'!$B$9 -> 3326.4706 | D7: 時給シート
A8: 施工管理者の1時間の人件費 | B8: 円/時間 | C8: ='時給'!$C$9 -> 3743.0341 | D8: 時給シート
A9: 1台1日の効果 | B9: 円/台/日 | C9: =$C$5/'前提'!$E$5*$C$7+$C$6/'前提'!$E$5*$C$8 -> 2079.2957 | D9: 15分÷60×職長の時給＋20分÷60×施工管理者の時給
A10: 1台1日の効果（万円） | B10: 万円/台/日 | C10: =$C$9/'前提'!$E$7 -> 0.20792957 | D10: 上の円÷10,000
A11: 1拠点・1年の効果
A12: 1拠点の台数 | B12: 台/拠点 | C12: ='前提'!$E$21 -> 10 | D12: 前提2-1
A13: 端末を使う日数 | B13: 日/年 | C13: ='前提'!$E$22 -> 240 | D13: 前提2-2。上限に近い想定
A14: お客様の効果（年） | B14: 万円/年 | C14: =$C$10*$C$12*$C$13 -> 499.03096 | D14: 1台1日の効果×台数×日数
A15: 1台1日の削減の合計 | B15: 分/台/日 | C15: =$C$5+$C$6 -> 35 | D15: 職長15分＋施工管理者20分
A16: 浮く時間（分） | B16: 分/年 | C16: =$C$15*$C$12*$C$13 -> 84000 | D16: 35分×10台×240日
A17: 浮く時間（時間） | B17: 時間/年 | C17: =$C$16/'前提'!$E$5 -> 1400 | D17: 上の分÷60
A18: お客様の支払い（1拠点・2年目以降の年額）
A19: 当社：基盤 | B19: 万円/年 | C19: ='値段と原価'!$C$5 -> 60 | D19: 月5万円×12（値段と原価。値段の倍率を反映）
A20: 当社：端末ライセンス×台数 | B20: 万円/年 | C20: ='値段と原価'!$C$6*$C$12 -> 240 | D20: 月2万円×12×10台
A21: 当社への利用料 | B21: 万円/年 | C21: =$C$19+$C$20 -> 300 | D21: 基盤＋端末ライセンス
A22: リース：カメラ付きAIグラス | B22: 万円/年 | C22: ='前提'!$E$29*'前提'!$E$31 -> 23.04 | D22: 8台×(8万円×3%×12)
A23: リース：表示付きARグラス | B23: 万円/年 | C23: ='前提'!$E$30*'前提'!$E$32 -> 8.64 | D23: 2台×(12万円×3%×12)
A24: リースの合計 | B24: 万円/年 | C24: =$C$22+$C$23 -> 31.68 | D24: お客様からリース会社へ払う（当社の売上ではない）
A25: お客様の支払いの合計 | B25: 万円/年 | C25: =$C$21+$C$24 -> 331.68 | D25: 利用料＋リース
A26: 倍率（効果÷支払い） | B26: 倍 | C26: =$C$14/$C$25 -> 1.5045555 | D26: お客様の効果÷支払いの合計
A27: 元が取れる分（1台1日に何分減れば支払いと同じになるか）
A28: 1台1日の支払い | B28: 円/台/日 | C28: =$C$25/($C$12*$C$13)*'前提'!$E$7 -> 1382 | D28: 支払い÷(台数×日数)
A29: 同じ配分での1分の人件費 | B29: 円/分 | C29: =($C$7*$C$5/$C$15+$C$8*$C$6/$C$15)/'前提'!$E$5 -> 59.408448 | D29: (職長の時給×15/35＋施工管理者の時給×20/35)÷60
A30: 元が取れる分 | B30: 分/台/日 | C30: =$C$28/$C$29 -> 23.262685 | D30: 1台1日の支払い÷同じ配分での1分の人件費
A31: 感度表：使う日数×1台1日の削減
A32: 年の効果 使う日数＼1台1日の削減（職長＋施工管理） | B32: 単位 | C32: =TEXT('前提'!$E$43+'前提'!$E$44,"0")&"分"&CHAR(10)&"（"&'前提'!$E$43&"＋"&'前提'!$E$44&"）" -> 25分 （10＋15） | D32: =TEXT('前提'!$F$43+'前提'!$F$44,"0")&"分"&CHAR(10)&"（"&'前提'!$F$43&"＋"&'前提'!$F$44&"）" -> 35分 （15＋20） | E32: =TEXT('前提'!$G$43+'前提'!$G$44,"0")&"分"&CHAR(10)&"（"&'前提'!$G$43&"＋"&'前提'!$G$44&"）" -> 60分 （25＋35） | F32: 式（言葉）
A33: ='前提'!$E$42 -> 180 | B33: 万円/年 | C33: =('前提'!$E$43/'前提'!$E$5*$C$7+'前提'!$E$44/'前提'!$E$5*$C$8)/'前提'!$E$7*$C$12*'前提'!$E$42 -> 268.23065 | D33: =('前提'!$F$43/'前提'!$E$5*$C$7+'前提'!$F$44/'前提'!$E$5*$C$8)/'前提'!$E$7*$C$12*'前提'!$E$42 -> 374.27322 | E33: =('前提'!$G$43/'前提'!$E$5*$C$7+'前提'!$G$44/'前提'!$E$5*$C$8)/'前提'!$E$7*$C$12*'前提'!$E$42 -> 642.50387 | F33: (分÷60×時給)の合計×台数×日数÷10,000
A34: ='前提'!$F$42 -> 200 | B34: 万円/年 | C34: =('前提'!$E$43/'前提'!$E$5*$C$7+'前提'!$E$44/'前提'!$E$5*$C$8)/'前提'!$E$7*$C$12*'前提'!$F$42 -> 298.03406 | D34: =('前提'!$F$43/'前提'!$E$5*$C$7+'前提'!$F$44/'前提'!$E$5*$C$8)/'前提'!$E$7*$C$12*'前提'!$F$42 -> 415.85913 | E34: =('前提'!$G$43/'前提'!$E$5*$C$7+'前提'!$G$44/'前提'!$E$5*$C$8)/'前提'!$E$7*$C$12*'前提'!$F$42 -> 713.89319 | F34: (分÷60×時給)の合計×台数×日数÷10,000
A35: ='前提'!$G$42 -> 220 | B35: 万円/年 | C35: =('前提'!$E$43/'前提'!$E$5*$C$7+'前提'!$E$44/'前提'!$E$5*$C$8)/'前提'!$E$7*$C$12*'前提'!$G$42 -> 327.83746 | D35: =('前提'!$F$43/'前提'!$E$5*$C$7+'前提'!$F$44/'前提'!$E$5*$C$8)/'前提'!$E$7*$C$12*'前提'!$G$42 -> 457.44505 | E35: =('前提'!$G$43/'前提'!$E$5*$C$7+'前提'!$G$44/'前提'!$E$5*$C$8)/'前提'!$E$7*$C$12*'前提'!$G$42 -> 785.28251 | F35: (分÷60×時給)の合計×台数×日数÷10,000
A36: ='前提'!$H$42 -> 240 | B36: 万円/年 | C36: =('前提'!$E$43/'前提'!$E$5*$C$7+'前提'!$E$44/'前提'!$E$5*$C$8)/'前提'!$E$7*$C$12*'前提'!$H$42 -> 357.64087 | D36: =('前提'!$F$43/'前提'!$E$5*$C$7+'前提'!$F$44/'前提'!$E$5*$C$8)/'前提'!$E$7*$C$12*'前提'!$H$42 -> 499.03096 | E36: =('前提'!$G$43/'前提'!$E$5*$C$7+'前提'!$G$44/'前提'!$E$5*$C$8)/'前提'!$E$7*$C$12*'前提'!$H$42 -> 856.67183 | F36: (分÷60×時給)の合計×台数×日数÷10,000
A37: 倍率 使う日数＼1台1日の削減（職長＋施工管理） | B37: 単位 | C37: =TEXT('前提'!$E$43+'前提'!$E$44,"0")&"分"&CHAR(10)&"（"&'前提'!$E$43&"＋"&'前提'!$E$44&"）" -> 25分 （10＋15） | D37: =TEXT('前提'!$F$43+'前提'!$F$44,"0")&"分"&CHAR(10)&"（"&'前提'!$F$43&"＋"&'前提'!$F$44&"）" -> 35分 （15＋20） | E37: =TEXT('前提'!$G$43+'前提'!$G$44,"0")&"分"&CHAR(10)&"（"&'前提'!$G$43&"＋"&'前提'!$G$44&"）" -> 60分 （25＋35） | F37: 式（言葉）
A38: ='前提'!$E$42 -> 180 | B38: 倍 | C38: ='お客様の効果'!$C$33/$C$25 -> 0.80870312 | D38: ='お客様の効果'!$D$33/$C$25 -> 1.1284166 | E38: ='お客様の効果'!$E$33/$C$25 -> 1.9371197 | F38: 年の効果÷お客様の支払い（331.68万円）
A39: ='前提'!$F$42 -> 200 | B39: 倍 | C39: ='お客様の効果'!$C$34/$C$25 -> 0.89855902 | D39: ='お客様の効果'!$D$34/$C$25 -> 1.2537962 | E39: ='お客様の効果'!$E$34/$C$25 -> 2.1523552 | F39: 年の効果÷お客様の支払い（331.68万円）
A40: ='前提'!$G$42 -> 220 | B40: 倍 | C40: ='お客様の効果'!$C$35/$C$25 -> 0.98841492 | D40: ='お客様の効果'!$D$35/$C$25 -> 1.3791759 | E40: ='お客様の効果'!$E$35/$C$25 -> 2.3675908 | F40: 年の効果÷お客様の支払い（331.68万円）
A41: ='前提'!$H$42 -> 240 | B41: 倍 | C41: ='お客様の効果'!$C$36/$C$25 -> 1.0782708 | D41: ='お客様の効果'!$D$36/$C$25 -> 1.5045555 | E41: ='お客様の効果'!$E$36/$C$25 -> 2.5828263 | F41: 年の効果÷お客様の支払い（331.68万円）
A42: 元が取れる分 使う日数 | B42: 単位 | C42: 元が取れる分 | D42: 式（言葉）
A43: ='前提'!$E$42 -> 180 | B43: 分/台/日 | C43: =$C$25/($C$12*'前提'!$E$42)*'前提'!$E$7/$C$29 -> 31.016913 | D43: 支払い÷(台数×日数)÷同じ配分での1分の人件費（削減の量には左右されない）
A44: ='前提'!$F$42 -> 200 | B44: 分/台/日 | C44: =$C$25/($C$12*'前提'!$F$42)*'前提'!$E$7/$C$29 -> 27.915222 | D44: 支払い÷(台数×日数)÷同じ配分での1分の人件費（削減の量には左右されない）
A45: ='前提'!$G$42 -> 220 | B45: 分/台/日 | C45: =$C$25/($C$12*'前提'!$G$42)*'前提'!$E$7/$C$29 -> 25.377474 | D45: 支払い÷(台数×日数)÷同じ配分での1分の人件費（削減の量には左右されない）
A46: ='前提'!$H$42 -> 240 | B46: 分/台/日 | C46: =$C$25/($C$12*'前提'!$H$42)*'前提'!$E$7/$C$29 -> 23.262685 | D46: 支払い÷(台数×日数)÷同じ配分での1分の人件費（削減の量には左右されない）
A47: 注：240日は上限に近い想定。雨天・現場の切れ目・端末を使わない日があれば、現場の稼働日数に合わせて減る。日数が減ると効果は比例して減り、元が取れる分は増える。25分と60分の内訳は tora_v2.js の感度表と同じ（10＋15、25＋35）。
A48: 手戻りの削減（参考：計画にも提案の金額にも入れない）
A49: 手戻りの削減（参考） | B49: 万円/年 | C49: ='前提'!$E$37*'前提'!$E$38*'前提'!$E$39*'前提'!$E$40 -> 360 | D49: 完成工事高30億円×手戻り2%×対象工種30%×削減20%
A50: 手戻りを足した場合の倍率（参考） | B50: 倍 | C50: =($C$14+$C$49)/$C$25 -> 2.589939 | D50: (お客様の効果＋手戻り)÷支払い
A51: 注：手戻り率は各社の現場事情で大きく違い、検証の費用も見合わない可能性があるため、計画にも提案の金額にも入れない。
A52: 注：「月6.5時間（書類電子化の実績）」は原典を確認できておらず、ARグラスの効果とも違うので使わない。

Sheet 値段と原価
A1: 値段と原価：1拠点300万円、原価84万円、粗利216万円（72%）
A2: 1台の原価は、クラウド・AIの公表単価から積み上げて検算した。計画の数字は tora_v2.js の CLOUD の値（モデルの値）を使い、検算の値と並べる（計算詳細版 p.9〜12）。
A3: 項目 | B3: 単位 | C3: 値 | F3: 式（言葉）
A4: 1拠点の売上（年）
A5: 基盤（値段の倍率を反映） | B5: 万円/年/拠点 | C5: ='前提'!$E$23*'前提'!$E$139 -> 60 | D5: 月5万円×12×値段の倍率
A6: 端末ライセンス1台（値段の倍率を反映） | B6: 万円/年/台 | C6: ='前提'!$E$24*'前提'!$E$139 -> 24 | D6: 月2万円×12×値段の倍率
A7: 1拠点の台数 | B7: 台/拠点 | C7: ='前提'!$E$21 -> 10 | D7: 前提2-1
A8: 1拠点の利用料 | B8: 万円/年/拠点 | C8: =$C$5+$C$6*$C$7 -> 300 | D8: 基盤60＋端末24×10台
A9: 参考：値段の倍率を掛ける前の1拠点の利用料 | B9: 万円/年/拠点 | C9: ='前提'!$E$23+'前提'!$E$24*$C$7 -> 300 | D9: 市場規模の計算に使う
A10: 1拠点の原価と粗利（年）
A11: 1台の原価（年） | B11: 万円/年/台 | C11: ='値段と原価'!$D$41*'前提'!$E$6/'前提'!$E$7 -> 7.2 | D11: 6,000円×12か月÷10,000（6,000円は下の内訳の合計）
A12: 1台の原価（原価の倍率を反映） | B12: 万円/年/台 | C12: =$C$11*'前提'!$E$141 -> 7.2 | D12: 1台の原価×原価の倍率（前提8-3）
A13: データ基盤 | B13: 万円/年/拠点 | C13: ='前提'!$E$74 -> 12 | D13: 月1万円×12
A14: 1拠点の原価 | B14: 万円/年/拠点 | C14: =$C$13+$C$12*$C$7 -> 84 | D14: データ基盤12＋1台7.2×10台
A15: 1拠点の粗利 | B15: 万円/年/拠点 | C15: =$C$8-$C$14 -> 216 | D15: 1拠点の利用料−1拠点の原価
A16: 粗利率（利用料） | B16: 割合 | C16: =$C$15/$C$8 -> 0.72 | D16: 1拠点の粗利÷1拠点の利用料
A17: 粗利率と台数・使い方（1拠点）
A18: 台数 | B18: 単位 | C18: 1拠点の利用料 （万円/年） | D18: ="粗利率"&CHAR(10)&"大事な場面だけ"&CHAR(10)&"月"&TEXT('値段と原価'!$D$41,"#,##0")&"円/台" -> 粗利率 大事な場面だけ 月6,000円/台 | E18: ="粗利率"&CHAR(10)&"全編を毎秒解析"&CHAR(10)&"月"&TEXT('前提'!$E$72,"#,##0")&"円/台" -> 粗利率 全編を毎秒解析 月50,000円/台 | F18: 式（言葉）
A19: ='前提'!$E$80 -> 5 | B19: 万円/年・割合 | C19: =$C$5+$C$6*'前提'!$E$80 -> 180 | D19: =1-($C$13+$C$12*'前提'!$E$80)/($C$5+$C$6*'前提'!$E$80) -> 0.73333333 | E19: =1-($C$13+'前提'!$E$72*'前提'!$E$6/'前提'!$E$7*'前提'!$E$80)/($C$5+$C$6*'前提'!$E$80) -> -0.73333333 | F19: 1−(データ基盤＋1台の原価×台数)÷(基盤＋端末×台数)
A20: ='前提'!$F$80 -> 10 | B20: 万円/年・割合 | C20: =$C$5+$C$6*'前提'!$F$80 -> 300 | D20: =1-($C$13+$C$12*'前提'!$F$80)/($C$5+$C$6*'前提'!$F$80) -> 0.72 | E20: =1-($C$13+'前提'!$E$72*'前提'!$E$6/'前提'!$E$7*'前提'!$F$80)/($C$5+$C$6*'前提'!$F$80) -> -1.04 | F20: 1−(データ基盤＋1台の原価×台数)÷(基盤＋端末×台数)
A21: ='前提'!$G$80 -> 25 | B21: 万円/年・割合 | C21: =$C$5+$C$6*'前提'!$G$80 -> 660 | D21: =1-($C$13+$C$12*'前提'!$G$80)/($C$5+$C$6*'前提'!$G$80) -> 0.70909091 | E21: =1-($C$13+'前提'!$E$72*'前提'!$E$6/'前提'!$E$7*'前提'!$G$80)/($C$5+$C$6*'前提'!$G$80) -> -1.2909091 | F21: 1−(データ基盤＋1台の原価×台数)÷(基盤＋端末×台数)
A22: 注：1台の値段（月2万円）が1台の原価（月0.6万円）を賄うので、台数が増えても粗利率はほぼ同じ。全編を送ると台数が増えるほど赤字が膨らむ。
A23: 1台の原価の内訳（円/台/月）
A24: 項目 | B24: 単位 | C24: 検算の値 | D24: モデルの値 （tora_v2.js） | E24: 差 モデル−検算 | F24: 式（言葉）
A25: 音声：録画の分数 | B25: 分/台/月 | C25: ='前提'!$E$47*'前提'!$E$48*'前提'!$E$5 -> 4800 | F25: 1日4時間×月20日×60分＝80時間
A26: 音声の文字起こし | B26: 円/台/月 | C26: =$C$25*'前提'!$E$49*'前提'!$E$46 -> 2160 | D26: ='前提'!$E$67 -> 2200 | E26: =$D$26-$C$26 -> 40 | F26: 4,800分×$0.003×150円。削減時間（35分）とは関係なく、録画した時間に掛かる
A27: 画像：1枚の画像のトークン | B27: トークン/枚 | C27: ='前提'!$E$52*'前提'!$E$53/'前提'!$E$54 -> 1228.8 | F27: 1280×720÷750
A28: 画像：1枚の入力トークン | B28: トークン/枚 | C28: =$C$27+'前提'!$E$55 -> 1528.8 | F28: 画像＋指示文300
A29: 画像解析 Claude Haiku 5.5：1枚 | B29: 円/枚 | C29: =($C$28*'前提'!$E$57+'前提'!$E$56*'前提'!$E$58)/'前提'!$E$10*'前提'!$E$46 -> 0.034182 | F29: (入力×$0.10＋出力150×$0.50)÷100万×150円
A30: 画像解析 Claude Haiku 5.5：月 | B30: 円/台/月 | C30: =$C$29*'前提'!$E$50 -> 102.546 | F30: 1枚×3,000枚
A31: 画像解析 Claude Sonnet 5.5：1枚 | B31: 円/枚 | C31: =($C$28*'前提'!$E$59+'前提'!$E$56*'前提'!$E$60)/'前提'!$E$10*'前提'!$E$46 -> 0.68364 | F31: (入力×$2＋出力150×$10)÷100万×150円
A32: 画像解析 Claude Sonnet 5.5：月 | B32: 円/台/月 | C32: =$C$31*'前提'!$E$50 -> 2050.92 | F32: 1枚×3,000枚
A33: 画像解析 モデルの置き方：1枚 | B33: 円/枚 | C33: ='前提'!$E$68/'前提'!$E$50 -> 0.33333333 | F33: 月1,000円÷3,000枚（1枚約1,000トークンとして置いた値）
A34: 画像解析（大事な場面 月3,000枚） | B34: 円/台/月 | D34: ='前提'!$E$68 -> 1000 | F34: モデルの1,000円は Haiku 5.5（約100円）と Sonnet 5.5（約2,050円）の間
A35: 全部を Sonnet 5.5 にした場合の増え方 | B35: 円/台/月 | C35: =$C$32-'前提'!$E$68 -> 1050.92 | F35: Sonnet 5.5 の月額−モデルの1,000円
A36: 報告書：1件の費用（Sonnet 5.5） | B36: 円/件 | C36: =('前提'!$E$62*'前提'!$E$59+'前提'!$E$63*'前提'!$E$60)/'前提'!$E$10*'前提'!$E$46 -> 9 | F36: (入力2万×$2＋出力2千×$10)÷100万×150円
A37: 報告書の生成 | B37: 円/台/月 | C37: =$C$36*'前提'!$E$61*'前提'!$E$48 -> 180 | D37: ='前提'!$E$69 -> 200 | E37: =$D$37-$C$37 -> 20 | F37: 1件×1日1件×20日
A38: 保存：3年間の平均の保管量 | B38: GB/台 | C38: ='前提'!$E$64*'前提'!$E$65/2 -> 180 | F38: 月10GB×36か月÷2（直線で増える量の平均）
A39: 動画の保存 | B39: 円/台/月 | C39: =$C$38*'前提'!$E$66*'前提'!$E$46 -> 675 | D39: ='前提'!$E$70 -> 700 | E39: =$D$39-$C$39 -> 25 | F39: 平均180GB×$0.025×150円
A40: 転送・監視・バックアップ・端末管理（MDM）・余裕 | B40: 円/台/月 | D40: ='前提'!$E$71 -> 1900 | F40: 見積（内訳の検算はしていない）
A41: 合計（計画で使う値） | B41: 円/台/月 | D41: ='値段と原価'!$D$26+'値段と原価'!$D$34+'値段と原価'!$D$37+'値段と原価'!$D$39+'値段と原価'!$D$40 -> 6000 | F41: 文字起こし＋画像解析＋報告書＋保存＋転送など（モデルの値の合計）
A42: 参考：検算の合計（画像は Haiku 5.5） | B42: 円/台/月 | C42: =$C$26+$C$30+$C$37+$C$39+'前提'!$E$71 -> 5017.546 | F42: 検算の値の合計（転送などはモデルの値）
A43: 参考：検算の合計（画像は Sonnet 5.5） | B43: 円/台/月 | C43: =$C$26+$C$32+$C$37+$C$39+'前提'!$E$71 -> 6965.92 | F43: 同上
A44: 広い原価で見た粗利率（5年目）
A45: 5年目の売上 | B45: 万円/年 | C45: ='拠点と売上'!$G$22 -> 26900 | D45: 拠点と売上
A46: 5年目の原価（今の分類） | B46: 万円/年 | C46: ='損益と現金'!$G$13 -> 10704.333 | D46: 利用料の原価＋導入支援の原価＋個社設定の人件費
A47: 5年目の粗利（今の分類） | B47: 万円/年 | C47: ='損益と現金'!$G$16 -> 16195.667 | D47: 売上−原価
A48: 粗利率（今の分類） | B48: 割合 | C48: =$C$47/$C$45 -> 0.60206939 | D48: 粗利÷売上
A49: 導入コンサルタントの人件費 | B49: 万円/年 | C49: ='体制と人件費'!$G$28 -> 5760 | D49: 8人×600万円×1.2（体制と人件費。計画の人数・年収）
A50: うち導入支援と個社設定へ振り替えた分 | B50: 万円/年 | C50: ='損益と現金'!$G$21 -> 4791.3333 | D50: 損益と現金の振替
A51: 振り替えていない分（定着支援・サポート） | B51: 万円/年 | C51: =$C$49-$C$50 -> 968.66667 | D51: 導入後の定着支援と問い合わせ対応の時間
A52: 現場監修の人件費（ラベル付け・品質の確認） | B52: 万円/年 | C52: ='体制と人件費'!$G$27 -> 1560 | D52: 2人×650万円×1.2
A53: 原価へ移す額 | B53: 万円/年 | C53: =$C$51+$C$52 -> 2528.6667 | D53: 振り替えていない分＋現場監修
A54: 広い原価での粗利 | B54: 万円/年 | C54: =$C$47-$C$53 -> 13667 | D54: 粗利−原価へ移す額
A55: 広い原価での粗利率 | B55: 割合 | C55: =$C$54/$C$45 -> 0.50806691 | D55: SaaS の慣行どおり、定着支援・サポート・現場監修を原価に入れた場合
A56: 5年目の利用料 | B56: 万円/年 | C56: ='拠点と売上'!$G$16 -> 19350 | D56: 拠点と売上
A57: 5年目の利用料の原価 | B57: 万円/年 | C57: ='損益と現金'!$G$8 -> 5418 | D57: 損益と現金
A58: 利用料の粗利率（今の分類） | B58: 割合 | C58: =1-$C$57/$C$56 -> 0.72 | D58: 1−利用料の原価÷利用料
A59: 利用料の粗利率（広い原価） | B59: 割合 | C59: =($C$56-$C$57-$C$53)/$C$56 -> 0.58931955 | D59: 移す額をすべて利用料の原価にした場合：(利用料−利用料の原価−原価へ移す額)÷利用料
A60: 販管費（広い分類） | B60: 万円/年 | C60: ='損益と現金'!$G$25-$C$53 -> 14784 | D60: 販管費−原価へ移す額
A61: 営業利益（広い分類） | B61: 万円/年 | C61: =$C$54-$C$60 -> -1117 | D61: 広い粗利−広い販管費
A62: 今の分類の営業利益との差 | B62: 万円/年 | C62: =$C$61-'損益と現金'!$G$27 -> 0 | D62: 0になる：分類を変えても営業利益は変わらない
A63: 注：分類を変えても営業利益は変わらない。サポート（問い合わせ窓口）は導入コンサルタントが受け持つので「振り替えていない分」に含めた。人件費は計画の人数・年収（つまみを掛ける前）。
A64: 保存：4年目以降の定常（3年保存を続けた場合）
A65: 項目 | B65: 単位 | C65: 検算の値 | D65: モデルの値 （tora_v2.js） | E65: 差 モデル−検算 | F65: 式（言葉）
A66: 保存：4年目以降の定常の保管量 | B66: GB/台 | C66: ='前提'!$E$64*'前提'!$E$65 -> 360 | F66: 月10GB×36か月
A67: 保存：定常の費用 | B67: 円/台/月 | C67: =$C$66*'前提'!$E$66*'前提'!$E$46 -> 1350 | F67: 360GB×$0.025×150円
A68: 保存：定常とモデルの差（1台） | B68: 円/台/月 | C68: =$C$67-'前提'!$E$70 -> 650 | F68: 定常−モデルの700円
A69: 保存：定常での1拠点の増え方 | B69: 万円/年/拠点 | C69: =$C$68*$C$7*'前提'!$E$6/'前提'!$E$7 -> 7.8 | F69: 差×10台×12か月÷10,000
A70: 保存：定常での粗利率の下がり幅 | B70: ポイント | C70: =$C$69/$C$8 -> 0.026 | F70: 1拠点の増え方÷1拠点の利用料
A71: 注：モデルは保存を3年間の平均で置いている。定常（4年目以降）では1台 月+650円（1拠点 年+7.8万円、粗利率−2.6ポイント）になる。
A72: 解析量のプラン案（参考・計画に入れない）
A73: 標準に含む画像 | B73: 枚/台/月 | C73: ='前提'!$E$50 -> 3000 | D73: 前提4-5
A74: 標準に含む保存 | B74: GB/台/月 | C74: ='前提'!$E$64 -> 10 | D74: 前提4-19
A75: 追加1,000枚の原価（Sonnet 5.5） | B75: 円/月 | C75: =$C$31*'前提'!$E$76 -> 683.64 | D75: 1枚の Sonnet 5.5 の費用×1,000枚
A76: 追加1,000枚の原価（Haiku 5.5・参考） | B76: 円/月 | C76: =$C$29*'前提'!$E$76 -> 34.182 | D76: 1枚の Haiku 5.5 の費用×1,000枚
A77: 追加1,000枚ごとの料金 | B77: 円/台/月 | C77: =ROUND($C$75*'前提'!$E$75/'前提'!$E$78,0)*'前提'!$E$78 -> 2000 | D77: Sonnet 5.5 の原価×3を千円単位に丸める
A78: その粗利率 | B78: 割合 | C78: =1-$C$75/$C$77 -> 0.65818 | D78: 1−原価÷料金
A79: 追加10GB/月の原価（3年保存の平均） | B79: 円/月 | C79: ='前提'!$E$77*'前提'!$E$65/2*'前提'!$E$66*'前提'!$E$46 -> 675 | D79: 毎月10GB多く送り3年保存：平均180GB×$0.025×150円
A80: 追加10GB/月の原価（4年目以降の定常） | B80: 円/月 | C80: ='前提'!$E$77*'前提'!$E$65*'前提'!$E$66*'前提'!$E$46 -> 1350 | D80: 360GB×$0.025×150円
A81: 追加10GBごとの料金 | B81: 円/台/月 | C81: =ROUND($C$79*'前提'!$E$75/'前提'!$E$78,0)*'前提'!$E$78 -> 2000 | D81: 3年平均の原価×3を千円単位に丸める
A82: その粗利率（3年平均） | B82: 割合 | C82: =1-$C$79/$C$81 -> 0.6625 | D82: 1−原価÷料金
A83: その粗利率（定常） | B83: 割合 | C83: =1-$C$80/$C$81 -> 0.325 | D83: 定常でも料金が原価を上回る
A84: 注：標準は1台 月3,000枚・保存10GBまで。超えた分は1,000枚ごと・10GBごとに追加料金。追加料金は原価の約3倍で置き、計算してから千円単位に丸めた。

Sheet 導入支援
A1: 導入支援：42人日＋交通費で原価141万円、値段200万円、粗利59万円
A2: 導入支援の人件費は原価に振り替える（販管費から引く）。tora_v2.js の SETUP_TASKS・setupDays・CSDAY・setupTravel と同じ（計算詳細版 p.13）。
A3: 項目 | B3: 単位 | C3: 値 | F3: 式（言葉）
A4: 作業と人日（1拠点）
A5: 現状調査・業務の流れの整理 | B5: 人日 | C5: ='前提'!$E$82 -> 5 | D5: 前提5-1
A6: 端末の設定・アカウント・端末管理 | B6: 人日 | C6: ='前提'!$E$83 -> 3 | D6: 前提5-2
A7: 図面・手順・報告書の型の登録 | B7: 人日 | C7: ='前提'!$E$84 -> 10 | D7: 前提5-3
A8: 職長・施工管理者への研修（2回） | B8: 人日 | C8: ='前提'!$E$85 -> 4 | D8: 前提5-4
A9: 現場での立ち会い・初期の手直し（週2日×8週） | B9: 人日 | C9: ='前提'!$E$86 -> 16 | D9: 前提5-5
A10: 導入前後の効果測定レポート | B10: 人日 | C10: ='前提'!$E$87 -> 4 | D10: 前提5-6
A11: 合計（約2か月） | B11: 人日 | C11: =SUM($C$5:$C$10) -> 42 | D11: 6つの作業の合計
A12: 原価と粗利（1拠点）
A13: 導入コンサルタントの年収 | B13: 万円/年 | C13: ='前提'!$E$97 -> 600 | D13: 前提6-5（1年目の値。tora_v2.js は600を直接使う）
A14: 会社負担を含める倍率 | B14: 倍 | C14: ='前提'!$E$109 -> 1.2 | D14: 前提6-17
A15: 年間稼働日 | B15: 日/年 | C15: ='前提'!$E$89 -> 240 | D15: 前提5-8
A16: 1人日の人件費 | B16: 万円/人日 | C16: =$C$13*$C$14/$C$15 -> 3 | D16: 年収600万円×1.2÷240日
A17: 人件費 | B17: 万円/拠点 | C17: =$C$11*$C$16 -> 126 | D17: 42人日×3万円
A18: 交通費 | B18: 万円/拠点 | C18: ='前提'!$E$88 -> 15 | D18: 16回訪問×約1万円
A19: 原価 | B19: 万円/拠点 | C19: =$C$17+$C$18 -> 141 | D19: 人件費＋交通費
A20: 値段 | B20: 万円/拠点 | C20: ='前提'!$E$25 -> 200 | D20: 前提2-5
A21: 粗利 | B21: 万円/拠点 | C21: =$C$20-$C$19 -> 59 | D21: 値段−原価
A22: 粗利率 | B22: 割合 | C22: =$C$21/$C$20 -> 0.295 | D22: 粗利÷値段
A23: お客様の支払い（1拠点）
A24: お客様の1年目の支払い | B24: 万円 | C24: ='お客様の効果'!$C$21+'お客様の効果'!$C$24+$C$20 -> 531.68 | D24: 利用料300＋リース31.68＋導入支援200
A25: お客様の2年目以降の支払い | B25: 万円/年 | C25: ='お客様の効果'!$C$25 -> 331.68 | D25: 利用料300＋リース31.68
A26: そのうち当社の売上（利用料） | B26: 万円/年 | C26: ='お客様の効果'!$C$21 -> 300 | D26: 1年目は導入支援200万円も当社の売上
A27: 注：当社の売上は利用料300万円（初年度は導入支援200万円も）。リース31.7万円はお客様からリース会社へ払うもので、当社の売上ではない。
A28: 注：導入コンサルタント1人が回せる新規拠点は年6（2か月で1拠点）。新規拠点がこの上限内かは「体制と人件費」で確かめる。

Sheet 体制と人件費
A1: 体制と人件費：8つの役割×年収×人数。5年目は23人
A2: 人件費＝年収×人数×1.2（会社負担）。採用費＝増えた人数×年収×15%。tora_v2.js の team() と run() の人件費・採用費と同じ（計算詳細版 p.17）。
A3: 項目 | B3: 単位 | C3: 1 | D3: 2 | E3: 3 | F3: 4 | G3: 5 | H3: 6 | I3: 7 | J3: 8 | K3: 9 | L3: 10 | M3: 式（言葉）
A4: 年収（万円/年）
A5: 年収：代表（創業者） | B5: 万円/年 | C5: ='前提'!$E$93 -> 480 | D5: ='前提'!$F$93 -> 600 | E5: ='前提'!$G$93 -> 720 | F5: ='前提'!$H$93 -> 720 | G5: ='前提'!$I$93 -> 720 | H5: ='前提'!$J$93 -> 720 | I5: ='前提'!$K$93 -> 720 | J5: ='前提'!$L$93 -> 720 | K5: ='前提'!$M$93 -> 720 | L5: ='前提'!$N$93 -> 720 | M5: 前提6-1
A6: 年収：CTO | B6: 万円/年 | C6: ='前提'!$E$94 -> 1000 | D6: ='前提'!$F$94 -> 1000 | E6: ='前提'!$G$94 -> 1000 | F6: ='前提'!$H$94 -> 1000 | G6: ='前提'!$I$94 -> 1000 | H6: ='前提'!$J$94 -> 1000 | I6: ='前提'!$K$94 -> 1000 | J6: ='前提'!$L$94 -> 1000 | K6: ='前提'!$M$94 -> 1000 | L6: ='前提'!$N$94 -> 1000 | M6: 前提6-2
A7: 年収：エンジニア | B7: 万円/年 | C7: ='前提'!$E$95 -> 800 | D7: ='前提'!$F$95 -> 800 | E7: ='前提'!$G$95 -> 800 | F7: ='前提'!$H$95 -> 800 | G7: ='前提'!$I$95 -> 800 | H7: ='前提'!$J$95 -> 800 | I7: ='前提'!$K$95 -> 800 | J7: ='前提'!$L$95 -> 800 | K7: ='前提'!$M$95 -> 800 | L7: ='前提'!$N$95 -> 800 | M7: 前提6-3
A8: 年収：現場監修（施工管理経験者） | B8: 万円/年 | C8: ='前提'!$E$96 -> 650 | D8: ='前提'!$F$96 -> 650 | E8: ='前提'!$G$96 -> 650 | F8: ='前提'!$H$96 -> 650 | G8: ='前提'!$I$96 -> 650 | H8: ='前提'!$J$96 -> 650 | I8: ='前提'!$K$96 -> 650 | J8: ='前提'!$L$96 -> 650 | K8: ='前提'!$M$96 -> 650 | L8: ='前提'!$N$96 -> 650 | M8: 前提6-4
A9: 年収：導入コンサルタント | B9: 万円/年 | C9: ='前提'!$E$97 -> 600 | D9: ='前提'!$F$97 -> 600 | E9: ='前提'!$G$97 -> 600 | F9: ='前提'!$H$97 -> 600 | G9: ='前提'!$I$97 -> 600 | H9: ='前提'!$J$97 -> 600 | I9: ='前提'!$K$97 -> 600 | J9: ='前提'!$L$97 -> 600 | K9: ='前提'!$M$97 -> 600 | L9: ='前提'!$N$97 -> 600 | M9: 前提6-5
A10: 年収：営業（技術営業） | B10: 万円/年 | C10: ='前提'!$E$98 -> 650 | D10: ='前提'!$F$98 -> 650 | E10: ='前提'!$G$98 -> 650 | F10: ='前提'!$H$98 -> 650 | G10: ='前提'!$I$98 -> 650 | H10: ='前提'!$J$98 -> 650 | I10: ='前提'!$K$98 -> 650 | J10: ='前提'!$L$98 -> 650 | K10: ='前提'!$M$98 -> 650 | L10: ='前提'!$N$98 -> 650 | M10: 前提6-6
A11: 年収：管理（人事・経理・総務） | B11: 万円/年 | C11: ='前提'!$E$99 -> 550 | D11: ='前提'!$F$99 -> 550 | E11: ='前提'!$G$99 -> 550 | F11: ='前提'!$H$99 -> 550 | G11: ='前提'!$I$99 -> 550 | H11: ='前提'!$J$99 -> 550 | I11: ='前提'!$K$99 -> 550 | J11: ='前提'!$L$99 -> 550 | K11: ='前提'!$M$99 -> 550 | L11: ='前提'!$N$99 -> 550 | M11: 前提6-7
A12: 年収：戦略企画 | B12: 万円/年 | C12: ='前提'!$E$100 -> 700 | D12: ='前提'!$F$100 -> 700 | E12: ='前提'!$G$100 -> 700 | F12: ='前提'!$H$100 -> 700 | G12: ='前提'!$I$100 -> 700 | H12: ='前提'!$J$100 -> 700 | I12: ='前提'!$K$100 -> 700 | J12: ='前提'!$L$100 -> 700 | K12: ='前提'!$M$100 -> 700 | L12: ='前提'!$N$100 -> 700 | M12: 前提6-8
A13: 人数（期末）
A14: 人数：代表（創業者） | B14: 人 | C14: ='前提'!$E$101 -> 1 | D14: ='前提'!$F$101 -> 1 | E14: ='前提'!$G$101 -> 1 | F14: ='前提'!$H$101 -> 1 | G14: ='前提'!$I$101 -> 1 | H14: ='前提'!$J$101 -> 1 | I14: ='前提'!$K$101 -> 1 | J14: ='前提'!$L$101 -> 1 | K14: ='前提'!$M$101 -> 1 | L14: ='前提'!$N$101 -> 1 | M14: 前提6-9
A15: 人数：CTO | B15: 人 | C15: ='前提'!$E$102 -> 1 | D15: ='前提'!$F$102 -> 1 | E15: ='前提'!$G$102 -> 1 | F15: ='前提'!$H$102 -> 1 | G15: ='前提'!$I$102 -> 1 | H15: ='前提'!$J$102 -> 1 | I15: ='前提'!$K$102 -> 1 | J15: ='前提'!$L$102 -> 1 | K15: ='前提'!$M$102 -> 1 | L15: ='前提'!$N$102 -> 1 | M15: 前提6-10
A16: 人数：エンジニア | B16: 人 | C16: ='前提'!$E$103 -> 1 | D16: ='前提'!$F$103 -> 2 | E16: ='前提'!$G$103 -> 3 | F16: ='前提'!$H$103 -> 4 | G16: ='前提'!$I$103 -> 5 | H16: ='前提'!$J$103 -> 6 | I16: ='前提'!$K$103 -> 6 | J16: ='前提'!$L$103 -> 7 | K16: ='前提'!$M$103 -> 7 | L16: ='前提'!$N$103 -> 8 | M16: 前提6-11
A17: 人数：現場監修（施工管理経験者） | B17: 人 | C17: ='前提'!$E$104 -> 1 | D17: ='前提'!$F$104 -> 1 | E17: ='前提'!$G$104 -> 1 | F17: ='前提'!$H$104 -> 1 | G17: ='前提'!$I$104 -> 2 | H17: ='前提'!$J$104 -> 2 | I17: ='前提'!$K$104 -> 3 | J17: ='前提'!$L$104 -> 3 | K17: ='前提'!$M$104 -> 3 | L17: ='前提'!$N$104 -> 4 | M17: 前提6-12
A18: 人数：導入コンサルタント | B18: 人 | C18: ='前提'!$E$105 -> 1 | D18: ='前提'!$F$105 -> 2 | E18: ='前提'!$G$105 -> 4 | F18: ='前提'!$H$105 -> 6 | G18: ='前提'!$I$105 -> 8 | H18: ='前提'!$J$105 -> 8 | I18: ='前提'!$K$105 -> 9 | J18: ='前提'!$L$105 -> 9 | K18: ='前提'!$M$105 -> 9 | L18: ='前提'!$N$105 -> 9 | M18: 前提6-13
A19: 人数：営業（技術営業） | B19: 人 | C19: ='前提'!$E$106 -> 0 | D19: ='前提'!$F$106 -> 1 | E19: ='前提'!$G$106 -> 1 | F19: ='前提'!$H$106 -> 3 | G19: ='前提'!$I$106 -> 3 | H19: ='前提'!$J$106 -> 3 | I19: ='前提'!$K$106 -> 4 | J19: ='前提'!$L$106 -> 4 | K19: ='前提'!$M$106 -> 4 | L19: ='前提'!$N$106 -> 4 | M19: 前提6-14
A20: 人数：管理（人事・経理・総務） | B20: 人 | C20: ='前提'!$E$107 -> 0 | D20: ='前提'!$F$107 -> 0 | E20: ='前提'!$G$107 -> 1 | F20: ='前提'!$H$107 -> 1 | G20: ='前提'!$I$107 -> 2 | H20: ='前提'!$J$107 -> 2 | I20: ='前提'!$K$107 -> 2 | J20: ='前提'!$L$107 -> 3 | K20: ='前提'!$M$107 -> 3 | L20: ='前提'!$N$107 -> 3 | M20: 前提6-15
A21: 人数：戦略企画 | B21: 人 | C21: ='前提'!$E$108 -> 0 | D21: ='前提'!$F$108 -> 0 | E21: ='前提'!$G$108 -> 0 | F21: ='前提'!$H$108 -> 1 | G21: ='前提'!$I$108 -> 1 | H21: ='前提'!$J$108 -> 1 | I21: ='前提'!$K$108 -> 1 | J21: ='前提'!$L$108 -> 1 | K21: ='前提'!$M$108 -> 2 | L21: ='前提'!$N$108 -> 2 | M21: 前提6-16
A22: 計画の社員数 | B22: 人 | C22: =SUM(C14:C21) -> 5 | D22: =SUM(D14:D21) -> 8 | E22: =SUM(E14:E21) -> 12 | F22: =SUM(F14:F21) -> 18 | G22: =SUM(G14:G21) -> 23 | H22: =SUM(H14:H21) -> 24 | I22: =SUM(I14:I21) -> 27 | J22: =SUM(J14:J21) -> 29 | ... L22: =SUM(L14:L21) -> 32 | M22: 8つの役割の合計
A23: 人件費（年収×人数×会社負担）
A24: 人件費：代表（創業者） | B24: 万円/年 | C24: =$C$5*$C$14*'前提'!$E$109 -> 576 | D24: =$D$5*$D$14*'前提'!$E$109 -> 720 | E24: =$E$5*$E$14*'前提'!$E$109 -> 864 | F24: =$F$5*$F$14*'前提'!$E$109 -> 864 | G24: =$G$5*$G$14*'前提'!$E$109 -> 864 | H24: =$H$5*$H$14*'前提'!$E$109 -> 864 | I24: =$I$5*$I$14*'前提'!$E$109 -> 864 | J24: =$J$5*$J$14*'前提'!$E$109 -> 864 | K24: =$K$5*$K$14*'前提'!$E$109 -> 864 | L24: =$L$5*$L$14*'前提'!$E$109 -> 864 | M24: 年収×人数×1.2
A25: 人件費：CTO | B25: 万円/年 | C25: =$C$6*$C$15*'前提'!$E$109 -> 1200 | D25: =$D$6*$D$15*'前提'!$E$109 -> 1200 | E25: =$E$6*$E$15*'前提'!$E$109 -> 1200 | F25: =$F$6*$F$15*'前提'!$E$109 -> 1200 | G25: =$G$6*$G$15*'前提'!$E$109 -> 1200 | H25: =$H$6*$H$15*'前提'!$E$109 -> 1200 | I25: =$I$6*$I$15*'前提'!$E$109 -> 1200 | J25: =$J$6*$J$15*'前提'!$E$109 -> 1200 | K25: =$K$6*$K$15*'前提'!$E$109 -> 1200 | L25: =$L$6*$L$15*'前提'!$E$109 -> 1200 | M25: 年収×人数×1.2
A26: 人件費：エンジニア | B26: 万円/年 | C26: =$C$7*$C$16*'前提'!$E$109 -> 960 | D26: =$D$7*$D$16*'前提'!$E$109 -> 1920 | E26: =$E$7*$E$16*'前提'!$E$109 -> 2880 | F26: =$F$7*$F$16*'前提'!$E$109 -> 3840 | G26: =$G$7*$G$16*'前提'!$E$109 -> 4800 | H26: =$H$7*$H$16*'前提'!$E$109 -> 5760 | I26: =$I$7*$I$16*'前提'!$E$109 -> 5760 | J26: =$J$7*$J$16*'前提'!$E$109 -> 6720 | K26: =$K$7*$K$16*'前提'!$E$109 -> 6720 | L26: =$L$7*$L$16*'前提'!$E$109 -> 7680 | M26: 年収×人数×1.2
A27: 人件費：現場監修（施工管理経験者） | B27: 万円/年 | C27: =$C$8*$C$17*'前提'!$E$109 -> 780 | D27: =$D$8*$D$17*'前提'!$E$109 -> 780 | E27: =$E$8*$E$17*'前提'!$E$109 -> 780 | F27: =$F$8*$F$17*'前提'!$E$109 -> 780 | G27: =$G$8*$G$17*'前提'!$E$109 -> 1560 | H27: =$H$8*$H$17*'前提'!$E$109 -> 1560 | I27: =$I$8*$I$17*'前提'!$E$109 -> 2340 | J27: =$J$8*$J$17*'前提'!$E$109 -> 2340 | K27: =$K$8*$K$17*'前提'!$E$109 -> 2340 | L27: =$L$8*$L$17*'前提'!$E$109 -> 3120 | M27: 年収×人数×1.2
A28: 人件費：導入コンサルタント | B28: 万円/年 | C28: =$C$9*$C$18*'前提'!$E$109 -> 720 | D28: =$D$9*$D$18*'前提'!$E$109 -> 1440 | E28: =$E$9*$E$18*'前提'!$E$109 -> 2880 | F28: =$F$9*$F$18*'前提'!$E$109 -> 4320 | G28: =$G$9*$G$18*'前提'!$E$109 -> 5760 | H28: =$H$9*$H$18*'前提'!$E$109 -> 5760 | I28: =$I$9*$I$18*'前提'!$E$109 -> 6480 | J28: =$J$9*$J$18*'前提'!$E$109 -> 6480 | K28: =$K$9*$K$18*'前提'!$E$109 -> 6480 | L28: =$L$9*$L$18*'前提'!$E$109 -> 6480 | M28: 年収×人数×1.2
A29: 人件費：営業（技術営業） | B29: 万円/年 | C29: =$C$10*$C$19*'前提'!$E$109 -> 0 | D29: =$D$10*$D$19*'前提'!$E$109 -> 780 | E29: =$E$10*$E$19*'前提'!$E$109 -> 780 | F29: =$F$10*$F$19*'前提'!$E$109 -> 2340 | G29: =$G$10*$G$19*'前提'!$E$109 -> 2340 | H29: =$H$10*$H$19*'前提'!$E$109 -> 2340 | I29: =$I$10*$I$19*'前提'!$E$109 -> 3120 | J29: =$J$10*$J$19*'前提'!$E$109 -> 3120 | K29: =$K$10*$K$19*'前提'!$E$109 -> 3120 | L29: =$L$10*$L$19*'前提'!$E$109 -> 3120 | M29: 年収×人数×1.2
A30: 人件費：管理（人事・経理・総務） | B30: 万円/年 | C30: =$C$11*$C$20*'前提'!$E$109 -> 0 | D30: =$D$11*$D$20*'前提'!$E$109 -> 0 | E30: =$E$11*$E$20*'前提'!$E$109 -> 660 | F30: =$F$11*$F$20*'前提'!$E$109 -> 660 | G30: =$G$11*$G$20*'前提'!$E$109 -> 1320 | H30: =$H$11*$H$20*'前提'!$E$109 -> 1320 | I30: =$I$11*$I$20*'前提'!$E$109 -> 1320 | J30: =$J$11*$J$20*'前提'!$E$109 -> 1980 | K30: =$K$11*$K$20*'前提'!$E$109 -> 1980 | L30: =$L$11*$L$20*'前提'!$E$109 -> 1980 | M30: 年収×人数×1.2
A31: 人件費：戦略企画 | B31: 万円/年 | C31: =$C$12*$C$21*'前提'!$E$109 -> 0 | D31: =$D$12*$D$21*'前提'!$E$109 -> 0 | E31: =$E$12*$E$21*'前提'!$E$109 -> 0 | F31: =$F$12*$F$21*'前提'!$E$109 -> 840 | G31: =$G$12*$G$21*'前提'!$E$109 -> 840 | H31: =$H$12*$H$21*'前提'!$E$109 -> 840 | I31: =$I$12*$I$21*'前提'!$E$109 -> 840 | J31: =$J$12*$J$21*'前提'!$E$109 -> 840 | K31: =$K$12*$K$21*'前提'!$E$109 -> 1680 | L31: =$L$12*$L$21*'前提'!$E$109 -> 1680 | M31: 年収×人数×1.2
A32: 人件費の合計（計画） | B32: 万円/年 | C32: =SUM(C24:C31) -> 4236 | D32: =SUM(D24:D31) -> 6840 | E32: =SUM(E24:E31) -> 10044 | F32: =SUM(F24:F31) -> 14844 | G32: =SUM(G24:G31) -> 18684 | H32: =SUM(H24:H31) -> 19644 | I32: =SUM(I24:I31) -> 21924 | J32: =SUM(J24:J31) -> 23544 | ... L32: =SUM(L24:L31) -> 26124 | M32: 8つの役割の合計
A33: 採用費（増えた人の年収×採用費率）
A34: 増員：代表（創業者） | B34: 人 | C34: =$C$14 -> 1 | D34: =MAX(0,$D$14-$C$14) -> 0 | E34: =MAX(0,$E$14-$D$14) -> 0 | F34: =MAX(0,$F$14-$E$14) -> 0 | G34: =MAX(0,$G$14-$F$14) -> 0 | H34: =MAX(0,$H$14-$G$14) -> 0 | I34: =MAX(0,$I$14-$H$14) -> 0 | J34: =MAX(0,$J$14-$I$14) -> 0 | K34: =MAX(0,$K$14-$J$14) -> 0 | L34: =MAX(0,$L$14-$K$14) -> 0 | M34: その年の人数−前の年の人数（減ったときは0）。1年目は開業時0人から
A35: 増員：CTO | B35: 人 | C35: =$C$15 -> 1 | D35: =MAX(0,$D$15-$C$15) -> 0 | E35: =MAX(0,$E$15-$D$15) -> 0 | F35: =MAX(0,$F$15-$E$15) -> 0 | G35: =MAX(0,$G$15-$F$15) -> 0 | H35: =MAX(0,$H$15-$G$15) -> 0 | I35: =MAX(0,$I$15-$H$15) -> 0 | J35: =MAX(0,$J$15-$I$15) -> 0 | K35: =MAX(0,$K$15-$J$15) -> 0 | L35: =MAX(0,$L$15-$K$15) -> 0 | M35: その年の人数−前の年の人数（減ったときは0）。1年目は開業時0人から
A36: 増員：エンジニア | B36: 人 | C36: =$C$16 -> 1 | D36: =MAX(0,$D$16-$C$16) -> 1 | E36: =MAX(0,$E$16-$D$16) -> 1 | F36: =MAX(0,$F$16-$E$16) -> 1 | G36: =MAX(0,$G$16-$F$16) -> 1 | H36: =MAX(0,$H$16-$G$16) -> 1 | I36: =MAX(0,$I$16-$H$16) -> 0 | J36: =MAX(0,$J$16-$I$16) -> 1 | K36: =MAX(0,$K$16-$J$16) -> 0 | L36: =MAX(0,$L$16-$K$16) -> 1 | M36: その年の人数−前の年の人数（減ったときは0）。1年目は開業時0人から
A37: 増員：現場監修（施工管理経験者） | B37: 人 | C37: =$C$17 -> 1 | D37: =MAX(0,$D$17-$C$17) -> 0 | E37: =MAX(0,$E$17-$D$17) -> 0 | F37: =MAX(0,$F$17-$E$17) -> 0 | G37: =MAX(0,$G$17-$F$17) -> 1 | H37: =MAX(0,$H$17-$G$17) -> 0 | I37: =MAX(0,$I$17-$H$17) -> 1 | J37: =MAX(0,$J$17-$I$17) -> 0 | K37: =MAX(0,$K$17-$J$17) -> 0 | L37: =MAX(0,$L$17-$K$17) -> 1 | M37: その年の人数−前の年の人数（減ったときは0）。1年目は開業時0人から
A38: 増員：導入コンサルタント | B38: 人 | C38: =$C$18 -> 1 | D38: =MAX(0,$D$18-$C$18) -> 1 | E38: =MAX(0,$E$18-$D$18) -> 2 | F38: =MAX(0,$F$18-$E$18) -> 2 | G38: =MAX(0,$G$18-$F$18) -> 2 | H38: =MAX(0,$H$18-$G$18) -> 0 | I38: =MAX(0,$I$18-$H$18) -> 1 | J38: =MAX(0,$J$18-$I$18) -> 0 | K38: =MAX(0,$K$18-$J$18) -> 0 | L38: =MAX(0,$L$18-$K$18) -> 0 | M38: その年の人数−前の年の人数（減ったときは0）。1年目は開業時0人から
A39: 増員：営業（技術営業） | B39: 人 | C39: =$C$19 -> 0 | D39: =MAX(0,$D$19-$C$19) -> 1 | E39: =MAX(0,$E$19-$D$19) -> 0 | F39: =MAX(0,$F$19-$E$19) -> 2 | G39: =MAX(0,$G$19-$F$19) -> 0 | H39: =MAX(0,$H$19-$G$19) -> 0 | I39: =MAX(0,$I$19-$H$19) -> 1 | J39: =MAX(0,$J$19-$I$19) -> 0 | K39: =MAX(0,$K$19-$J$19) -> 0 | L39: =MAX(0,$L$19-$K$19) -> 0 | M39: その年の人数−前の年の人数（減ったときは0）。1年目は開業時0人から
A40: 増員：管理（人事・経理・総務） | B40: 人 | C40: =$C$20 -> 0 | D40: =MAX(0,$D$20-$C$20) -> 0 | E40: =MAX(0,$E$20-$D$20) -> 1 | F40: =MAX(0,$F$20-$E$20) -> 0 | G40: =MAX(0,$G$20-$F$20) -> 1 | H40: =MAX(0,$H$20-$G$20) -> 0 | I40: =MAX(0,$I$20-$H$20) -> 0 | J40: =MAX(0,$J$20-$I$20) -> 1 | K40: =MAX(0,$K$20-$J$20) -> 0 | L40: =MAX(0,$L$20-$K$20) -> 0 | M40: その年の人数−前の年の人数（減ったときは0）。1年目は開業時0人から
A41: 増員：戦略企画 | B41: 人 | C41: =$C$21 -> 0 | D41: =MAX(0,$D$21-$C$21) -> 0 | E41: =MAX(0,$E$21-$D$21) -> 0 | F41: =MAX(0,$F$21-$E$21) -> 1 | G41: =MAX(0,$G$21-$F$21) -> 0 | H41: =MAX(0,$H$21-$G$21) -> 0 | I41: =MAX(0,$I$21-$H$21) -> 0 | J41: =MAX(0,$J$21-$I$21) -> 0 | K41: =MAX(0,$K$21-$J$21) -> 1 | L41: =MAX(0,$L$21-$K$21) -> 0 | M41: その年の人数−前の年の人数（減ったときは0）。1年目は開業時0人から
A42: 増員×年収の合計 | B42: 万円/年 | C42: =SUMPRODUCT(C34:C41,C5:C12) -> 3530 | D42: =SUMPRODUCT(D34:D41,D5:D12) -> 2050 | E42: =SUMPRODUCT(E34:E41,E5:E12) -> 2550 | F42: =SUMPRODUCT(F34:F41,F5:F12) -> 4000 | G42: =SUMPRODUCT(G34:G41,G5:G12) -> 3200 | H42: =SUMPRODUCT(H34:H41,H5:H12) -> 800 | I42: =SUMPRODUCT(I34:I41,I5:I12) -> 1900 | J42: =SUMPRODUCT(J34:J41,J5:J12) -> 1350 | ... L42: =SUMPRODUCT(L34:L41,L5:L12) -> 1450 | M42: 役割ごとの増員×その年の年収を足す
A43: 採用費（計画） | B43: 万円/年 | C43: =$C$42*'前提'!$E$112 -> 529.5 | D43: =$D$42*'前提'!$E$112 -> 307.5 | E43: =$E$42*'前提'!$E$112 -> 382.5 | F43: =$F$42*'前提'!$E$112 -> 600 | G43: =$G$42*'前提'!$E$112 -> 480 | H43: =$H$42*'前提'!$E$112 -> 120 | I43: =$I$42*'前提'!$E$112 -> 285 | J43: =$J$42*'前提'!$E$112 -> 202.5 | K43: =$K$42*'前提'!$E$112 -> 105 | L43: =$L$42*'前提'!$E$112 -> 217.5 | M43: 増員×年収の合計×15%
A44: つまみの反映（初期値なら計画のまま）
A45: 年収の上乗せ分 | B45: 万円/年 | C45: ='前提'!$E$142*'前提'!$E$109*$C$22 -> 0 | D45: ='前提'!$E$142*'前提'!$E$109*$D$22 -> 0 | E45: ='前提'!$E$142*'前提'!$E$109*$E$22 -> 0 | F45: ='前提'!$E$142*'前提'!$E$109*$F$22 -> 0 | G45: ='前提'!$E$142*'前提'!$E$109*$G$22 -> 0 | H45: ='前提'!$E$142*'前提'!$E$109*$H$22 -> 0 | I45: ='前提'!$E$142*'前提'!$E$109*$I$22 -> 0 | J45: ='前提'!$E$142*'前提'!$E$109*$J$22 -> 0 | K45: ='前提'!$E$142*'前提'!$E$109*$K$22 -> 0 | L45: ='前提'!$E$142*'前提'!$E$109*$L$22 -> 0 | M45: 上乗せ×1.2×計画の社員数（前提8-4）
A46: 社員数（採用連動の後） | B46: 人 | C46: =IF(ISBLANK('前提'!$E$143),$C$22,'前提'!$E$144+ROUND(($C$22-'前提'!$E$144)*'前提'!$E$143,0)) -> 5 | D46: =IF(ISBLANK('前提'!$E$143),$D$22,'前提'!$E$144+ROUND(($D$22-'前提'!$E$144)*'前提'!$E$143,0)) -> 8 | E46: =IF(ISBLANK('前提'!$E$143),$E$22,'前提'!$E$144+ROUND(($E$22-'前提'!$E$144)*'前提'!$E$143,0)) -> 12 | F46: =IF(ISBLANK('前提'!$E$143),$F$22,'前提'!$E$144+ROUND(($F$22-'前提'!$E$144)*'前提'!$E$143,0)) -> 18 | G46: =IF(ISBLANK('前提'!$E$143),$G$22,'前提'!$E$144+ROUND(($G$22-'前提'!$E$144)*'前提'!$E$143,0)) -> 23 | H46: =IF(ISBLANK('前提'!$E$143),$H$22,'前提'!$E$144+ROUND(($H$22-'前提'!$E$144)*'前提'!$E$143,0)) -> 24 | I46: =IF(ISBLANK('前提'!$E$143),$I$22,'前提'!$E$144+ROUND(($I$22-'前提'!$E$144)*'前提'!$E$143,0)) -> 27 | J46: =IF(ISBLANK('前提'!$E$143),$J$22,'前提'!$E$144+ROUND(($J$22-'前提'!$E$144)*'前提'!$E$143,0)) -> 29 | K46: =IF(ISBLANK('前提'!$E$143),$K$22,'前提'!$E$144+ROUND(($K$22-'前提'!$E$144)*'前提'!$E$143,0)) -> 30 | L46: =IF(ISBLANK('前提'!$E$143),$L$22,'前提'!$E$144+ROUND(($L$22-'前提'!$E$144)*'前提'!$E$143,0)) -> 32 | M46: kが空なら計画のまま。kがあれば 4＋(計画−4)×k を四捨五入
A47: 人数の倍率 | B47: 倍 | C47: =$C$46/$C$22 -> 1 | D47: =$D$46/$D$22 -> 1 | E47: =$E$46/$E$22 -> 1 | F47: =$F$46/$F$22 -> 1 | G47: =$G$46/$G$22 -> 1 | H47: =$H$46/$H$22 -> 1 | I47: =$I$46/$I$22 -> 1 | J47: =$J$46/$J$22 -> 1 | K47: =$K$46/$K$22 -> 1 | L47: =$L$46/$L$22 -> 1 | M47: 社員数÷計画の社員数
A48: 人件費（損益で使う） | B48: 万円/年 | C48: =($C$32+$C$45)*$C$47 -> 4236 | D48: =($D$32+$D$45)*$D$47 -> 6840 | E48: =($E$32+$E$45)*$E$47 -> 10044 | F48: =($F$32+$F$45)*$F$47 -> 14844 | G48: =($G$32+$G$45)*$G$47 -> 18684 | H48: =($H$32+$H$45)*$H$47 -> 19644 | I48: =($I$32+$I$45)*$I$47 -> 21924 | J48: =($J$32+$J$45)*$J$47 -> 23544 | K48: =($K$32+$K$45)*$K$47 -> 24384 | L48: =($L$32+$L$45)*$L$47 -> 26124 | M48: (人件費の合計＋上乗せ分)×人数の倍率
A49: 採用費（損益で使う） | B49: 万円/年 | C49: =$C$43*$C$47 -> 529.5 | D49: =$D$43*$D$47 -> 307.5 | E49: =$E$43*$E$47 -> 382.5 | F49: =$F$43*$F$47 -> 600 | G49: =$G$43*$G$47 -> 480 | H49: =$H$43*$H$47 -> 120 | I49: =$I$43*$I$47 -> 285 | J49: =$J$43*$J$47 -> 202.5 | K49: =$K$43*$K$47 -> 105 | L49: =$L$43*$L$47 -> 217.5 | M49: 採用費×人数の倍率
A50: 導入コンサルタントの確認（新規拠点は 人数×6 が上限）
A51: 1年に回せる新規拠点の上限 | B51: 拠点 | C51: =$C$18*'前提'!$E$90 -> 6 | D51: =$D$18*'前提'!$E$90 -> 12 | E51: =$E$18*'前提'!$E$90 -> 24 | F51: =$F$18*'前提'!$E$90 -> 36 | G51: =$G$18*'前提'!$E$90 -> 48 | H51: =$H$18*'前提'!$E$90 -> 48 | I51: =$I$18*'前提'!$E$90 -> 54 | J51: =$J$18*'前提'!$E$90 -> 54 | K51: =$K$18*'前提'!$E$90 -> 54 | L51: =$L$18*'前提'!$E$90 -> 54 | M51: 導入コンサルタントの人数×6
A52: 新規拠点 | B52: 拠点 | C52: ='前提'!$E$118 -> 3 | D52: ='前提'!$F$118 -> 9 | E52: ='前提'!$G$118 -> 18 | F52: ='前提'!$H$118 -> 27 | G52: ='前提'!$I$118 -> 33 | H52: ='前提'!$J$118 -> 36 | I52: ='前提'!$K$118 -> 38 | J52: ='前提'!$L$118 -> 40 | K52: ='前提'!$M$118 -> 40 | L52: ='前提'!$N$118 -> 40 | M52: 前提7-1
A53: 判定 | B53: ─ | C53: =IF($C$52<=$C$51,"上限内","超える") -> 上限内 | D53: =IF($D$52<=$D$51,"上限内","超える") -> 上限内 | E53: =IF($E$52<=$E$51,"上限内","超える") -> 上限内 | F53: =IF($F$52<=$F$51,"上限内","超える") -> 上限内 | G53: =IF($G$52<=$G$51,"上限内","超える") -> 上限内 | H53: =IF($H$52<=$H$51,"上限内","超える") -> 上限内 | I53: =IF($I$52<=$I$51,"上限内","超える") -> 上限内 | J53: =IF($J$52<=$J$51,"上限内","超える") -> 上限内 | K53: =IF($K$52<=$K$51,"上限内","超える") -> 上限内 | L53: =IF($L$52<=$L$51,"上限内","超える") -> 上限内 | M53: 新規拠点≦上限なら「上限内」
A54: 稼働できる人日 | B54: 人日 | C54: =$C$18*'前提'!$E$89 -> 240 | D54: =$D$18*'前提'!$E$89 -> 480 | E54: =$E$18*'前提'!$E$89 -> 960 | F54: =$F$18*'前提'!$E$89 -> 1440 | G54: =$G$18*'前提'!$E$89 -> 1920 | H54: =$H$18*'前提'!$E$89 -> 1920 | I54: =$I$18*'前提'!$E$89 -> 2160 | J54: =$J$18*'前提'!$E$89 -> 2160 | K54: =$K$18*'前提'!$E$89 -> 2160 | L54: =$L$18*'前提'!$E$89 -> 2160 | M54: 人数×240日
A55: 導入支援に使う人日 | B55: 人日 | C55: =$C$52*'導入支援'!$C$11 -> 126 | D55: =$D$52*'導入支援'!$C$11 -> 378 | E55: =$E$52*'導入支援'!$C$11 -> 756 | F55: =$F$52*'導入支援'!$C$11 -> 1134 | G55: =$G$52*'導入支援'!$C$11 -> 1386 | H55: =$H$52*'導入支援'!$C$11 -> 1512 | I55: =$I$52*'導入支援'!$C$11 -> 1596 | J55: =$J$52*'導入支援'!$C$11 -> 1680 | K55: =$K$52*'導入支援'!$C$11 -> 1680 | L55: =$L$52*'導入支援'!$C$11 -> 1680 | M55: 新規拠点×42人日
A56: 個社設定に使う人日 | B56: 人日 | C56: ='損益と現金'!$C$12/'導入支援'!$C$16 -> 133.33333 | D56: ='損益と現金'!$D$12/'導入支援'!$C$16 -> 166.66667 | E56: ='損益と現金'!$E$12/'導入支援'!$C$16 -> 244.44444 | F56: ='損益と現金'!$F$12/'導入支援'!$C$16 -> 122.22222 | G56: ='損益と現金'!$G$12/'導入支援'!$C$16 -> 211.11111 | H56: ='損益と現金'!$H$12/'導入支援'!$C$16 -> 222.22222 | I56: ='損益と現金'!$I$12/'導入支援'!$C$16 -> 244.44444 | J56: ='損益と現金'!$J$12/'導入支援'!$C$16 -> 266.66667 | K56: ='損益と現金'!$K$12/'導入支援'!$C$16 -> 288.88889 | L56: ='損益と現金'!$L$12/'導入支援'!$C$16 -> 311.11111 | M56: 個社設定の人件費÷1人日の人件費（3万円）
A57: 稼働率（導入支援＋個社設定） | B57: 割合 | C57: =($C$55+$C$56)/$C$54 -> 1.0805556 | D57: =($D$55+$D$56)/$D$54 -> 1.1347222 | E57: =($E$55+$E$56)/$E$54 -> 1.0421296 | F57: =($F$55+$F$56)/$F$54 -> 0.87237654 | G57: =($G$55+$G$56)/$G$54 -> 0.8318287 | H57: =($H$55+$H$56)/$H$54 -> 0.90324074 | I57: =($I$55+$I$56)/$I$54 -> 0.85205761 | J57: =($J$55+$J$56)/$J$54 -> 0.90123457 | K57: =($K$55+$K$56)/$K$54 -> 0.91152263 | L57: =($L$55+$L$56)/$L$54 -> 0.9218107 | M57: 使う人日÷稼働できる人日
A58: 注：新規拠点はどの年も上限（人数×6）の内に入っている。ただし個社設定もすべて導入コンサルタントが行うとすると、1〜3年目は稼働率が100%を超える。その分はエンジニアや代表が受け持つ前提になる（計算詳細版 p.15「導入コンサルタントとエンジニアが行う」）。人件費は役割ごとに計上済みなので、損益の数字は変わらない。

Sheet 拠点と売上
A1: 拠点と売上：期首−解約＋新規＝期末。売上の柱は既存の利用料
A2: 1年目は試験導入で利用料なし。新規は初年度に半年分。解約は期首×10%を四捨五入（1年目は0）。tora_v2.js の run({years:10}) と同じ式（計算詳細版 p.14・15）。
A3: 項目 | B3: 単位 | C3: 1 | D3: 2 | E3: 3 | F3: 4 | G3: 5 | H3: 6 | I3: 7 | J3: 8 | K3: 9 | L3: 10 | M3: 式（言葉）
A4: 拠点の積み上げ
A5: 期首の拠点 | B5: 拠点 | C5: ='前提'!$E$135 -> 0 | D5: =$C$9 -> 3 | E5: =$D$9 -> 12 | F5: =$E$9 -> 29 | G5: =$F$9 -> 53 | H5: =$G$9 -> 81 | I5: =$H$9 -> 109 | J5: =$I$9 -> 136 | K5: =$J$9 -> 162 | L5: =$K$9 -> 186 | M5: 前の年の期末。1年目は開業時の拠点（前提7-18）
A6: 使う解約率 | B6: 割合/年 | C6: =IF(ISBLANK('前提'!$E$140),'前提'!$E$119,'前提'!$E$140) -> 0.1 | D6: =IF(ISBLANK('前提'!$E$140),'前提'!$E$119,'前提'!$E$140) -> 0.1 | E6: =IF(ISBLANK('前提'!$E$140),'前提'!$E$119,'前提'!$E$140) -> 0.1 | F6: =IF(ISBLANK('前提'!$E$140),'前提'!$E$119,'前提'!$E$140) -> 0.1 | G6: =IF(ISBLANK('前提'!$E$140),'前提'!$E$119,'前提'!$E$140) -> 0.1 | H6: =IF(ISBLANK('前提'!$E$140),'前提'!$E$119,'前提'!$E$140) -> 0.1 | I6: =IF(ISBLANK('前提'!$E$140),'前提'!$E$119,'前提'!$E$140) -> 0.1 | J6: =IF(ISBLANK('前提'!$E$140),'前提'!$E$119,'前提'!$E$140) -> 0.1 | ... L6: =IF(ISBLANK('前提'!$E$140),'前提'!$E$119,'前提'!$E$140) -> 0.1 | M6: 前提8-2が空なら前提7-2
A7: 解約 | B7: 拠点 | C7: =IF(C$3=1,0,ROUND($C$5*$C$6,0)) -> 0 | D7: =IF(D$3=1,0,ROUND($D$5*$D$6,0)) -> 0 | E7: =IF(E$3=1,0,ROUND($E$5*$E$6,0)) -> 1 | F7: =IF(F$3=1,0,ROUND($F$5*$F$6,0)) -> 3 | G7: =IF(G$3=1,0,ROUND($G$5*$G$6,0)) -> 5 | H7: =IF(H$3=1,0,ROUND($H$5*$H$6,0)) -> 8 | I7: =IF(I$3=1,0,ROUND($I$5*$I$6,0)) -> 11 | J7: =IF(J$3=1,0,ROUND($J$5*$J$6,0)) -> 14 | K7: =IF(K$3=1,0,ROUND($K$5*$K$6,0)) -> 16 | L7: =IF(L$3=1,0,ROUND($L$5*$L$6,0)) -> 19 | M7: 1年目は0。2年目から 期首×解約率 を四捨五入
A8: 新規 | B8: 拠点 | C8: ='前提'!$E$118 -> 3 | D8: ='前提'!$F$118 -> 9 | E8: ='前提'!$G$118 -> 18 | F8: ='前提'!$H$118 -> 27 | G8: ='前提'!$I$118 -> 33 | H8: ='前提'!$J$118 -> 36 | I8: ='前提'!$K$118 -> 38 | J8: ='前提'!$L$118 -> 40 | K8: ='前提'!$M$118 -> 40 | L8: ='前提'!$N$118 -> 40 | M8: 前提7-1
A9: 期末の拠点 | B9: 拠点 | C9: =$C$5-$C$7+$C$8 -> 3 | D9: =$D$5-$D$7+$D$8 -> 12 | E9: =$E$5-$E$7+$E$8 -> 29 | F9: =$F$5-$F$7+$F$8 -> 53 | G9: =$G$5-$G$7+$G$8 -> 81 | H9: =$H$5-$H$7+$H$8 -> 109 | I9: =$I$5-$I$7+$I$8 -> 136 | J9: =$J$5-$J$7+$J$8 -> 162 | K9: =$K$5-$K$7+$K$8 -> 186 | L9: =$L$5-$L$7+$L$8 -> 207 | M9: 期首−解約＋新規
A10: 利用料
A11: 通年で課金する拠点（期首−解約） | B11: 拠点 | C11: =$C$5-$C$7 -> 0 | D11: =$D$5-$D$7 -> 3 | E11: =$E$5-$E$7 -> 11 | F11: =$F$5-$F$7 -> 26 | G11: =$G$5-$G$7 -> 48 | H11: =$H$5-$H$7 -> 73 | I11: =$I$5-$I$7 -> 98 | J11: =$J$5-$J$7 -> 122 | K11: =$K$5-$K$7 -> 146 | L11: =$L$5-$L$7 -> 167 | M11: 期首−解約
A12: 1拠点の利用料 | B12: 万円/年 | C12: ='値段と原価'!$C$8 -> 300 | D12: ='値段と原価'!$C$8 -> 300 | E12: ='値段と原価'!$C$8 -> 300 | F12: ='値段と原価'!$C$8 -> 300 | G12: ='値段と原価'!$C$8 -> 300 | H12: ='値段と原価'!$C$8 -> 300 | I12: ='値段と原価'!$C$8 -> 300 | J12: ='値段と原価'!$C$8 -> 300 | ... L12: ='値段と原価'!$C$8 -> 300 | M12: 値段と原価（値段の倍率を反映）
A13: 新規の初年度の課金割合 | B13: 割合 | C13: =IF(C$3='前提'!$E$121,0,'前提'!$E$120) -> 0 | D13: =IF(D$3='前提'!$E$121,0,'前提'!$E$120) -> 0.5 | E13: =IF(E$3='前提'!$E$121,0,'前提'!$E$120) -> 0.5 | F13: =IF(F$3='前提'!$E$121,0,'前提'!$E$120) -> 0.5 | G13: =IF(G$3='前提'!$E$121,0,'前提'!$E$120) -> 0.5 | H13: =IF(H$3='前提'!$E$121,0,'前提'!$E$120) -> 0.5 | I13: =IF(I$3='前提'!$E$121,0,'前提'!$E$120) -> 0.5 | J13: =IF(J$3='前提'!$E$121,0,'前提'!$E$120) -> 0.5 | ... L13: =IF(L$3='前提'!$E$121,0,'前提'!$E$120) -> 0.5 | M13: 試験導入の年（1年目）は0、それ以外は半年分
A14: 既存の利用料 | B14: 万円/年 | C14: =$C$11*$C$12 -> 0 | D14: =$D$11*$D$12 -> 900 | E14: =$E$11*$E$12 -> 3300 | F14: =$F$11*$F$12 -> 7800 | G14: =$G$11*$G$12 -> 14400 | H14: =$H$11*$H$12 -> 21900 | I14: =$I$11*$I$12 -> 29400 | J14: =$J$11*$J$12 -> 36600 | K14: =$K$11*$K$12 -> 43800 | L14: =$L$11*$L$12 -> 50100 | M14: (期首−解約)×1拠点の利用料
A15: 新規の利用料 | B15: 万円/年 | C15: =$C$8*$C$12*$C$13 -> 0 | D15: =$D$8*$D$12*$D$13 -> 1350 | E15: =$E$8*$E$12*$E$13 -> 2700 | F15: =$F$8*$F$12*$F$13 -> 4050 | G15: =$G$8*$G$12*$G$13 -> 4950 | H15: =$H$8*$H$12*$H$13 -> 5400 | I15: =$I$8*$I$12*$I$13 -> 5700 | J15: =$J$8*$J$12*$J$13 -> 6000 | K15: =$K$8*$K$12*$K$13 -> 6000 | L15: =$L$8*$L$12*$L$13 -> 6000 | M15: 新規×1拠点の利用料×初年度の課金割合
A16: 利用料の合計 | B16: 万円/年 | C16: =$C$14+$C$15 -> 0 | D16: =$D$14+$D$15 -> 2250 | E16: =$E$14+$E$15 -> 6000 | F16: =$F$14+$F$15 -> 11850 | G16: =$G$14+$G$15 -> 19350 | H16: =$H$14+$H$15 -> 27300 | I16: =$I$14+$I$15 -> 35100 | J16: =$J$14+$J$15 -> 42600 | K16: =$K$14+$K$15 -> 49800 | L16: =$L$14+$L$15 -> 56100 | M16: 既存＋新規
A17: 参考：解約で減った利用料 | B17: 万円/年 | C17: =$C$7*$C$12 -> 0 | D17: =$D$7*$D$12 -> 0 | E17: =$E$7*$E$12 -> 300 | F17: =$F$7*$F$12 -> 900 | G17: =$G$7*$G$12 -> 1500 | H17: =$H$7*$H$12 -> 2400 | I17: =$I$7*$I$12 -> 3300 | J17: =$J$7*$J$12 -> 4200 | K17: =$K$7*$K$12 -> 4800 | L17: =$L$7*$L$12 -> 5700 | M17: 解約×1拠点の利用料
A18: サービスと売上
A19: 導入支援 | B19: 万円/年 | C19: =$C$8*'前提'!$E$25 -> 600 | D19: =$D$8*'前提'!$E$25 -> 1800 | E19: =$E$8*'前提'!$E$25 -> 3600 | F19: =$F$8*'前提'!$E$25 -> 5400 | G19: =$G$8*'前提'!$E$25 -> 6600 | H19: =$H$8*'前提'!$E$25 -> 7200 | I19: =$I$8*'前提'!$E$25 -> 7600 | J19: =$J$8*'前提'!$E$25 -> 8000 | K19: =$K$8*'前提'!$E$25 -> 8000 | L19: =$L$8*'前提'!$E$25 -> 8000 | M19: 新規×200万円
A20: 個社設定 | B20: 万円/年 | C20: ='前提'!$E$124 -> 600 | D20: ='前提'!$F$124 -> 750 | E20: ='前提'!$G$124 -> 1100 | F20: ='前提'!$H$124 -> 550 | G20: ='前提'!$I$124 -> 950 | H20: ='前提'!$J$124 -> 1000 | I20: ='前提'!$K$124 -> 1100 | J20: ='前提'!$L$124 -> 1200 | K20: ='前提'!$M$124 -> 1300 | L20: ='前提'!$N$124 -> 1400 | M20: 前提7-7
A21: サービスの売上 | B21: 万円/年 | C21: =$C$19+$C$20 -> 1200 | D21: =$D$19+$D$20 -> 2550 | E21: =$E$19+$E$20 -> 4700 | F21: =$F$19+$F$20 -> 5950 | G21: =$G$19+$G$20 -> 7550 | H21: =$H$19+$H$20 -> 8200 | I21: =$I$19+$I$20 -> 8700 | J21: =$J$19+$J$20 -> 9200 | K21: =$K$19+$K$20 -> 9300 | L21: =$L$19+$L$20 -> 9400 | M21: 導入支援＋個社設定
A22: 売上 | B22: 万円/年 | C22: =$C$16+$C$21 -> 1200 | D22: =$D$16+$D$21 -> 4800 | E22: =$E$16+$E$21 -> 10700 | F22: =$F$16+$F$21 -> 17800 | G22: =$G$16+$G$21 -> 26900 | H22: =$H$16+$H$21 -> 35500 | I22: =$I$16+$I$21 -> 43800 | J22: =$J$16+$J$21 -> 51800 | K22: =$K$16+$K$21 -> 59100 | L22: =$L$16+$L$21 -> 65500 | M22: 利用料＋サービス
A23: 既存の利用料の割合 | B23: 割合 | C23: =$C$14/$C$22 -> 0 | D23: =$D$14/$D$22 -> 0.1875 | E23: =$E$14/$E$22 -> 0.30841121 | F23: =$F$14/$F$22 -> 0.43820225 | G23: =$G$14/$G$22 -> 0.53531599 | H23: =$H$14/$H$22 -> 0.61690141 | I23: =$I$14/$I$22 -> 0.67123288 | J23: =$J$14/$J$22 -> 0.70656371 | K23: =$K$14/$K$22 -> 0.74111675 | L23: =$L$14/$L$22 -> 0.7648855 | M23: 既存の利用料÷売上

Sheet 損益と現金
A1: 損益と現金：10台のままでも6年目に黒字、8年目に累計を取り戻す
A2: 販管費＝人件費−原価への振替＋採用費＋その他の経費＋顧問。導入支援と個社設定の人件費は原価へ振り替える。tora_v2.js の run({years:10}) と同じ式（計算詳細版 p.3・18・30）。
A3: 項目 | B3: 単位 | C3: 1 | D3: 2 | E3: 3 | F3: 4 | G3: 5 | H3: 6 | I3: 7 | J3: 8 | K3: 9 | L3: 10 | M3: 式（言葉）
A4: 原価
A5: 課金する拠点（通年換算） | B5: 拠点 | C5: ='拠点と売上'!$C$11+'拠点と売上'!$C$8*'拠点と売上'!$C$13 -> 0 | D5: ='拠点と売上'!$D$11+'拠点と売上'!$D$8*'拠点と売上'!$D$13 -> 7.5 | E5: ='拠点と売上'!$E$11+'拠点と売上'!$E$8*'拠点と売上'!$E$13 -> 20 | F5: ='拠点と売上'!$F$11+'拠点と売上'!$F$8*'拠点と売上'!$F$13 -> 39.5 | G5: ='拠点と売上'!$G$11+'拠点と売上'!$G$8*'拠点と売上'!$G$13 -> 64.5 | H5: ='拠点と売上'!$H$11+'拠点と売上'!$H$8*'拠点と売上'!$H$13 -> 91 | I5: ='拠点と売上'!$I$11+'拠点と売上'!$I$8*'拠点と売上'!$I$13 -> 117 | J5: ='拠点と売上'!$J$11+'拠点と売上'!$J$8*'拠点と売上'!$J$13 -> 142 | K5: ='拠点と売上'!$K$11+'拠点と売上'!$K$8*'拠点と売上'!$K$13 -> 166 | L5: ='拠点と売上'!$L$11+'拠点と売上'!$L$8*'拠点と売上'!$L$13 -> 187 | M5: (期首−解約)＋新規×初年度の課金割合
A6: 1拠点の原価 | B6: 万円/年 | C6: ='値段と原価'!$C$14 -> 84 | D6: ='値段と原価'!$C$14 -> 84 | E6: ='値段と原価'!$C$14 -> 84 | F6: ='値段と原価'!$C$14 -> 84 | G6: ='値段と原価'!$C$14 -> 84 | H6: ='値段と原価'!$C$14 -> 84 | I6: ='値段と原価'!$C$14 -> 84 | J6: ='値段と原価'!$C$14 -> 84 | ... L6: ='値段と原価'!$C$14 -> 84 | M6: 値段と原価（データ基盤＋1台の原価×台数）
A7: 試験導入の原価（3か月分） | B7: 万円/年 | C7: =IF(C$3='前提'!$E$121,'拠点と売上'!$C$8*$C$6*'前提'!$E$123,0) -> 63 | D7: =IF(D$3='前提'!$E$121,'拠点と売上'!$D$8*$D$6*'前提'!$E$123,0) -> 0 | E7: =IF(E$3='前提'!$E$121,'拠点と売上'!$E$8*$E$6*'前提'!$E$123,0) -> 0 | F7: =IF(F$3='前提'!$E$121,'拠点と売上'!$F$8*$F$6*'前提'!$E$123,0) -> 0 | G7: =IF(G$3='前提'!$E$121,'拠点と売上'!$G$8*$G$6*'前提'!$E$123,0) -> 0 | H7: =IF(H$3='前提'!$E$121,'拠点と売上'!$H$8*$H$6*'前提'!$E$123,0) -> 0 | I7: =IF(I$3='前提'!$E$121,'拠点と売上'!$I$8*$I$6*'前提'!$E$123,0) -> 0 | J7: =IF(J$3='前提'!$E$121,'拠点と売上'!$J$8*$J$6*'前提'!$E$123,0) -> 0 | K7: =IF(K$3='前提'!$E$121,'拠点と売上'!$K$8*$K$6*'前提'!$E$123,0) -> 0 | L7: =IF(L$3='前提'!$E$121,'拠点と売上'!$L$8*$L$6*'前提'!$E$123,0) -> 0 | M7: 試験導入の年だけ 新規×1拠点の原価×3/12
A8: 利用料の原価 | B8: 万円/年 | C8: =$C$5*$C$6+$C$7 -> 63 | D8: =$D$5*$D$6+$D$7 -> 630 | E8: =$E$5*$E$6+$E$7 -> 1680 | F8: =$F$5*$F$6+$F$7 -> 3318 | G8: =$G$5*$G$6+$G$7 -> 5418 | H8: =$H$5*$H$6+$H$7 -> 7644 | I8: =$I$5*$I$6+$I$7 -> 9828 | J8: =$J$5*$J$6+$J$7 -> 11928 | K8: =$K$5*$K$6+$K$7 -> 13944 | L8: =$L$5*$L$6+$L$7 -> 15708 | M8: 課金する拠点×1拠点の原価＋試験導入の原価
A9: 導入支援の人件費 | B9: 万円/年 | C9: ='拠点と売上'!$C$8*'導入支援'!$C$17 -> 378 | D9: ='拠点と売上'!$D$8*'導入支援'!$C$17 -> 1134 | E9: ='拠点と売上'!$E$8*'導入支援'!$C$17 -> 2268 | F9: ='拠点と売上'!$F$8*'導入支援'!$C$17 -> 3402 | G9: ='拠点と売上'!$G$8*'導入支援'!$C$17 -> 4158 | H9: ='拠点と売上'!$H$8*'導入支援'!$C$17 -> 4536 | I9: ='拠点と売上'!$I$8*'導入支援'!$C$17 -> 4788 | J9: ='拠点と売上'!$J$8*'導入支援'!$C$17 -> 5040 | K9: ='拠点と売上'!$K$8*'導入支援'!$C$17 -> 5040 | L9: ='拠点と売上'!$L$8*'導入支援'!$C$17 -> 5040 | M9: 新規×126万円（42人日×3万円）
A10: 導入支援の交通費 | B10: 万円/年 | C10: ='拠点と売上'!$C$8*'前提'!$E$88 -> 45 | D10: ='拠点と売上'!$D$8*'前提'!$E$88 -> 135 | E10: ='拠点と売上'!$E$8*'前提'!$E$88 -> 270 | F10: ='拠点と売上'!$F$8*'前提'!$E$88 -> 405 | G10: ='拠点と売上'!$G$8*'前提'!$E$88 -> 495 | H10: ='拠点と売上'!$H$8*'前提'!$E$88 -> 540 | I10: ='拠点と売上'!$I$8*'前提'!$E$88 -> 570 | J10: ='拠点と売上'!$J$8*'前提'!$E$88 -> 600 | K10: ='拠点と売上'!$K$8*'前提'!$E$88 -> 600 | L10: ='拠点と売上'!$L$8*'前提'!$E$88 -> 600 | M10: 新規×15万円
A11: 導入支援の原価 | B11: 万円/年 | C11: =$C$9+$C$10 -> 423 | D11: =$D$9+$D$10 -> 1269 | E11: =$E$9+$E$10 -> 2538 | F11: =$F$9+$F$10 -> 3807 | G11: =$G$9+$G$10 -> 4653 | H11: =$H$9+$H$10 -> 5076 | I11: =$I$9+$I$10 -> 5358 | J11: =$J$9+$J$10 -> 5640 | K11: =$K$9+$K$10 -> 5640 | L11: =$L$9+$L$10 -> 5640 | M11: 人件費＋交通費
A12: 個社設定の人件費 | B12: 万円/年 | C12: ='拠点と売上'!$C$20*(1-'前提'!$E$125) -> 400 | D12: ='拠点と売上'!$D$20*(1-'前提'!$E$125) -> 500 | E12: ='拠点と売上'!$E$20*(1-'前提'!$E$125) -> 733.33333 | F12: ='拠点と売上'!$F$20*(1-'前提'!$E$125) -> 366.66667 | G12: ='拠点と売上'!$G$20*(1-'前提'!$E$125) -> 633.33333 | H12: ='拠点と売上'!$H$20*(1-'前提'!$E$125) -> 666.66667 | I12: ='拠点と売上'!$I$20*(1-'前提'!$E$125) -> 733.33333 | J12: ='拠点と売上'!$J$20*(1-'前提'!$E$125) -> 800 | K12: ='拠点と売上'!$K$20*(1-'前提'!$E$125) -> 866.66667 | L12: ='拠点と売上'!$L$20*(1-'前提'!$E$125) -> 933.33333 | M12: 個社設定×2/3（粗利1/3）
A13: 原価の合計 | B13: 万円/年 | C13: =$C$8+$C$11+$C$12 -> 886 | D13: =$D$8+$D$11+$D$12 -> 2399 | E13: =$E$8+$E$11+$E$12 -> 4951.3333 | F13: =$F$8+$F$11+$F$12 -> 7491.6667 | G13: =$G$8+$G$11+$G$12 -> 10704.333 | H13: =$H$8+$H$11+$H$12 -> 13386.667 | I13: =$I$8+$I$11+$I$12 -> 15919.333 | J13: =$J$8+$J$11+$J$12 -> 18368 | K13: =$K$8+$K$11+$K$12 -> 20450.667 | L13: =$L$8+$L$11+$L$12 -> 22281.333 | M13: 利用料の原価＋導入支援の原価＋個社設定の人件費
A14: 粗利
A15: 売上 | B15: 万円/年 | C15: ='拠点と売上'!$C$22 -> 1200 | D15: ='拠点と売上'!$D$22 -> 4800 | E15: ='拠点と売上'!$E$22 -> 10700 | F15: ='拠点と売上'!$F$22 -> 17800 | G15: ='拠点と売上'!$G$22 -> 26900 | H15: ='拠点と売上'!$H$22 -> 35500 | I15: ='拠点と売上'!$I$22 -> 43800 | J15: ='拠点と売上'!$J$22 -> 51800 | K15: ='拠点と売上'!$K$22 -> 59100 | L15: ='拠点と売上'!$L$22 -> 65500 | M15: 拠点と売上
A16: 粗利 | B16: 万円/年 | C16: =$C$15-$C$13 -> 314 | D16: =$D$15-$D$13 -> 2401 | E16: =$E$15-$E$13 -> 5748.6667 | F16: =$F$15-$F$13 -> 10308.333 | G16: =$G$15-$G$13 -> 16195.667 | H16: =$H$15-$H$13 -> 22113.333 | I16: =$I$15-$I$13 -> 27880.667 | J16: =$J$15-$J$13 -> 33432 | K16: =$K$15-$K$13 -> 38649.333 | L16: =$L$15-$L$13 -> 43218.667 | M16: 売上−原価
A17: 粗利率 | B17: 割合 | C17: =$C$16/$C$15 -> 0.26166667 | D17: =$D$16/$D$15 -> 0.50020833 | E17: =$E$16/$E$15 -> 0.53725857 | F17: =$F$16/$F$15 -> 0.57911985 | G17: =$G$16/$G$15 -> 0.60206939 | H17: =$H$16/$H$15 -> 0.6229108 | I17: =$I$16/$I$15 -> 0.6365449 | J17: =$J$16/$J$15 -> 0.64540541 | K17: =$K$16/$K$15 -> 0.65396503 | L17: =$L$16/$L$15 -> 0.65982697 | M17: 粗利÷売上
A18: 利用料の粗利率 | B18: 割合 | C18: =IF('拠点と売上'!$C$16=0,0,1-$C$8/'拠点と売上'!$C$16) -> 0 | D18: =IF('拠点と売上'!$D$16=0,0,1-$D$8/'拠点と売上'!$D$16) -> 0.72 | E18: =IF('拠点と売上'!$E$16=0,0,1-$E$8/'拠点と売上'!$E$16) -> 0.72 | F18: =IF('拠点と売上'!$F$16=0,0,1-$F$8/'拠点と売上'!$F$16) -> 0.72 | G18: =IF('拠点と売上'!$G$16=0,0,1-$G$8/'拠点と売上'!$G$16) -> 0.72 | H18: =IF('拠点と売上'!$H$16=0,0,1-$H$8/'拠点と売上'!$H$16) -> 0.72 | I18: =IF('拠点と売上'!$I$16=0,0,1-$I$8/'拠点と売上'!$I$16) -> 0.72 | J18: =IF('拠点と売上'!$J$16=0,0,1-$J$8/'拠点と売上'!$J$16) -> 0.72 | K18: =IF('拠点と売上'!$K$16=0,0,1-$K$8/'拠点と売上'!$K$16) -> 0.72 | L18: =IF('拠点と売上'!$L$16=0,0,1-$L$8/'拠点と売上'!$L$16) -> 0.72 | M18: 1−利用料の原価÷利用料（1年目は利用料がないので0）
A19: 販管費
A20: 人件費 | B20: 万円/年 | C20: ='体制と人件費'!$C$48 -> 4236 | D20: ='体制と人件費'!$D$48 -> 6840 | E20: ='体制と人件費'!$E$48 -> 10044 | F20: ='体制と人件費'!$F$48 -> 14844 | G20: ='体制と人件費'!$G$48 -> 18684 | H20: ='体制と人件費'!$H$48 -> 19644 | I20: ='体制と人件費'!$I$48 -> 21924 | J20: ='体制と人件費'!$J$48 -> 23544 | K20: ='体制と人件費'!$K$48 -> 24384 | L20: ='体制と人件費'!$L$48 -> 26124 | M20: 体制と人件費
A21: 原価への振替 | B21: 万円/年 | C21: =$C$9+$C$12 -> 778 | D21: =$D$9+$D$12 -> 1634 | E21: =$E$9+$E$12 -> 3001.3333 | F21: =$F$9+$F$12 -> 3768.6667 | G21: =$G$9+$G$12 -> 4791.3333 | H21: =$H$9+$H$12 -> 5202.6667 | I21: =$I$9+$I$12 -> 5521.3333 | J21: =$J$9+$J$12 -> 5840 | K21: =$K$9+$K$12 -> 5906.6667 | L21: =$L$9+$L$12 -> 5973.3333 | M21: 導入支援の人件費＋個社設定の人件費（販管費から引く）
A22: 採用費 | B22: 万円/年 | C22: ='体制と人件費'!$C$49 -> 529.5 | D22: ='体制と人件費'!$D$49 -> 307.5 | E22: ='体制と人件費'!$E$49 -> 382.5 | F22: ='体制と人件費'!$F$49 -> 600 | G22: ='体制と人件費'!$G$49 -> 480 | H22: ='体制と人件費'!$H$49 -> 120 | I22: ='体制と人件費'!$I$49 -> 285 | J22: ='体制と人件費'!$J$49 -> 202.5 | K22: ='体制と人件費'!$K$49 -> 105 | L22: ='体制と人件費'!$L$49 -> 217.5 | M22: 体制と人件費
A23: その他の経費（7項目） | B23: 万円/年 | C23: ='前提'!$E$126+'前提'!$E$127+'前提'!$E$128+'前提'!$E$129+'前提'!$E$130+'前提'!$E$131+'前提'!$E$132 -> 990 | D23: ='前提'!$F$126+'前提'!$F$127+'前提'!$F$128+'前提'!$F$129+'前提'!$F$130+'前提'!$F$131+'前提'!$F$132 -> 1470 | E23: ='前提'!$G$126+'前提'!$G$127+'前提'!$G$128+'前提'!$G$129+'前提'!$G$130+'前提'!$G$131+'前提'!$G$132 -> 1840 | F23: ='前提'!$H$126+'前提'!$H$127+'前提'!$H$128+'前提'!$H$129+'前提'!$H$130+'前提'!$H$131+'前提'!$H$132 -> 2310 | G23: ='前提'!$I$126+'前提'!$I$127+'前提'!$I$128+'前提'!$I$129+'前提'!$I$130+'前提'!$I$131+'前提'!$I$132 -> 2760 | H23: ='前提'!$J$126+'前提'!$J$127+'前提'!$J$128+'前提'!$J$129+'前提'!$J$130+'前提'!$J$131+'前提'!$J$132 -> 2850 | I23: ='前提'!$K$126+'前提'!$K$127+'前提'!$K$128+'前提'!$K$129+'前提'!$K$130+'前提'!$K$131+'前提'!$K$132 -> 3130 | J23: ='前提'!$L$126+'前提'!$L$127+'前提'!$L$128+'前提'!$L$129+'前提'!$L$130+'前提'!$L$131+'前提'!$L$132 -> 3340 | K23: ='前提'!$M$126+'前提'!$M$127+'前提'!$M$128+'前提'!$M$129+'前提'!$M$130+'前提'!$M$131+'前提'!$M$132 -> 3580 | L23: ='前提'!$N$126+'前提'!$N$127+'前提'!$N$128+'前提'!$N$129+'前提'!$N$130+'前提'!$N$131+'前提'!$N$132 -> 3690 | M23: オフィス＋広告＋交通費＋端末・ソフト＋専門家＋雑費＋AIの学習費（前提7-9〜7-15）
A24: 社外顧問 | B24: 万円/年 | C24: ='前提'!$E$115 -> 180 | D24: ='前提'!$E$115 -> 180 | E24: ='前提'!$E$115 -> 180 | F24: ='前提'!$E$115 -> 180 | G24: ='前提'!$E$115 -> 180 | H24: ='前提'!$E$115 -> 180 | I24: ='前提'!$E$115 -> 180 | J24: ='前提'!$E$115 -> 180 | ... L24: ='前提'!$E$115 -> 180 | M24: 月15万円×12
A25: 販管費 | B25: 万円/年 | C25: =$C$20-$C$21+$C$22+$C$23+$C$24 -> 5157.5 | D25: =$D$20-$D$21+$D$22+$D$23+$D$24 -> 7163.5 | E25: =$E$20-$E$21+$E$22+$E$23+$E$24 -> 9445.1667 | F25: =$F$20-$F$21+$F$22+$F$23+$F$24 -> 14165.333 | G25: =$G$20-$G$21+$G$22+$G$23+$G$24 -> 17312.667 | H25: =$H$20-$H$21+$H$22+$H$23+$H$24 -> 17591.333 | I25: =$I$20-$I$21+$I$22+$I$23+$I$24 -> 19997.667 | J25: =$J$20-$J$21+$J$22+$J$23+$J$24 -> 21426.5 | K25: =$K$20-$K$21+$K$22+$K$23+$K$24 -> 22342.333 | L25: =$L$20-$L$21+$L$22+$L$23+$L$24 -> 24238.167 | M25: 人件費−振替＋採用費＋その他＋顧問
A26: 営業利益と現金
A27: 営業利益 | B27: 万円/年 | C27: =$C$16-$C$25 -> -4843.5 | D27: =$D$16-$D$25 -> -4762.5 | E27: =$E$16-$E$25 -> -3696.5 | F27: =$F$16-$F$25 -> -3857 | G27: =$G$16-$G$25 -> -1117 | H27: =$H$16-$H$25 -> 4522 | I27: =$I$16-$I$25 -> 7883 | J27: =$J$16-$J$25 -> 12005.5 | K27: =$K$16-$K$25 -> 16307 | L27: =$L$16-$L$25 -> 18980.5 | M27: 粗利−販管費
A28: 累計の営業損益 | B28: 万円 | C28: =$C$27 -> -4843.5 | D28: =$C$28+$D$27 -> -9606 | E28: =$D$28+$E$27 -> -13302.5 | F28: =$E$28+$F$27 -> -17159.5 | G28: =$F$28+$G$27 -> -18276.5 | H28: =$G$28+$H$27 -> -13754.5 | I28: =$H$28+$I$27 -> -5871.5 | J28: =$I$28+$J$27 -> 6134 | K28: =$J$28+$K$27 -> 22441 | L28: =$K$28+$L$27 -> 41421.5 | M28: 前の年の累計＋その年の営業利益
A29: 資金投入 | B29: 万円/年 | C29: ='前提'!$E$133 -> 20000 | D29: ='前提'!$F$133 -> 0 | E29: ='前提'!$G$133 -> 5000 | F29: ='前提'!$H$133 -> 0 | G29: ='前提'!$I$133 -> 0 | H29: ='前提'!$J$133 -> 0 | I29: ='前提'!$K$133 -> 0 | J29: ='前提'!$L$133 -> 0 | K29: ='前提'!$M$133 -> 0 | L29: ='前提'!$N$133 -> 0 | M29: 前提7-16（準備期の500万円は別）
A30: 期末の現金 | B30: 万円 | C30: ='前提'!$E$136+$C$29+$C$27 -> 15156.5 | D30: =$C$30+$D$29+$D$27 -> 10394 | E30: =$D$30+$E$29+$E$27 -> 11697.5 | F30: =$E$30+$F$29+$F$27 -> 7840.5 | G30: =$F$30+$G$29+$G$27 -> 6723.5 | H30: =$G$30+$H$29+$H$27 -> 11245.5 | I30: =$H$30+$I$29+$I$27 -> 19128.5 | J30: =$I$30+$J$29+$J$27 -> 31134 | K30: =$J$30+$K$29+$K$27 -> 47441 | L30: =$K$30+$L$29+$L$27 -> 66421.5 | M30: 前の年の現金＋資金投入＋営業利益。1年目は期首0から
A31: （営業利益が黒字の年） | B31: 年目 | C31: =IF($C$27>0,C$3,"") | D31: =IF($D$27>0,D$3,"") | E31: =IF($E$27>0,E$3,"") | F31: =IF($F$27>0,F$3,"") | G31: =IF($G$27>0,G$3,"") | H31: =IF($H$27>0,H$3,"") -> 6 | I31: =IF($I$27>0,I$3,"") -> 7 | J31: =IF($J$27>0,J$3,"") -> 8 | K31: =IF($K$27>0,K$3,"") -> 9 | L31: =IF($L$27>0,L$3,"") -> 10 | M31: 黒字なら年の番号、赤字なら空
A32: （累計が黒字の年） | B32: 年目 | C32: =IF($C$28>0,C$3,"") | D32: =IF($D$28>0,D$3,"") | E32: =IF($E$28>0,E$3,"") | F32: =IF($F$28>0,F$3,"") | G32: =IF($G$28>0,G$3,"") | H32: =IF($H$28>0,H$3,"") | I32: =IF($I$28>0,I$3,"") | J32: =IF($J$28>0,J$3,"") -> 8 | K32: =IF($K$28>0,K$3,"") -> 9 | L32: =IF($L$28>0,L$3,"") -> 10 | M32: 累計が黒字なら年の番号
A33: 結果
A34: 黒字化の年（10年で） | B34: 年目 | C34: =IF(COUNT($C$31:$L$31)=0,"10年でなし",MIN($C$31:$L$31)) -> 6 | D34: 営業利益が初めて黒字になる年
A35: 黒字化の年（5年で） | B35: 年目 | C35: =IF(COUNT($C$31:$G$31)=0,"5年でなし",MIN($C$31:$G$31)) -> 5年でなし | D35: 1〜5年目だけで見た場合
A36: 累計回収の年（10年で） | B36: 年目 | C36: =IF(COUNT($C$32:$L$32)=0,"10年でなし",MIN($C$32:$L$32)) -> 8 | D36: 累計の営業損益が初めて黒字になる年
A37: 最低の現金（10年） | B37: 万円 | C37: =MIN($C$30:$L$30) -> 6723.5 | D37: 期末の現金のいちばん低い値
A38: 最低の現金の年 | B38: 年目 | C38: =INDEX($C$3:$L$3,1,MATCH($C$37,$C$30:$L$30,0)) -> 5
A39: 最低の現金（5年） | B39: 万円 | C39: =MIN($C$30:$G$30) -> 6723.5 | D39: 1〜5年目
A40: 累計赤字の底 | B40: 万円 | C40: =MIN($C$28:$L$28) -> -18276.5 | D40: 累計の営業損益のいちばん低い値
A41: 注：簡易計算で、運転資本（売掛・前受）・税・償却を含まない。黒字化の年は緑、マイナスは赤（▲）で示す。

Sheet 黒字ライン
A1: 黒字ライン：その年の体制で何拠点・何台あれば黒字か
A2: 損益分岐点売上＝販管費÷粗利率。必要な拠点＝(販管費−サービスの粗利)÷1拠点の利用料の粗利216万円（拠点は通年で課金するとして）（計算詳細版 p.19・22）。
A3: 項目 | B3: 単位 | C3: 1 | D3: 2 | E3: 3 | F3: 4 | G3: 5 | H3: 6 | I3: 7 | J3: 8 | K3: 9 | L3: 10 | M3: 式（言葉）
A4: 売上で見る（損益分岐点売上＝販管費÷粗利率）
A5: 販管費 | B5: 万円/年 | C5: ='損益と現金'!$C$25 -> 5157.5 | D5: ='損益と現金'!$D$25 -> 7163.5 | E5: ='損益と現金'!$E$25 -> 9445.1667 | F5: ='損益と現金'!$F$25 -> 14165.333 | G5: ='損益と現金'!$G$25 -> 17312.667 | H5: ='損益と現金'!$H$25 -> 17591.333 | I5: ='損益と現金'!$I$25 -> 19997.667 | J5: ='損益と現金'!$J$25 -> 21426.5 | K5: ='損益と現金'!$K$25 -> 22342.333 | L5: ='損益と現金'!$L$25 -> 24238.167 | M5: 損益と現金
A6: 粗利率 | B6: 割合 | C6: ='損益と現金'!$C$17 -> 0.26166667 | D6: ='損益と現金'!$D$17 -> 0.50020833 | E6: ='損益と現金'!$E$17 -> 0.53725857 | F6: ='損益と現金'!$F$17 -> 0.57911985 | G6: ='損益と現金'!$G$17 -> 0.60206939 | H6: ='損益と現金'!$H$17 -> 0.6229108 | I6: ='損益と現金'!$I$17 -> 0.6365449 | J6: ='損益と現金'!$J$17 -> 0.64540541 | K6: ='損益と現金'!$K$17 -> 0.65396503 | L6: ='損益と現金'!$L$17 -> 0.65982697 | M6: 損益と現金
A7: 損益分岐点売上 | B7: 万円/年 | C7: =$C$5/$C$6 -> 19710.191 | D7: =$D$5/$D$6 -> 14321.033 | E7: =$E$5/$E$6 -> 17580.3 | F7: =$F$5/$F$6 -> 24460.107 | G7: =$G$5/$G$6 -> 28755.268 | H7: =$H$5/$H$6 -> 28240.534 | I7: =$I$5/$I$6 -> 31415.956 | J7: =$J$5/$J$6 -> 33198.513 | K7: =$K$5/$K$6 -> 34164.416 | L7: =$L$5/$L$6 -> 36734.125 | M7: 販管費÷粗利率
A8: 実際の売上 | B8: 万円/年 | C8: ='拠点と売上'!$C$22 -> 1200 | D8: ='拠点と売上'!$D$22 -> 4800 | E8: ='拠点と売上'!$E$22 -> 10700 | F8: ='拠点と売上'!$F$22 -> 17800 | G8: ='拠点と売上'!$G$22 -> 26900 | H8: ='拠点と売上'!$H$22 -> 35500 | I8: ='拠点と売上'!$I$22 -> 43800 | J8: ='拠点と売上'!$J$22 -> 51800 | K8: ='拠点と売上'!$K$22 -> 59100 | L8: ='拠点と売上'!$L$22 -> 65500 | M8: 拠点と売上
A9: 分岐点に対する売上の割合 | B9: 割合 | C9: =$C$8/$C$7 -> 0.06088221 | D9: =$D$8/$D$7 -> 0.33517135 | E9: =$E$8/$E$7 -> 0.60863581 | F9: =$F$8/$F$7 -> 0.72771555 | G9: =$G$8/$G$7 -> 0.93548077 | H9: =$H$8/$H$7 -> 1.2570584 | I9: =$I$8/$I$7 -> 1.394196 | J9: =$J$8/$J$7 -> 1.5603108 | K9: =$K$8/$K$7 -> 1.7298701 | L9: =$L$8/$L$7 -> 1.7830832 | M9: 売上÷損益分岐点売上（100%以上で黒字）
A10: 安全余裕率 | B10: 割合 | C10: =IF($C$8>$C$7,1-$C$7/$C$8,"─") -> ─ | D10: =IF($D$8>$D$7,1-$D$7/$D$8,"─") -> ─ | E10: =IF($E$8>$E$7,1-$E$7/$E$8,"─") -> ─ | F10: =IF($F$8>$F$7,1-$F$7/$F$8,"─") -> ─ | G10: =IF($G$8>$G$7,1-$G$7/$G$8,"─") -> ─ | H10: =IF($H$8>$H$7,1-$H$7/$H$8,"─") -> 0.20449201 | I10: =IF($I$8>$I$7,1-$I$7/$I$8,"─") -> 0.28274073 | J10: =IF($J$8>$J$7,1-$J$7/$J$8,"─") -> 0.35910206 | K10: =IF($K$8>$K$7,1-$K$7/$K$8,"─") -> 0.4219219 | L10: =IF($L$8>$L$7,1-$L$7/$L$8,"─") -> 0.43917366 | M10: (売上−分岐点売上)÷売上。赤字の年は「─」
A11: 人で見る
A12: 社員数 | B12: 人 | C12: ='体制と人件費'!$C$46 -> 5 | D12: ='体制と人件費'!$D$46 -> 8 | E12: ='体制と人件費'!$E$46 -> 12 | F12: ='体制と人件費'!$F$46 -> 18 | G12: ='体制と人件費'!$G$46 -> 23 | H12: ='体制と人件費'!$H$46 -> 24 | I12: ='体制と人件費'!$I$46 -> 27 | J12: ='体制と人件費'!$J$46 -> 29 | K12: ='体制と人件費'!$K$46 -> 30 | L12: ='体制と人件費'!$L$46 -> 32 | M12: 体制と人件費（採用連動の後）
A13: 期末の拠点 | B13: 拠点 | C13: ='拠点と売上'!$C$9 -> 3 | D13: ='拠点と売上'!$D$9 -> 12 | E13: ='拠点と売上'!$E$9 -> 29 | F13: ='拠点と売上'!$F$9 -> 53 | G13: ='拠点と売上'!$G$9 -> 81 | H13: ='拠点と売上'!$H$9 -> 109 | I13: ='拠点と売上'!$I$9 -> 136 | J13: ='拠点と売上'!$J$9 -> 162 | K13: ='拠点と売上'!$K$9 -> 186 | L13: ='拠点と売上'!$L$9 -> 207 | M13: 拠点と売上
A14: 社員1人あたりの拠点 | B14: 拠点/人 | C14: =$C$13/$C$12 -> 0.6 | D14: =$D$13/$D$12 -> 1.5 | E14: =$E$13/$E$12 -> 2.4166667 | F14: =$F$13/$F$12 -> 2.9444444 | G14: =$G$13/$G$12 -> 3.5217391 | H14: =$H$13/$H$12 -> 4.5416667 | I14: =$I$13/$I$12 -> 5.037037 | J14: =$J$13/$J$12 -> 5.5862069 | K14: =$K$13/$K$12 -> 6.2 | L14: =$L$13/$L$12 -> 6.46875 | M14: 期末の拠点÷社員数
A15: 社員1人あたりの販管費 | B15: 万円/人 | C15: =$C$5/$C$12 -> 1031.5 | D15: =$D$5/$D$12 -> 895.4375 | E15: =$E$5/$E$12 -> 787.09722 | F15: =$F$5/$F$12 -> 786.96296 | G15: =$G$5/$G$12 -> 752.72464 | H15: =$H$5/$H$12 -> 732.97222 | I15: =$I$5/$I$12 -> 740.65432 | J15: =$J$5/$J$12 -> 738.84483 | K15: =$K$5/$K$12 -> 744.74444 | L15: =$L$5/$L$12 -> 757.44271 | M15: 販管費÷社員数
A16: 社員1人あたりに要る課金拠点 | B16: 拠点/人 | C16: =$C$15/'値段と原価'!$C$15 -> 4.775463 | D16: =$D$15/'値段と原価'!$C$15 -> 4.145544 | E16: =$E$15/'値段と原価'!$C$15 -> 3.6439686 | F16: =$F$15/'値段と原価'!$C$15 -> 3.6433471 | G16: =$G$15/'値段と原価'!$C$15 -> 3.4848363 | H16: =$H$15/'値段と原価'!$C$15 -> 3.3933899 | I16: =$I$15/'値段と原価'!$C$15 -> 3.4289552 | J16: =$J$15/'値段と原価'!$C$15 -> 3.4205779 | K16: =$K$15/'値段と原価'!$C$15 -> 3.4478909 | L16: =$L$15/'値段と原価'!$C$15 -> 3.5066792 | M16: 社員1人の販管費÷1拠点の利用料の粗利（新規は初年度半額なので期末ではもっと要る）
A17: その年の体制で黒字に必要な拠点（通年で課金する拠点として）
A18: サービスの粗利 | B18: 万円/年 | C18: ='拠点と売上'!$C$21-'損益と現金'!$C$11-'損益と現金'!$C$12 -> 377 | D18: ='拠点と売上'!$D$21-'損益と現金'!$D$11-'損益と現金'!$D$12 -> 781 | E18: ='拠点と売上'!$E$21-'損益と現金'!$E$11-'損益と現金'!$E$12 -> 1428.6667 | F18: ='拠点と売上'!$F$21-'損益と現金'!$F$11-'損益と現金'!$F$12 -> 1776.3333 | G18: ='拠点と売上'!$G$21-'損益と現金'!$G$11-'損益と現金'!$G$12 -> 2263.6667 | H18: ='拠点と売上'!$H$21-'損益と現金'!$H$11-'損益と現金'!$H$12 -> 2457.3333 | I18: ='拠点と売上'!$I$21-'損益と現金'!$I$11-'損益と現金'!$I$12 -> 2608.6667 | J18: ='拠点と売上'!$J$21-'損益と現金'!$J$11-'損益と現金'!$J$12 -> 2760 | K18: ='拠点と売上'!$K$21-'損益と現金'!$K$11-'損益と現金'!$K$12 -> 2793.3333 | L18: ='拠点と売上'!$L$21-'損益と現金'!$L$11-'損益と現金'!$L$12 -> 2826.6667 | M18: 導入支援＋個社設定−導入支援の原価−個社設定の人件費
A19: 1拠点の利用料の粗利 | B19: 万円/年 | C19: ='値段と原価'!$C$15 -> 216 | D19: ='値段と原価'!$C$15 -> 216 | E19: ='値段と原価'!$C$15 -> 216 | F19: ='値段と原価'!$C$15 -> 216 | G19: ='値段と原価'!$C$15 -> 216 | H19: ='値段と原価'!$C$15 -> 216 | I19: ='値段と原価'!$C$15 -> 216 | J19: ='値段と原価'!$C$15 -> 216 | ... L19: ='値段と原価'!$C$15 -> 216 | M19: 値段と原価（300−84）
A20: 黒字に必要な課金拠点 | B20: 拠点 | C20: =($C$5-$C$18)/$C$19 -> 22.131944 | D20: =($D$5-$D$18)/$D$19 -> 29.548611 | E20: =($E$5-$E$18)/$E$19 -> 37.113426 | F20: =($F$5-$F$18)/$F$19 -> 57.356481 | G20: =($G$5-$G$18)/$G$19 -> 69.671296 | H20: =($H$5-$H$18)/$H$19 -> 70.064815 | I20: =($I$5-$I$18)/$I$19 -> 80.50463 | J20: =($J$5-$J$18)/$J$19 -> 86.418981 | K20: =($K$5-$K$18)/$K$19 -> 90.50463 | L20: =($L$5-$L$18)/$L$19 -> 99.127315 | M20: (販管費−サービスの粗利)÷216
A21: 実際の課金拠点（通年換算） | B21: 拠点 | C21: ='損益と現金'!$C$5 -> 0 | D21: ='損益と現金'!$D$5 -> 7.5 | E21: ='損益と現金'!$E$5 -> 20 | F21: ='損益と現金'!$F$5 -> 39.5 | G21: ='損益と現金'!$G$5 -> 64.5 | H21: ='損益と現金'!$H$5 -> 91 | I21: ='損益と現金'!$I$5 -> 117 | J21: ='損益と現金'!$J$5 -> 142 | K21: ='損益と現金'!$K$5 -> 166 | L21: ='損益と現金'!$L$5 -> 187 | M21: 損益と現金（1年目は試験導入なので0）
A22: 課金拠点の余裕（実際−必要） | B22: 拠点 | C22: =$C$21-$C$20 -> -22.131944 | D22: =$D$21-$D$20 -> -22.048611 | E22: =$E$21-$E$20 -> -17.113426 | F22: =$F$21-$F$20 -> -17.856481 | G22: =$G$21-$G$20 -> -5.1712963 | H22: =$H$21-$H$20 -> 20.935185 | I22: =$I$21-$I$20 -> 36.49537 | J22: =$J$21-$J$20 -> 55.581019 | K22: =$K$21-$K$20 -> 75.49537 | L22: =$L$21-$L$20 -> 87.872685 | M22: マイナス（赤）なら足りない
A23: 5年目に黒字にするのに必要な1拠点の台数（81拠点のまま台数だけ増やす）
A24: 課金する拠点（通年換算） | B24: 拠点 | C24: =INDEX($C$21:$L$21,1,'前提'!$E$148) -> 64.5 | D24: その年の (期首−解約)＋新規×半年
A25: 期末の拠点 | B25: 拠点 | C25: =INDEX($C$13:$L$13,1,'前提'!$E$148) -> 81
A26: 必要な利用料の粗利 | B26: 万円/年 | C26: =INDEX($C$5:$L$5,1,'前提'!$E$148)-INDEX($C$18:$L$18,1,'前提'!$E$148) -> 15049 | D26: 販管費−サービスの粗利
A27: 1拠点あたりに必要な利用料の粗利 | B27: 万円/年/拠点 | C27: =$C$26/$C$24 -> 233.31783 | D27: 必要な利用料の粗利÷課金する拠点
A28: 基盤の粗利（1拠点） | B28: 万円/年/拠点 | C28: ='値段と原価'!$C$5-'値段と原価'!$C$13 -> 48 | D28: 基盤60−データ基盤12
A29: 1台の粗利 | B29: 万円/年/台 | C29: ='値段と原価'!$C$6-'値段と原価'!$C$12 -> 16.8 | D29: 端末24−1台の原価7.2
A30: 必要な台数（計算） | B30: 台/拠点 | C30: =($C$27-$C$28)/$C$29 -> 11.030823 | D30: (1拠点に必要な粗利−基盤の粗利)÷1台の粗利
A31: 必要な台数（整数に切り上げ） | B31: 台/拠点 | C31: =ROUNDUP($C$30,0) -> 12 | D31: この台数なら5年目に黒字
A32: 確認：その台数での5年目の営業利益 | B32: 万円/年 | C32: =$C$24*($C$28+$C$29*$C$31)+INDEX($C$18:$L$18,1,'前提'!$E$148)-INDEX($C$5:$L$5,1,'前提'!$E$148) -> 1050.2 | D32: 課金する拠点×(基盤の粗利＋1台の粗利×台数)＋サービスの粗利−販管費
A33: 確認：1台少ない場合の5年目の営業利益 | B33: 万円/年 | C33: =$C$24*($C$28+$C$29*($C$31-1))+INDEX($C$18:$L$18,1,'前提'!$E$148)-INDEX($C$5:$L$5,1,'前提'!$E$148) -> -33.4 | D33: 同じ式で台数−1
A34: 確認：15台の場合の5年目の営業利益 | B34: 万円/年 | C34: =$C$24*($C$28+$C$29*'前提'!$E$149)+INDEX($C$18:$L$18,1,'前提'!$E$148)-INDEX($C$5:$L$5,1,'前提'!$E$148) -> 4301 | D34: 前提9-4の台数。tora_v2.js の1拠点15台（4,301万円）と同じになる
A35: 注：台数を増やしても、導入支援・人件費・データ基盤は変わらないとした（tora_v2.js と同じ）。
A36: 問い：黒字ラインは結局何台／何拠点？
A37: ="5年目（社員"&TEXT(INDEX($C$12:$L$12,1,'前提'!$E$148),"0")&"人・販管費"&TEXT(INDEX($C$5:$L$5,1,'前提'!$E$148),"#,##0")&"万円）で黒字にするには、通年で課金する拠点が"&TEXT(INDEX($C$20:$L$20,1,'前提'!$E$148),"0.0")&"拠点要る（実際は"&TEXT(INDEX($C$21:$L$21,1,'前提'!$E$148),"0.0")&"）。期末"&TEXT($C$25,"0")&"拠点のまま台数で越えるなら、1拠点"&TEXT($C$31,"0")&"台（計算では"&TEXT($C$30,"0.00")&"台）。10台のままなら"&IF(ISNUMBER('損益と現金'!$C$34),TEXT('損益と現金'!$C$34,"0")&"年目（期末"&TEXT(INDEX($C$13:$L$13,1,'損益と現金'!$C$34),"0")&"拠点・社員"&TEXT(INDEX($C$12:$L$12,1,'損益と現金'!$C$34),"0")&"人）に黒字。","10年以内には黒字にならない。") -> 5年目（社員23人・販管費17,313万円）で黒字にするには、通年で課金する拠点が69.7拠点要る（実際は64.5）。期末81拠点のまま台数で越えるなら、1拠点12台（計算では11.03台）。10台のままなら6年目（期末109拠点・社員24人）に黒字。

Sheet LTV・CAC
A1: LTV・CAC：LTVは控えめに7年で約1,571万円、CACは約86万円
A2: LTV＝1拠点の年の粗利×継続年数＋導入支援の粗利。CAC＝(営業の人件費＋広告)÷新規拠点（5年目）。tora_v2.js の unit() と同じ（計算詳細版 p.20）。
A3: 項目 | B3: 単位 | C3: 値 | F3: 式（言葉）
A4: LTV（1拠点が残す粗利）
A5: 1拠点の年の粗利 | B5: 万円/年 | C5: ='値段と原価'!$C$15 -> 216 | D5: 値段と原価（300−84）
A6: 導入支援の粗利 | B6: 万円/拠点 | C6: ='導入支援'!$C$21 -> 59 | D6: 導入支援（200−141）
A7: 計画の継続年数 | B7: 年 | C7: ='前提'!$E$146 -> 7 | D7: 前提9-1
A8: LTV（計画） | B8: 万円/拠点 | C8: =$C$5*$C$7+$C$6 -> 1571 | D8: 216×7年＋59
A9: 解約率から見た平均の継続年数 | B9: 年 | C9: =1/'拠点と売上'!$C$6 -> 10 | D9: 1÷解約率10%＝10年。7年は控えめ
A10: CAC（1拠点を獲得する費用）
A11: 計算する年 | B11: 年目 | C11: ='前提'!$E$147 -> 5 | D11: 前提9-2
A12: 営業の人数 | B12: 人 | C12: =INDEX('体制と人件費'!$C$19:$L$19,1,$C$11) -> 3 | D12: 体制と人件費（5年目3人）
A13: 営業の年収 | B13: 万円/年 | C13: =INDEX('体制と人件費'!$C$10:$L$10,1,$C$11) -> 650 | D13: 体制と人件費
A14: 営業の人件費 | B14: 万円/年 | C14: =$C$12*$C$13*'前提'!$E$109 -> 2340 | D14: 3人×650万円×1.2
A15: 広告・展示会 | B15: 万円/年 | C15: =INDEX('前提'!$E$127:$N$127,1,$C$11) -> 500 | D15: 前提7-10
A16: 新規拠点 | B16: 拠点/年 | C16: =INDEX('前提'!$E$118:$N$118,1,$C$11) -> 33 | D16: 前提7-1
A17: CAC | B17: 万円/拠点 | C17: =($C$14+$C$15)/$C$16 -> 86.060606 | D17: (営業3人×650万円×1.2＋広告500)÷新規33
A18: 回収月数 | B18: か月 | C18: =$C$17/($C$5/'前提'!$E$6) -> 4.7811448 | D18: CAC÷(1拠点の年の粗利÷12)
A19: LTV÷CAC（計画） | B19: 倍 | C19: =$C$8/$C$17 -> 18.254577 | D19: LTV÷CAC
A20: 継続年数を変えたら
A21: 継続年数 | B21: 単位 | C21: LTV（万円/拠点） | D21: LTV÷CAC（倍） | E21: 式（言葉）
A22: ='前提'!$E$151 -> 3 | B22: 万円・倍 | C22: =$C$5*'前提'!$E$151+$C$6 -> 707 | D22: =($C$5*'前提'!$E$151+$C$6)/$C$17 -> 8.2151408 | E22: 216×継続年数＋59、それをCACで割る
A23: ='前提'!$F$151 -> 5 | B23: 万円・倍 | C23: =$C$5*'前提'!$F$151+$C$6 -> 1139 | D23: =($C$5*'前提'!$F$151+$C$6)/$C$17 -> 13.234859 | E23: 216×継続年数＋59、それをCACで割る
A24: ='前提'!$G$151 -> 7 | B24: 万円・倍 | C24: =$C$5*'前提'!$G$151+$C$6 -> 1571 | D24: =($C$5*'前提'!$G$151+$C$6)/$C$17 -> 18.254577 | E24: 216×継続年数＋59、それをCACで割る
A25: ='前提'!$H$151 -> 10 | B25: 万円・倍 | C25: =$C$5*'前提'!$H$151+$C$6 -> 2219 | D25: =($C$5*'前提'!$H$151+$C$6)/$C$17 -> 25.784155 | E25: 216×継続年数＋59、それをCACで割る
A26: 獲得が難しくなったら（CACが増えた場合）
A27: CACの倍率 | B27: 単位 | C27: CAC（万円/拠点） | D27: LTV÷CAC（倍・計画の年数） | E27: 回収月数（か月） | F27: 式（言葉）
A28: ='前提'!$E$152 -> 1 | B28: 万円・倍・か月 | C28: =$C$17*'前提'!$E$152 -> 86.060606 | D28: =$C$8/($C$17*'前提'!$E$152) -> 18.254577 | E28: =$C$18*'前提'!$E$152 -> 4.7811448 | F28: CAC×倍率
A29: ='前提'!$F$152 -> 2 | B29: 万円・倍・か月 | C29: =$C$17*'前提'!$F$152 -> 172.12121 | D29: =$C$8/($C$17*'前提'!$F$152) -> 9.1272887 | E29: =$C$18*'前提'!$F$152 -> 9.5622896 | F29: CAC×倍率
A30: ='前提'!$G$152 -> 4 | B30: 万円・倍・か月 | C30: =$C$17*'前提'!$G$152 -> 344.24242 | D30: =$C$8/($C$17*'前提'!$G$152) -> 4.5636444 | E30: =$C$18*'前提'!$G$152 -> 19.124579 | F30: CAC×倍率
A31: 注：1〜2年目は創業者が営業するため、CACに創業者の人件費は入れていない（聞かれたらそのまま答える）。
A32: 注：SaaS でよく使われる目安は「LTV÷CACが3倍以上、回収12か月以内」。

Sheet 崩れたとき
A1: 崩れたとき：前提を一つずつ崩した結果（tora_v2.js で計算した値）
A2: 灰色の数字は tora_v2.js の run() で計算した値を貼ったもの。1年目〜5年目は計算詳細版 p.21 と同じ。10年で見た列は run({years:10}) に同じ変更を入れた値（新規−30%は6〜10年目の新規と個社設定も0.7倍）。右の列の通りに前提のつまみを変えると、Excel でも同じ結果になる。
A3: シナリオ | B3: 想定する事態 | C3: 黒字化 （5年で） | D3: 黒字化 （10年で） | E3: 5年目の営業利益 （万円） | F3: 最低の現金 5年で（万円） | G3: 最低の現金 10年で（万円） | H3: 累計回収 （10年で） | I3: Excel で同じ結果を出すには（前提のどこを変えるか）
A4: 計画どおり | B4: ─ | C4: 5年でなし | D4: 6 | E4: -1117 | F4: 6723.5 | G4: 6723.5 | H4: 8 | I4: 初期値のまま
A5: 値段 −20% | B5: 値引きされた | C5: 5年でなし | D5: 7 | E5: -4987 | F5: -1166.5 | G5: -2104.5 | H5: 10年でなし | I5: 8-1 値段の倍率を 0.8
A6: 解約 年20% | B6: 定着しなかった | C6: 5年でなし | D6: 6 | E6: -3061 | F6: 3267.5 | G6: 3267.5 | H6: 10 | I6: 8-2 解約率の上書きに 20%
A7: AI・保存費が2倍 | B7: 処理量が想定より多い | C7: 5年でなし | D7: 8 | E7: -5761 | F7: -2798.5 | G7: -5369.5 | H7: 10年でなし | I7: 8-3 原価の倍率を 2
A8: 年収 +100万円／人 | B8: 採用市場が厳しい | C8: 5年でなし | D8: 6 | E8: -3877 | F8: -1196.5 | G8: -1196.5 | H8: 9 | I8: 8-4 年収の上乗せを 100
A9: 新規 −30%（採用も連動） | B9: 営業が想定より遅い | C9: 5年でなし | D9: 6 | E9: -2572.6957 | F9: 2770.9918 | G9: 2770.9918 | H9: 10 | I9: 7-1 新規拠点を0.7倍して四捨五入（3,9,18,27,33→2,6,13,19,23）、7-7 個社設定を0.7倍、8-5 採用連動のkに 0.7
A10: 新規 −30%（採用は計画どおり） | B10: やってはいけない例 | C10: 5年でなし | D10: 8 | E10: -7572 | F10: -8291.5 | G10: -14626.5 | H10: 10年でなし | I10: 7-1 と 7-7 を上と同じく0.7倍（kは空のまま）
A11: 1拠点15台 | B11: 効果が出た班から追加 | C11: 5 | D11: 5 | E11: 4301 | F11: 10997 | G11: 10997 | H11: 6 | I11: 2-1 台数を 15（リースの構成は12台＋3台）
A12: 全編をクラウドで解析 | B12: やってはいけない例 | C12: 5年でなし | D12: 10年でなし | E12: -35173 | F12: -63104.5 | G12: -374590.5 | H12: 10年でなし | I12: 8-3 原価の倍率を 60÷7.2（1台 月5万円）
A13: 営業の採用を3年目から | B13: 営業の立ち上げを遅らせる | C13: 5年でなし | D13: 6 | E13: -1117 | F13: 7503.5 | G13: 7503.5 | H13: 8 | I13: 6-14 営業の人数を 0,0,1,3,3（2年目の採用をやめる）
A15: 注：計画の余裕は小さい。1拠点10台のままでは5年以内に黒字にならず、値引き・解約の増加・AI費用の増加・年収の上昇はどれも赤字を広げ、最低の現金がマイナスになるものもある。
A16: 注：特に危ないのは、動画を全部クラウドで解析する使い方と、獲得が遅れているのに計画どおり採用すること。守りは、1拠点の台数を増やすことと、採用を拠点数に合わせて遅らせること。
A17: 注：営業の採用を3年目からにすると、2年目の人件費780万円と採用費が浮き、最低の現金は約780万円増える。5年目の営業利益は変わらない（拠点の計画を変えていないため）。
A18: 注：黒字化の年は数字（緑）、「なし」は期間内に黒字にならないこと。マイナスは▲（赤）。

Sheet 資金と黒字倒産
A1: 資金と黒字倒産：自己資金は段階に分けて入れる。黒字でも現金が尽きる場合を先に見る
A2: 資金投入は準備期500万円＋1年目2億円＋3年目5,000万円。このモデルは運転資本・税・償却を含まない簡易計算。下の①〜④は、簡易計算の現金からさらに出ていく額を年ごとに見たもの（計算詳細版 p.23）。
A3: 項目 | B3: 単位 | C3: 1 | D3: 2 | E3: 3 | F3: 4 | G3: 5 | H3: 6 | I3: 7 | J3: 8 | K3: 9 | L3: 10 | M3: 式（言葉）
A4: 資金と現金
A5: 資金投入 | B5: 万円/年 | C5: ='前提'!$E$133 -> 20000 | D5: ='前提'!$F$133 -> 0 | E5: ='前提'!$G$133 -> 5000 | F5: ='前提'!$H$133 -> 0 | G5: ='前提'!$I$133 -> 0 | H5: ='前提'!$J$133 -> 0 | I5: ='前提'!$K$133 -> 0 | J5: ='前提'!$L$133 -> 0 | K5: ='前提'!$M$133 -> 0 | L5: ='前提'!$N$133 -> 0 | M5: 前提7-16
A6: 営業利益 | B6: 万円/年 | C6: ='損益と現金'!$C$27 -> -4843.5 | D6: ='損益と現金'!$D$27 -> -4762.5 | E6: ='損益と現金'!$E$27 -> -3696.5 | F6: ='損益と現金'!$F$27 -> -3857 | G6: ='損益と現金'!$G$27 -> -1117 | H6: ='損益と現金'!$H$27 -> 4522 | I6: ='損益と現金'!$I$27 -> 7883 | J6: ='損益と現金'!$J$27 -> 12005.5 | K6: ='損益と現金'!$K$27 -> 16307 | L6: ='損益と現金'!$L$27 -> 18980.5 | M6: 損益と現金
A7: 期末の現金（簡易計算） | B7: 万円 | C7: ='損益と現金'!$C$30 -> 15156.5 | D7: ='損益と現金'!$D$30 -> 10394 | E7: ='損益と現金'!$E$30 -> 11697.5 | F7: ='損益と現金'!$F$30 -> 7840.5 | G7: ='損益と現金'!$G$30 -> 6723.5 | H7: ='損益と現金'!$H$30 -> 11245.5 | I7: ='損益と現金'!$I$30 -> 19128.5 | J7: ='損益と現金'!$J$30 -> 31134 | K7: ='損益と現金'!$K$30 -> 47441 | L7: ='損益と現金'!$L$30 -> 66421.5 | M7: 損益と現金
A8: 最低残高の目安（その年の販管費の3か月分） | B8: 万円 | C8: ='損益と現金'!$C$25*'前提'!$E$137/'前提'!$E$6 -> 1289.375 | D8: ='損益と現金'!$D$25*'前提'!$E$137/'前提'!$E$6 -> 1790.875 | E8: ='損益と現金'!$E$25*'前提'!$E$137/'前提'!$E$6 -> 2361.2917 | F8: ='損益と現金'!$F$25*'前提'!$E$137/'前提'!$E$6 -> 3541.3333 | G8: ='損益と現金'!$G$25*'前提'!$E$137/'前提'!$E$6 -> 4328.1667 | H8: ='損益と現金'!$H$25*'前提'!$E$137/'前提'!$E$6 -> 4397.8333 | I8: ='損益と現金'!$I$25*'前提'!$E$137/'前提'!$E$6 -> 4999.4167 | J8: ='損益と現金'!$J$25*'前提'!$E$137/'前提'!$E$6 -> 5356.625 | K8: ='損益と現金'!$K$25*'前提'!$E$137/'前提'!$E$6 -> 5585.5833 | L8: ='損益と現金'!$L$25*'前提'!$E$137/'前提'!$E$6 -> 6059.5417 | M8: 販管費×3÷12
A9: 目安との差 | B9: 万円 | C9: =$C$7-$C$8 -> 13867.125 | D9: =$D$7-$D$8 -> 8603.125 | E9: =$E$7-$E$8 -> 9336.2083 | F9: =$F$7-$F$8 -> 4299.1667 | G9: =$G$7-$G$8 -> 2395.3333 | H9: =$H$7-$H$8 -> 6847.6667 | I9: =$I$7-$I$8 -> 14129.083 | J9: =$J$7-$J$8 -> 25777.375 | K9: =$K$7-$K$8 -> 41855.417 | L9: =$L$7-$L$8 -> 60361.958 | M9: 期末の現金−最低残高の目安
A10: 準備期の資金 | B10: 万円 | C10: ='前提'!$E$134 -> 500 | D10: 試作品・実証。準備期に使い切る
A11: 資金投入の合計（準備期を含む） | B11: 万円 | C11: =$C$10+SUM('前提'!$E$133:$N$133) -> 25500 | D11: 500＋2億＋5,000万＝2.55億円
A12: 最低の現金（10年） | B12: 万円 | C12: ='損益と現金'!$C$37 -> 6723.5 | D12: 損益と現金
A13: 参考：4年目の販管費の3か月分 | B13: 万円 | C13: =INDEX('損益と現金'!$C$25:$L$25,1,4)*'前提'!$E$137/'前提'!$E$6 -> 3541.3333 | D13: 計算詳細版 p.21・23 の最低現金のライン
A14: ① 売掛の回収が遅い（月額の後払い・支払いサイト60日）
A15: 売掛金の残高（年末） | B15: 万円 | C15: ='拠点と売上'!$C$22*'前提'!$E$154/'前提'!$E$8 -> 197.26027 | D15: ='拠点と売上'!$D$22*'前提'!$E$154/'前提'!$E$8 -> 789.0411 | E15: ='拠点と売上'!$E$22*'前提'!$E$154/'前提'!$E$8 -> 1758.9041 | F15: ='拠点と売上'!$F$22*'前提'!$E$154/'前提'!$E$8 -> 2926.0274 | G15: ='拠点と売上'!$G$22*'前提'!$E$154/'前提'!$E$8 -> 4421.9178 | H15: ='拠点と売上'!$H$22*'前提'!$E$154/'前提'!$E$8 -> 5835.6164 | I15: ='拠点と売上'!$I$22*'前提'!$E$154/'前提'!$E$8 -> 7200 | J15: ='拠点と売上'!$J$22*'前提'!$E$154/'前提'!$E$8 -> 8515.0685 | K15: ='拠点と売上'!$K$22*'前提'!$E$154/'前提'!$E$8 -> 9715.0685 | L15: ='拠点と売上'!$L$22*'前提'!$E$154/'前提'!$E$8 -> 10767.123 | M15: 売上×60÷365
A16: その年に増えた売掛（現金が減る額） | B16: 万円/年 | C16: =$C$15 -> 197.26027 | D16: =$D$15-$C$15 -> 591.78082 | E16: =$E$15-$D$15 -> 969.86301 | F16: =$F$15-$E$15 -> 1167.1233 | G16: =$G$15-$F$15 -> 1495.8904 | H16: =$H$15-$G$15 -> 1413.6986 | I16: =$I$15-$H$15 -> 1364.3836 | J16: =$J$15-$I$15 -> 1315.0685 | K16: =$K$15-$J$15 -> 1200 | L16: =$L$15-$K$15 -> 1052.0548 | M16: 今年の残高−前の年の残高
A17: 売掛を引いた現金 | B17: 万円 | C17: =$C$7-$C$15 -> 14959.24 | D17: =$D$7-$D$15 -> 9604.9589 | E17: =$E$7-$E$15 -> 9938.5959 | F17: =$F$7-$F$15 -> 4914.4726 | G17: =$G$7-$G$15 -> 2301.5822 | H17: =$H$7-$H$15 -> 5409.8836 | I17: =$I$7-$I$15 -> 11928.5 | J17: =$J$7-$J$15 -> 22618.932 | K17: =$K$7-$K$15 -> 37725.932 | L17: =$L$7-$L$15 -> 55654.377 | M17: 期末の現金−売掛金の残高
A18: ② 採用の先行（拠点が増える前に人件費が出る）
A19: 翌年の人件費の増加 | B19: 万円 | C19: ='体制と人件費'!$D$48-'体制と人件費'!$C$48 -> 2604 | D19: ='体制と人件費'!$E$48-'体制と人件費'!$D$48 -> 3204 | E19: ='体制と人件費'!$F$48-'体制と人件費'!$E$48 -> 4800 | F19: ='体制と人件費'!$G$48-'体制と人件費'!$F$48 -> 3840 | G19: ='体制と人件費'!$H$48-'体制と人件費'!$G$48 -> 960 | H19: ='体制と人件費'!$I$48-'体制と人件費'!$H$48 -> 2280 | I19: ='体制と人件費'!$J$48-'体制と人件費'!$I$48 -> 1620 | J19: ='体制と人件費'!$K$48-'体制と人件費'!$J$48 -> 840 | K19: ='体制と人件費'!$L$48-'体制と人件費'!$K$48 -> 1740 | L19: ─ | M19: 翌年の人件費−その年の人件費（10年目は翌年の計画がないので「─」）
A20: 先に出る人件費 | B20: 万円 | C20: =MAX(0,$C$19)*'前提'!$E$155/'前提'!$E$6 -> 651 | D20: =MAX(0,$D$19)*'前提'!$E$155/'前提'!$E$6 -> 801 | E20: =MAX(0,$E$19)*'前提'!$E$155/'前提'!$E$6 -> 1200 | F20: =MAX(0,$F$19)*'前提'!$E$155/'前提'!$E$6 -> 960 | G20: =MAX(0,$G$19)*'前提'!$E$155/'前提'!$E$6 -> 240 | H20: =MAX(0,$H$19)*'前提'!$E$155/'前提'!$E$6 -> 570 | I20: =MAX(0,$I$19)*'前提'!$E$155/'前提'!$E$6 -> 405 | J20: =MAX(0,$J$19)*'前提'!$E$155/'前提'!$E$6 -> 210 | K20: =MAX(0,$K$19)*'前提'!$E$155/'前提'!$E$6 -> 435 | L20: ─ | M20: 翌年の増加×3か月÷12
A21: 先行分を引いた現金 | B21: 万円 | C21: =$C$7-$C$20 -> 14505.5 | D21: =$D$7-$D$20 -> 9593 | E21: =$E$7-$E$20 -> 10497.5 | F21: =$F$7-$F$20 -> 6880.5 | G21: =$G$7-$G$20 -> 6483.5 | H21: =$H$7-$H$20 -> 10675.5 | I21: =$I$7-$I$20 -> 18723.5 | J21: =$J$7-$J$20 -> 30924 | K21: =$K$7-$K$20 -> 47006 | L21: ─ | M21: 期末の現金−先に出る人件費
A22: ③ 端末込みの料金にした場合の端末の先払い（3年目から）
A23: 新しく買う端末 | B23: 台 | C23: =IF(C$3>='前提'!$E$156,'拠点と売上'!$C$8*'前提'!$E$21,0) -> 0 | D23: =IF(D$3>='前提'!$E$156,'拠点と売上'!$D$8*'前提'!$E$21,0) -> 0 | E23: =IF(E$3>='前提'!$E$156,'拠点と売上'!$E$8*'前提'!$E$21,0) -> 180 | F23: =IF(F$3>='前提'!$E$156,'拠点と売上'!$F$8*'前提'!$E$21,0) -> 270 | G23: =IF(G$3>='前提'!$E$156,'拠点と売上'!$G$8*'前提'!$E$21,0) -> 330 | H23: =IF(H$3>='前提'!$E$156,'拠点と売上'!$H$8*'前提'!$E$21,0) -> 360 | I23: =IF(I$3>='前提'!$E$156,'拠点と売上'!$I$8*'前提'!$E$21,0) -> 380 | J23: =IF(J$3>='前提'!$E$156,'拠点と売上'!$J$8*'前提'!$E$21,0) -> 400 | K23: =IF(K$3>='前提'!$E$156,'拠点と売上'!$K$8*'前提'!$E$21,0) -> 400 | L23: =IF(L$3>='前提'!$E$156,'拠点と売上'!$L$8*'前提'!$E$21,0) -> 400 | M23: 3年目から 新規拠点×10台
A24: 端末の先払い | B24: 万円/年 | C24: =$C$23*'前提'!$E$157 -> 0 | D24: =$D$23*'前提'!$E$157 -> 0 | E24: =$E$23*'前提'!$E$157 -> 1440 | F24: =$F$23*'前提'!$E$157 -> 2160 | G24: =$G$23*'前提'!$E$157 -> 2640 | H24: =$H$23*'前提'!$E$157 -> 2880 | I24: =$I$23*'前提'!$E$157 -> 3040 | J24: =$J$23*'前提'!$E$157 -> 3200 | K24: =$K$23*'前提'!$E$157 -> 3200 | L24: =$L$23*'前提'!$E$157 -> 3200 | M24: 新しく買う端末×8万円
A25: まだ回収していない端末代（年末） | B25: 万円 | C25: =$C$24*MAX(0,1-0/'前提'!$E$158) -> 0 | D25: =$D$24*MAX(0,1-0/'前提'!$E$158)+$C$24*MAX(0,1-1/'前提'!$E$158) -> 0 | E25: =$E$24*MAX(0,1-0/'前提'!$E$158)+$D$24*MAX(0,1-1/'前提'!$E$158)+$C$24*MAX(0,1-2/'前提'!$E$158) -> 1440 | F25: =$F$24*MAX(0,1-0/'前提'!$E$158)+$E$24*MAX(0,1-1/'前提'!$E$158)+$D$24*MAX(0,1-2/'前提'!$E$158)+$C$24*MAX(0,1-3/'前提'!$E$158) -> 3120 | G25: =$G$24*MAX(0,1-0/'前提'!$E$158)+$F$24*MAX(0,1-1/'前提'!$E$158)+$E$24*MAX(0,1-2/'前提'!$E$158)+$D$24*MAX(0,1-3/'前提'!$E$158) -> 4560 | H25: =$H$24*MAX(0,1-0/'前提'!$E$158)+$G$24*MAX(0,1-1/'前提'!$E$158)+$F$24*MAX(0,1-2/'前提'!$E$158)+$E$24*MAX(0,1-3/'前提'!$E$158) -> 5360 | I25: =$I$24*MAX(0,1-0/'前提'!$E$158)+$H$24*MAX(0,1-1/'前提'!$E$158)+$G$24*MAX(0,1-2/'前提'!$E$158)+$F$24*MAX(0,1-3/'前提'!$E$158) -> 5840 | J25: =$J$24*MAX(0,1-0/'前提'!$E$158)+$I$24*MAX(0,1-1/'前提'!$E$158)+$H$24*MAX(0,1-2/'前提'!$E$158)+$G$24*MAX(0,1-3/'前提'!$E$158) -> 6186.6667 | K25: =$K$24*MAX(0,1-0/'前提'!$E$158)+$J$24*MAX(0,1-1/'前提'!$E$158)+$I$24*MAX(0,1-2/'前提'!$E$158)+$H$24*MAX(0,1-3/'前提'!$E$158) -> 6346.6667 | L25: =$L$24*MAX(0,1-0/'前提'!$E$158)+$K$24*MAX(0,1-1/'前提'!$E$158)+$J$24*MAX(0,1-2/'前提'!$E$158)+$I$24*MAX(0,1-3/'前提'!$E$158) -> 6400 | M25: その年に買った分＋1年前の分×(1−1/3)＋2年前の分×(1−2/3)（翌年から3年で均等に回収）
A26: 未回収分を引いた現金 | B26: 万円 | C26: =$C$7-$C$25 -> 15156.5 | D26: =$D$7-$D$25 -> 10394 | E26: =$E$7-$E$25 -> 10257.5 | F26: =$F$7-$F$25 -> 4720.5 | G26: =$G$7-$G$25 -> 2163.5 | H26: =$H$7-$H$25 -> 5885.5 | I26: =$I$7-$I$25 -> 13288.5 | J26: =$J$7-$J$25 -> 24947.333 | K26: =$K$7-$K$25 -> 41094.333 | L26: =$L$7-$L$25 -> 60021.5 | M26: 期末の現金−まだ回収していない端末代
A27: ④ 急な拠点増で導入支援の人件費が先に出る（新規が計画より5割多い場合）
A28: 計画より多い新規拠点 | B28: 拠点 | C28: ='拠点と売上'!$C$8*'前提'!$E$159 -> 1.5 | D28: ='拠点と売上'!$D$8*'前提'!$E$159 -> 4.5 | E28: ='拠点と売上'!$E$8*'前提'!$E$159 -> 9 | F28: ='拠点と売上'!$F$8*'前提'!$E$159 -> 13.5 | G28: ='拠点と売上'!$G$8*'前提'!$E$159 -> 16.5 | H28: ='拠点と売上'!$H$8*'前提'!$E$159 -> 18 | I28: ='拠点と売上'!$I$8*'前提'!$E$159 -> 19 | J28: ='拠点と売上'!$J$8*'前提'!$E$159 -> 20 | K28: ='拠点と売上'!$K$8*'前提'!$E$159 -> 20 | L28: ='拠点と売上'!$L$8*'前提'!$E$159 -> 20 | M28: 新規×50%
A29: 先に出る導入支援の原価 | B29: 万円 | C29: =$C$28*'導入支援'!$C$19 -> 211.5 | D29: =$D$28*'導入支援'!$C$19 -> 634.5 | E29: =$E$28*'導入支援'!$C$19 -> 1269 | F29: =$F$28*'導入支援'!$C$19 -> 1903.5 | G29: =$G$28*'導入支援'!$C$19 -> 2326.5 | H29: =$H$28*'導入支援'!$C$19 -> 2538 | I29: =$I$28*'導入支援'!$C$19 -> 2679 | J29: =$J$28*'導入支援'!$C$19 -> 2820 | K29: =$K$28*'導入支援'!$C$19 -> 2820 | L29: =$L$28*'導入支援'!$C$19 -> 2820 | M29: 多い新規×141万円
A30: 着手金で先に入る額 | B30: 万円 | C30: =$C$28*'前提'!$E$25*'前提'!$E$160 -> 150 | D30: =$D$28*'前提'!$E$25*'前提'!$E$160 -> 450 | E30: =$E$28*'前提'!$E$25*'前提'!$E$160 -> 900 | F30: =$F$28*'前提'!$E$25*'前提'!$E$160 -> 1350 | G30: =$G$28*'前提'!$E$25*'前提'!$E$160 -> 1650 | H30: =$H$28*'前提'!$E$25*'前提'!$E$160 -> 1800 | I30: =$I$28*'前提'!$E$25*'前提'!$E$160 -> 1900 | J30: =$J$28*'前提'!$E$25*'前提'!$E$160 -> 2000 | K30: =$K$28*'前提'!$E$25*'前提'!$E$160 -> 2000 | L30: =$L$28*'前提'!$E$25*'前提'!$E$160 -> 2000 | M30: 多い新規×200万円×50%
A31: 差し引き先に出る現金 | B31: 万円 | C31: =$C$29-$C$30 -> 61.5 | D31: =$D$29-$D$30 -> 184.5 | E31: =$E$29-$E$30 -> 369 | F31: =$F$29-$F$30 -> 553.5 | G31: =$G$29-$G$30 -> 676.5 | H31: =$H$29-$H$30 -> 738 | I31: =$I$29-$I$30 -> 779 | J31: =$J$29-$J$30 -> 820 | K31: =$K$29-$K$30 -> 820 | L31: =$L$29-$L$30 -> 820 | M31: 原価−着手金
A32: 追加で要る導入コンサルタント | B32: 人 | C32: =$C$28/'前提'!$E$90 -> 0.25 | D32: =$D$28/'前提'!$E$90 -> 0.75 | E32: =$E$28/'前提'!$E$90 -> 1.5 | F32: =$F$28/'前提'!$E$90 -> 2.25 | G32: =$G$28/'前提'!$E$90 -> 2.75 | H32: =$H$28/'前提'!$E$90 -> 3 | I32: =$I$28/'前提'!$E$90 -> 3.1666667 | J32: =$J$28/'前提'!$E$90 -> 3.3333333 | K32: =$K$28/'前提'!$E$90 -> 3.3333333 | L32: =$L$28/'前提'!$E$90 -> 3.3333333 | M32: 多い新規÷6（採用はさらに先行する）
A33: 差し引きを引いた現金 | B33: 万円 | C33: =$C$7-$C$31 -> 15095 | D33: =$D$7-$D$31 -> 10209.5 | E33: =$E$7-$E$31 -> 11328.5 | F33: =$F$7-$F$31 -> 7287 | G33: =$G$7-$G$31 -> 6047 | H33: =$H$7-$H$31 -> 10507.5 | I33: =$I$7-$I$31 -> 18349.5 | J33: =$J$7-$J$31 -> 30314 | K33: =$K$7-$K$31 -> 46621 | L33: =$L$7-$L$31 -> 65601.5 | M33: 期末の現金−差し引き先に出る現金
A34: ①〜④のいちばん低い現金
A35: ① 売掛を引いた現金の最低 | B35: 万円 | C35: =MIN($C$17:$L$17) -> 2301.5822
A36: ② 先行分を引いた現金の最低 | B36: 万円 | C36: =MIN($C$21:$K$21) -> 6483.5 | D36: 1〜9年目
A37: ③ 未回収分を引いた現金の最低 | B37: 万円 | C37: =MIN($C$26:$L$26) -> 2163.5
A38: ④ 差し引きを引いた現金の最低 | B38: 万円 | C38: =MIN($C$33:$L$33) -> 6047
A39: ① 最低残高の目安（販管費3か月分）を下回る年の数 | B39: 年 | C39: =SUMPRODUCT(--($C$17:$L$17<$C$8:$L$8)) -> 1 | D39: その年の販管費×3÷12 を下回る年を数える
A40: ② 最低残高の目安（販管費3か月分）を下回る年の数 | B40: 年 | C40: =SUMPRODUCT(--($C$21:$K$21<$C$8:$K$8)) -> 0 | D40: その年の販管費×3÷12 を下回る年を数える
A41: ③ 最低残高の目安（販管費3か月分）を下回る年の数 | B41: 年 | C41: =SUMPRODUCT(--($C$26:$L$26<$C$8:$L$8)) -> 1 | D41: その年の販管費×3÷12 を下回る年を数える
A42: ④ 最低残高の目安（販管費3か月分）を下回る年の数 | B42: 年 | C42: =SUMPRODUCT(--($C$33:$L$33<$C$8:$L$8)) -> 0 | D42: その年の販管費×3÷12 を下回る年を数える
A43: 黒字倒産が起こる場合と備え
A44: ① 売掛の回収が遅い：月額の後払いで支払いサイト60日なら、売上×60÷365の運転資金が要る（5年目で約4,400万円）。備え：利用料は年額前払い。導入支援は着手金50%。
A45: ② 採用の先行：導入コンサルタントや営業を、拠点が増える前に採ると人件費が先に出る。備え：採用は拠点数の実績に合わせて遅らせる（採用連動。前提8-5）。期末で社員1人約4拠点の見込みが立ってから採る。
A46: ③ 端末込みの料金：当社が端末をまとめて買うと、1台8万円×新規の台数を先に払い、料金で3年かけて回収する。備え：本契約はお客様名義のリースを基本にし、端末込みは現金に余裕がある年だけ選べるようにする。
A47: ④ 急な拠点増：新規が計画より多いと、導入支援の人件費と交通費が売上より先に出て、導入コンサルタントの採用も先に要る。備え：着手金50%。新規の受け入れは導入コンサルタントの人数×6を上限にする。
A48: ⑤ 税金・賞与の支払い月：賞与は年2回、法人税等は決算から2か月以内にまとめて出る。黒字化した後は中間納付もある（このモデルは税を含まない）。備え：資金繰り表で12か月先までの入出金を管理する。
A49: 共通の備え：自己資金は段階に分けて入れる（準備期500万円→実証に合格したら1年目2億円→3年目に継続率と台数の線を越えていれば5,000万円）。最低残高は販管費の3か月分を下回らないようにし、下回りそうなら先に採用を止める。
A50: 注：このモデルは運転資本（売掛・前受）・税・償却を含まない簡易計算。①〜④は互いに重なりうる。

Sheet 市場規模
A1: 市場規模：ターゲット市場（電気工事・電気通信工事の中堅以上）約141億円
A2: 業種×規模で、顧客数×1社の年額×年1回を足し上げる。tora_market.js の SEG・SOM・estimate() と同じ（計算詳細版 p.24・25）。
A3: 業種 | B3: 規模 | C3: 顧客数（社） | D3: 1社の年額（万円/年） | E3: ターゲット（1＝入れる） | F3: 市場（万円/年） | G3: 市場（億円/年） | H3: 確度 | I3: メモ・式（言葉）
A4: 電線・ケーブル工場 | B4: 大（300人以上） | C4: ='前提'!$E$164 -> 40 | D4: ='前提'!$F$164 -> 500 | E4: ='前提'!$G$164 -> 0 | F4: =C4*D4 -> 20000 | G4: =F4/'前提'!$E$9 -> 2 | H4: 仮定 | I4: 15ライン相当。353事業所の内訳は仮定。顧客数×1社の年額
A5: 電線・ケーブル工場 | B5: 中（30〜299人） | C5: ='前提'!$E$165 -> 150 | D5: ='前提'!$F$165 -> 300 | E5: ='前提'!$G$165 -> 0 | F5: =C5*D5 -> 45000 | G5: =F5/'前提'!$E$9 -> 4.5 | H5: 仮定 | I5: 隣接市場（成長期以降）。顧客数×1社の年額
A6: 電線・ケーブル工場 | B6: 小（30人未満） | C6: ='前提'!$E$166 -> 163 | D6: ='前提'!$F$166 -> 120 | E6: ='前提'!$G$166 -> 0 | F6: =C6*D6 -> 19560 | G6: =F6/'前提'!$E$9 -> 1.956 | H6: 仮定 | I6: 回収条件（月105人時）を満たしにくい。顧客数×1社の年額
A7: 電気工事会社 | B7: 大（300人以上） | C7: ='前提'!$E$167 -> 300 | D7: ='前提'!$F$167 -> 1500 | E7: ='前提'!$G$167 -> 1 | F7: =C7*D7 -> 450000 | G7: =F7/'前提'!$E$9 -> 45 | H7: 仮定 | I7: 支店5拠点×300万円。顧客数×1社の年額
A8: 電気工事会社 | B8: 中（30〜299人） | C8: ='前提'!$E$168 -> 2100 | D8: ='前提'!$F$168 -> 300 | E8: ='前提'!$G$168 -> 1 | F8: =C8*D8 -> 630000 | G8: =F8/'前提'!$E$9 -> 63 | H8: 仮定 | I8: 資本金5,000万円以上 約2,400社の内訳は仮定。顧客数×1社の年額
A9: 電気工事会社 | B9: 小（30人未満） | C9: ='前提'!$E$169 -> 63097 | D9: ='前提'!$F$169 -> 60 | E9: ='前提'!$G$169 -> 0 | F9: =C9*D9 -> 3785820 | G9: =F9/'前提'!$E$9 -> 378.582 | H9: 統計−仮定 | I9: 65,497社の残り。ライト版を想定（65,497社−大300−中2,100）。顧客数×1社の年額
A10: 電気通信工事会社 | B10: 大（300人以上） | C10: ='前提'!$E$170 -> 100 | D10: ='前提'!$F$170 -> 1500 | E10: ='前提'!$G$170 -> 1 | F10: =C10*D10 -> 150000 | G10: =F10/'前提'!$E$9 -> 15 | H10: 仮定 | I10: 支店5拠点×300万円。顧客数×1社の年額
A11: 電気通信工事会社 | B11: 中（30〜299人） | C11: ='前提'!$E$171 -> 600 | D11: ='前提'!$F$171 -> 300 | E11: ='前提'!$G$171 -> 1 | F11: =C11*D11 -> 180000 | G11: =F11/'前提'!$E$9 -> 18 | H11: 仮定 | I11: 同規模層 約700社の内訳は仮定。顧客数×1社の年額
A12: 全セルの合計（参考） | C12: =SUM(C4:C11) -> 66550 | F12: =SUM(F4:F11) -> 5280380 | G12: =F12/'前提'!$E$9 -> 528.038 | I12: 8つのセルの合計（電線工場と小規模を含む）
A13: ターゲット市場（ターゲット＝1のセル） | C13: =SUMPRODUCT(E4:E11,C4:C11) -> 3100 | F13: =SUMPRODUCT(E4:E11,F4:F11) -> 1410000 | G13: =F13/'前提'!$E$9 -> 141 | I13: 電気工事・電気通信工事の大と中。顧客数×年額をターゲットのセルだけ足す
A15: SOM（1〜5年目に狙うセルの漏斗）
A16: セル | B16: 顧客数（社） | C16: 地域の割合 | D16: 会える率 | E16: 成約率 | F16: 1社の拠点数 | G16: 獲得する拠点 | H16: 売上（万円/年） | I16: 式（言葉）
A17: 電気工事会社・中（30〜299人） | B17: =$C$8 -> 2100 | C17: ='前提'!$E$173 -> 0.35 | D17: ='前提'!$F$173 -> 0.45 | E17: ='前提'!$G$173 -> 0.25 | F17: ='前提'!$H$173 -> 1 | G17: =B17*C17*D17*E17*F17 -> 82.6875 | H17: =G17*'値段と原価'!$C$9 -> 24806.25 | I17: 顧客数×地域×会える率×成約率×1社の拠点数。売上＝拠点×300万円。関東の比率35%（川崎拠点から日帰り圏）。業界団体・展示会・紹介で45%に会う
A18: 電気工事会社・大（300人以上） | B18: =$C$7 -> 300 | C18: ='前提'!$E$174 -> 0.35 | D18: ='前提'!$F$174 -> 0.1 | E18: ='前提'!$G$174 -> 0.1 | F18: ='前提'!$H$174 -> 5 | G18: =B18*C18*D18*E18*F18 -> 5.25 | H18: =G18*'値段と原価'!$C$9 -> 1575 | I18: 顧客数×地域×会える率×成約率×1社の拠点数。売上＝拠点×300万円。大手1社を目玉の事例に（支店5拠点）。協力会社へ波及する
A19: SOM の合計 | G19: =SUM(G17:G18) -> 87.9375 | H19: =SUM(H17:H18) -> 26381.25 | I19: 獲得する拠点の合計と売上（約88拠点・約2.64億円）
A20: 5年目の売上（期末の拠点×300万円）÷ターゲット市場 | G20: ='拠点と売上'!$G$9*'値段と原価'!$C$9/$F$13 -> 0.017234043 | I20: 81拠点×300万円÷141億円
A22: 参考：小規模向けのライト版（基盤＋3台）で一部を取れた場合の上振れ（計画に入れない）
A23: 取れる割合 | B23: 小規模の電気工事会社（社） | C23: 取れる社数（社） | D23: ライト版の年額（万円/年） | E23: 売上（万円/年） | F23: 売上（億円/年） | I23: 式（言葉）
A24: ='前提'!$E$176 -> 0.001 | B24: =$C$9 -> 63097 | C24: =A24*B24 -> 63.097 | D24: ='前提'!$E$23+'前提'!$E$24*'前提'!$E$175 -> 132 | E24: =C24*D24 -> 8328.804 | F24: =E24/'前提'!$E$9 -> 0.8328804 | I24: 小規模の社数×取れる割合×(基盤60＋端末24×3台)
A25: ='前提'!$F$176 -> 0.005 | B25: =$C$9 -> 63097 | C25: =A25*B25 -> 315.485 | D25: ='前提'!$E$23+'前提'!$E$24*'前提'!$E$175 -> 132 | E25: =C25*D25 -> 41644.02 | F25: =E25/'前提'!$E$9 -> 4.164402 | I25: 小規模の社数×取れる割合×(基盤60＋端末24×3台)
A26: ='前提'!$G$176 -> 0.01 | B26: =$C$9 -> 63097 | C26: =A26*B26 -> 630.97 | D26: ='前提'!$E$23+'前提'!$E$24*'前提'!$E$175 -> 132 | E26: =C26*D26 -> 83288.04 | F26: =E26/'前提'!$E$9 -> 8.328804 | I26: 小規模の社数×取れる割合×(基盤60＋端末24×3台)
A28: 注：65,497社は国の統計（建設業許可業者数調査）。大・中・小の内訳は仮定で、業界団体の名簿と経済センサスで数え直す。
A29: 注：小規模（30人未満）を外すのは、書類が少ないからではなく、1拠点10台が要らないため。全体の表の小規模の年額60万円は tora_market.js の置き方（さらに小さい構成）。
A30: 注：ライト版は計画に入れない上振れ。取れる割合は仮定。

Sheet 照合
A1: 照合：Excel の結果と tora_v2.js の値（node で計算して貼った値）
A2: E列＝このブックの式の結果、F列＝tora_v2.js の値（灰色・貼り付け）。差の絶対値が前提12-1以下なら「一致」。前提のつまみ（8-1〜8-6）が初期値のときに一致する。つまみを動かすと「不一致」になるのが正しい。
A3: 区分 | B3: 項目 | C3: 年 | D3: 単位 | E3: Excel の値 | F3: tora_v2.js の値 | G3: 差（Excel−JS） | H3: 判定 | I3: Excel のセル
A4: 合計 | B4: ="照合 "&COUNTA(H5:H145)&" 項目：一致 "&COUNTIF(H5:H145,"一致")&"・不一致 "&COUNTIF(H5:H145,"不一致") -> 照合 141 項目：一致 141・不一致 0 | H4: =IF(COUNTIF(H5:H145,"不一致")=0,"すべて一致","不一致あり") -> すべて一致
A5: 時給 | B5: 職長の1時間の人件費 | D5: 円/時間 | E5: ='時給'!$B$9 -> 3326.4706 | F5: 3326.4706 | G5: =IF(AND(ISNUMBER(E5),ISNUMBER(F5)),E5-F5,"─") -> 0 | H5: =IF(ISNUMBER(G5),IF(ABS(G5)<='前提'!$E$178,"一致","不一致"),IF(E5=F5,"一致","不一致")) -> 一致 | I5: 時給 B9
A6: 時給 | B6: 施工管理者の1時間の人件費 | D6: 円/時間 | E6: ='時給'!$C$9 -> 3743.0341 | F6: 3743.0341 | G6: =IF(AND(ISNUMBER(E6),ISNUMBER(F6)),E6-F6,"─") -> 0 | H6: =IF(ISNUMBER(G6),IF(ABS(G6)<='前提'!$E$178,"一致","不一致"),IF(E6=F6,"一致","不一致")) -> 一致 | I6: 時給 C9
A7: お客様 | B7: 1台1日の効果 | D7: 万円/台/日 | E7: ='お客様の効果'!$C$10 -> 0.20792957 | F7: 0.20792957 | G7: =IF(AND(ISNUMBER(E7),ISNUMBER(F7)),E7-F7,"─") -> 0 | H7: =IF(ISNUMBER(G7),IF(ABS(G7)<='前提'!$E$178,"一致","不一致"),IF(E7=F7,"一致","不一致")) -> 一致 | I7: お客様の効果 C10
A8: お客様 | B8: お客様の効果（年） | D8: 万円/年 | E8: ='お客様の効果'!$C$14 -> 499.03096 | F8: 499.03096 | G8: =IF(AND(ISNUMBER(E8),ISNUMBER(F8)),E8-F8,"─") -> 0 | H8: =IF(ISNUMBER(G8),IF(ABS(G8)<='前提'!$E$178,"一致","不一致"),IF(E8=F8,"一致","不一致")) -> 一致 | I8: お客様の効果 C14
A9: お客様 | B9: 浮く時間 | D9: 時間/年 | E9: ='お客様の効果'!$C$17 -> 1400 | F9: 1400 | G9: =IF(AND(ISNUMBER(E9),ISNUMBER(F9)),E9-F9,"─") -> 0 | H9: =IF(ISNUMBER(G9),IF(ABS(G9)<='前提'!$E$178,"一致","不一致"),IF(E9=F9,"一致","不一致")) -> 一致 | I9: お客様の効果 C17
A10: お客様 | B10: お客様の支払い | D10: 万円/年 | E10: ='お客様の効果'!$C$25 -> 331.68 | F10: 331.68 | G10: =IF(AND(ISNUMBER(E10),ISNUMBER(F10)),E10-F10,"─") -> 0 | H10: =IF(ISNUMBER(G10),IF(ABS(G10)<='前提'!$E$178,"一致","不一致"),IF(E10=F10,"一致","不一致")) -> 一致 | I10: お客様の効果 C25
A11: お客様 | B11: リースの合計 | D11: 万円/年 | E11: ='お客様の効果'!$C$24 -> 31.68 | F11: 31.68 | G11: =IF(AND(ISNUMBER(E11),ISNUMBER(F11)),E11-F11,"─") -> 0 | H11: =IF(ISNUMBER(G11),IF(ABS(G11)<='前提'!$E$178,"一致","不一致"),IF(E11=F11,"一致","不一致")) -> 一致 | I11: お客様の効果 C24
A12: お客様 | B12: 倍率 | D12: 倍 | E12: ='お客様の効果'!$C$26 -> 1.5045555 | F12: 1.5045555 | G12: =IF(AND(ISNUMBER(E12),ISNUMBER(F12)),E12-F12,"─") -> 0 | H12: =IF(ISNUMBER(G12),IF(ABS(G12)<='前提'!$E$178,"一致","不一致"),IF(E12=F12,"一致","不一致")) -> 一致 | I12: お客様の効果 C26
A13: お客様 | B13: 元が取れる分 | D13: 分/台/日 | E13: ='お客様の効果'!$C$30 -> 23.262685 | F13: 23.262685 | G13: =IF(AND(ISNUMBER(E13),ISNUMBER(F13)),E13-F13,"─") -> 0 | H13: =IF(ISNUMBER(G13),IF(ABS(G13)<='前提'!$E$178,"一致","不一致"),IF(E13=F13,"一致","不一致")) -> 一致 | I13: お客様の効果 C30
A14: お客様 | B14: 手戻りの削減（参考） | D14: 万円/年 | E14: ='お客様の効果'!$C$49 -> 360 | F14: 360 | G14: =IF(AND(ISNUMBER(E14),ISNUMBER(F14)),E14-F14,"─") -> 0 | H14: =IF(ISNUMBER(G14),IF(ABS(G14)<='前提'!$E$178,"一致","不一致"),IF(E14=F14,"一致","不一致")) -> 一致 | I14: お客様の効果 C49
A15: 値段と原価 | B15: 1拠点の利用料 | D15: 万円/年 | E15: ='値段と原価'!$C$8 -> 300 | F15: 300 | G15: =IF(AND(ISNUMBER(E15),ISNUMBER(F15)),E15-F15,"─") -> 0 | H15: =IF(ISNUMBER(G15),IF(ABS(G15)<='前提'!$E$178,"一致","不一致"),IF(E15=F15,"一致","不一致")) -> 一致 | I15: 値段と原価 C8
A16: 値段と原価 | B16: 1台の原価（年） | D16: 万円/年/台 | E16: ='値段と原価'!$C$12 -> 7.2 | F16: 7.2 | G16: =IF(AND(ISNUMBER(E16),ISNUMBER(F16)),E16-F16,"─") -> 0 | H16: =IF(ISNUMBER(G16),IF(ABS(G16)<='前提'!$E$178,"一致","不一致"),IF(E16=F16,"一致","不一致")) -> 一致 | I16: 値段と原価 C12
A17: 値段と原価 | B17: 1拠点の原価 | D17: 万円/年 | E17: ='値段と原価'!$C$14 -> 84 | F17: 84 | G17: =IF(AND(ISNUMBER(E17),ISNUMBER(F17)),E17-F17,"─") -> 0 | H17: =IF(ISNUMBER(G17),IF(ABS(G17)<='前提'!$E$178,"一致","不一致"),IF(E17=F17,"一致","不一致")) -> 一致 | I17: 値段と原価 C14
A18: 値段と原価 | B18: 1拠点の粗利 | D18: 万円/年 | E18: ='値段と原価'!$C$15 -> 216 | F18: 216 | G18: =IF(AND(ISNUMBER(E18),ISNUMBER(F18)),E18-F18,"─") -> 0 | H18: =IF(ISNUMBER(G18),IF(ABS(G18)<='前提'!$E$178,"一致","不一致"),IF(E18=F18,"一致","不一致")) -> 一致 | I18: 値段と原価 C15
A19: 値段と原価 | B19: 粗利率（利用料） | D19: 割合 | E19: ='値段と原価'!$C$16 -> 0.72 | F19: 0.72 | G19: =IF(AND(ISNUMBER(E19),ISNUMBER(F19)),E19-F19,"─") -> 0 | H19: =IF(ISNUMBER(G19),IF(ABS(G19)<='前提'!$E$178,"一致","不一致"),IF(E19=F19,"一致","不一致")) -> 一致 | I19: 値段と原価 C16
A20: 値段と原価 | B20: 粗利率：5台・大事な場面だけ | D20: 割合 | E20: ='値段と原価'!$D$19 -> 0.73333333 | F20: 0.73333333 | G20: =IF(AND(ISNUMBER(E20),ISNUMBER(F20)),E20-F20,"─") -> 0 | H20: =IF(ISNUMBER(G20),IF(ABS(G20)<='前提'!$E$178,"一致","不一致"),IF(E20=F20,"一致","不一致")) -> 一致 | I20: 値段と原価 D19
A21: 値段と原価 | B21: 粗利率：5台・全編を毎秒解析 | D21: 割合 | E21: ='値段と原価'!$E$19 -> -0.73333333 | F21: -0.73333333 | G21: =IF(AND(ISNUMBER(E21),ISNUMBER(F21)),E21-F21,"─") -> 0 | H21: =IF(ISNUMBER(G21),IF(ABS(G21)<='前提'!$E$178,"一致","不一致"),IF(E21=F21,"一致","不一致")) -> 一致 | I21: 値段と原価 E19
A22: 値段と原価 | B22: 粗利率：10台・大事な場面だけ | D22: 割合 | E22: ='値段と原価'!$D$20 -> 0.72 | F22: 0.72 | G22: =IF(AND(ISNUMBER(E22),ISNUMBER(F22)),E22-F22,"─") -> 0 | H22: =IF(ISNUMBER(G22),IF(ABS(G22)<='前提'!$E$178,"一致","不一致"),IF(E22=F22,"一致","不一致")) -> 一致 | I22: 値段と原価 D20
A23: 値段と原価 | B23: 粗利率：10台・全編を毎秒解析 | D23: 割合 | E23: ='値段と原価'!$E$20 -> -1.04 | F23: -1.04 | G23: =IF(AND(ISNUMBER(E23),ISNUMBER(F23)),E23-F23,"─") -> 0 | H23: =IF(ISNUMBER(G23),IF(ABS(G23)<='前提'!$E$178,"一致","不一致"),IF(E23=F23,"一致","不一致")) -> 一致 | I23: 値段と原価 E20
A24: 値段と原価 | B24: 粗利率：25台・大事な場面だけ | D24: 割合 | E24: ='値段と原価'!$D$21 -> 0.70909091 | F24: 0.70909091 | G24: =IF(AND(ISNUMBER(E24),ISNUMBER(F24)),E24-F24,"─") -> 0 | H24: =IF(ISNUMBER(G24),IF(ABS(G24)<='前提'!$E$178,"一致","不一致"),IF(E24=F24,"一致","不一致")) -> 一致 | I24: 値段と原価 D21
A25: 値段と原価 | B25: 粗利率：25台・全編を毎秒解析 | D25: 割合 | E25: ='値段と原価'!$E$21 -> -1.2909091 | F25: -1.2909091 | G25: =IF(AND(ISNUMBER(E25),ISNUMBER(F25)),E25-F25,"─") -> 0 | H25: =IF(ISNUMBER(G25),IF(ABS(G25)<='前提'!$E$178,"一致","不一致"),IF(E25=F25,"一致","不一致")) -> 一致 | I25: 値段と原価 E21
A26: 導入支援 | B26: 1人日の人件費 | D26: 万円/人日 | E26: ='導入支援'!$C$16 -> 3 | F26: 3 | G26: =IF(AND(ISNUMBER(E26),ISNUMBER(F26)),E26-F26,"─") -> 0 | H26: =IF(ISNUMBER(G26),IF(ABS(G26)<='前提'!$E$178,"一致","不一致"),IF(E26=F26,"一致","不一致")) -> 一致 | I26: 導入支援 C16
A27: 導入支援 | B27: 導入支援の原価 | D27: 万円/拠点 | E27: ='導入支援'!$C$19 -> 141 | F27: 141 | G27: =IF(AND(ISNUMBER(E27),ISNUMBER(F27)),E27-F27,"─") -> 0 | H27: =IF(ISNUMBER(G27),IF(ABS(G27)<='前提'!$E$178,"一致","不一致"),IF(E27=F27,"一致","不一致")) -> 一致 | I27: 導入支援 C19
A28: 導入支援 | B28: 導入支援の粗利 | D28: 万円/拠点 | E28: ='導入支援'!$C$21 -> 59 | F28: 59 | G28: =IF(AND(ISNUMBER(E28),ISNUMBER(F28)),E28-F28,"─") -> 0 | H28: =IF(ISNUMBER(G28),IF(ABS(G28)<='前提'!$E$178,"一致","不一致"),IF(E28=F28,"一致","不一致")) -> 一致 | I28: 導入支援 C21
A29: 拠点 | B29: 期末の拠点 | C29: 1 | D29: 拠点 | E29: ='拠点と売上'!$C$9 -> 3 | F29: 3 | G29: =IF(AND(ISNUMBER(E29),ISNUMBER(F29)),E29-F29,"─") -> 0 | H29: =IF(ISNUMBER(G29),IF(ABS(G29)<='前提'!$E$178,"一致","不一致"),IF(E29=F29,"一致","不一致")) -> 一致 | I29: 拠点と売上 C9
A30: 拠点 | B30: 期末の拠点 | C30: 2 | D30: 拠点 | E30: ='拠点と売上'!$D$9 -> 12 | F30: 12 | G30: =IF(AND(ISNUMBER(E30),ISNUMBER(F30)),E30-F30,"─") -> 0 | H30: =IF(ISNUMBER(G30),IF(ABS(G30)<='前提'!$E$178,"一致","不一致"),IF(E30=F30,"一致","不一致")) -> 一致 | I30: 拠点と売上 D9
A31: 拠点 | B31: 期末の拠点 | C31: 3 | D31: 拠点 | E31: ='拠点と売上'!$E$9 -> 29 | F31: 29 | G31: =IF(AND(ISNUMBER(E31),ISNUMBER(F31)),E31-F31,"─") -> 0 | H31: =IF(ISNUMBER(G31),IF(ABS(G31)<='前提'!$E$178,"一致","不一致"),IF(E31=F31,"一致","不一致")) -> 一致 | I31: 拠点と売上 E9
A32: 拠点 | B32: 期末の拠点 | C32: 4 | D32: 拠点 | E32: ='拠点と売上'!$F$9 -> 53 | F32: 53 | G32: =IF(AND(ISNUMBER(E32),ISNUMBER(F32)),E32-F32,"─") -> 0 | H32: =IF(ISNUMBER(G32),IF(ABS(G32)<='前提'!$E$178,"一致","不一致"),IF(E32=F32,"一致","不一致")) -> 一致 | I32: 拠点と売上 F9
A33: 拠点 | B33: 期末の拠点 | C33: 5 | D33: 拠点 | E33: ='拠点と売上'!$G$9 -> 81 | F33: 81 | G33: =IF(AND(ISNUMBER(E33),ISNUMBER(F33)),E33-F33,"─") -> 0 | H33: =IF(ISNUMBER(G33),IF(ABS(G33)<='前提'!$E$178,"一致","不一致"),IF(E33=F33,"一致","不一致")) -> 一致 | I33: 拠点と売上 G9
A34: 拠点 | B34: 期末の拠点 | C34: 6 | D34: 拠点 | E34: ='拠点と売上'!$H$9 -> 109 | F34: 109 | G34: =IF(AND(ISNUMBER(E34),ISNUMBER(F34)),E34-F34,"─") -> 0 | H34: =IF(ISNUMBER(G34),IF(ABS(G34)<='前提'!$E$178,"一致","不一致"),IF(E34=F34,"一致","不一致")) -> 一致 | I34: 拠点と売上 H9
A35: 拠点 | B35: 期末の拠点 | C35: 7 | D35: 拠点 | E35: ='拠点と売上'!$I$9 -> 136 | F35: 136 | G35: =IF(AND(ISNUMBER(E35),ISNUMBER(F35)),E35-F35,"─") -> 0 | H35: =IF(ISNUMBER(G35),IF(ABS(G35)<='前提'!$E$178,"一致","不一致"),IF(E35=F35,"一致","不一致")) -> 一致 | I35: 拠点と売上 I9
A36: 拠点 | B36: 期末の拠点 | C36: 8 | D36: 拠点 | E36: ='拠点と売上'!$J$9 -> 162 | F36: 162 | G36: =IF(AND(ISNUMBER(E36),ISNUMBER(F36)),E36-F36,"─") -> 0 | H36: =IF(ISNUMBER(G36),IF(ABS(G36)<='前提'!$E$178,"一致","不一致"),IF(E36=F36,"一致","不一致")) -> 一致 | I36: 拠点と売上 J9
A37: 拠点 | B37: 期末の拠点 | C37: 9 | D37: 拠点 | E37: ='拠点と売上'!$K$9 -> 186 | F37: 186 | G37: =IF(AND(ISNUMBER(E37),ISNUMBER(F37)),E37-F37,"─") -> 0 | H37: =IF(ISNUMBER(G37),IF(ABS(G37)<='前提'!$E$178,"一致","不一致"),IF(E37=F37,"一致","不一致")) -> 一致 | I37: 拠点と売上 K9
A38: 拠点 | B38: 期末の拠点 | C38: 10 | D38: 拠点 | E38: ='拠点と売上'!$L$9 -> 207 | F38: 207 | G38: =IF(AND(ISNUMBER(E38),ISNUMBER(F38)),E38-F38,"─") -> 0 | H38: =IF(ISNUMBER(G38),IF(ABS(G38)<='前提'!$E$178,"一致","不一致"),IF(E38=F38,"一致","不一致")) -> 一致 | I38: 拠点と売上 L9
A39: 売上 | B39: 売上 | C39: 1 | D39: 万円 | E39: ='拠点と売上'!$C$22 -> 1200 | F39: 1200 | G39: =IF(AND(ISNUMBER(E39),ISNUMBER(F39)),E39-F39,"─") -> 0 | H39: =IF(ISNUMBER(G39),IF(ABS(G39)<='前提'!$E$178,"一致","不一致"),IF(E39=F39,"一致","不一致")) -> 一致 | I39: 拠点と売上 C22
A40: 売上 | B40: 売上 | C40: 2 | D40: 万円 | E40: ='拠点と売上'!$D$22 -> 4800 | F40: 4800 | G40: =IF(AND(ISNUMBER(E40),ISNUMBER(F40)),E40-F40,"─") -> 0 | H40: =IF(ISNUMBER(G40),IF(ABS(G40)<='前提'!$E$178,"一致","不一致"),IF(E40=F40,"一致","不一致")) -> 一致 | I40: 拠点と売上 D22
A41: 売上 | B41: 売上 | C41: 3 | D41: 万円 | E41: ='拠点と売上'!$E$22 -> 10700 | F41: 10700 | G41: =IF(AND(ISNUMBER(E41),ISNUMBER(F41)),E41-F41,"─") -> 0 | H41: =IF(ISNUMBER(G41),IF(ABS(G41)<='前提'!$E$178,"一致","不一致"),IF(E41=F41,"一致","不一致")) -> 一致 | I41: 拠点と売上 E22
A42: 売上 | B42: 売上 | C42: 4 | D42: 万円 | E42: ='拠点と売上'!$F$22 -> 17800 | F42: 17800 | G42: =IF(AND(ISNUMBER(E42),ISNUMBER(F42)),E42-F42,"─") -> 0 | H42: =IF(ISNUMBER(G42),IF(ABS(G42)<='前提'!$E$178,"一致","不一致"),IF(E42=F42,"一致","不一致")) -> 一致 | I42: 拠点と売上 F22
A43: 売上 | B43: 売上 | C43: 5 | D43: 万円 | E43: ='拠点と売上'!$G$22 -> 26900 | F43: 26900 | G43: =IF(AND(ISNUMBER(E43),ISNUMBER(F43)),E43-F43,"─") -> 0 | H43: =IF(ISNUMBER(G43),IF(ABS(G43)<='前提'!$E$178,"一致","不一致"),IF(E43=F43,"一致","不一致")) -> 一致 | I43: 拠点と売上 G22
A44: 売上 | B44: 売上 | C44: 6 | D44: 万円 | E44: ='拠点と売上'!$H$22 -> 35500 | F44: 35500 | G44: =IF(AND(ISNUMBER(E44),ISNUMBER(F44)),E44-F44,"─") -> 0 | H44: =IF(ISNUMBER(G44),IF(ABS(G44)<='前提'!$E$178,"一致","不一致"),IF(E44=F44,"一致","不一致")) -> 一致 | I44: 拠点と売上 H22
A45: 売上 | B45: 売上 | C45: 7 | D45: 万円 | E45: ='拠点と売上'!$I$22 -> 43800 | F45: 43800 | G45: =IF(AND(ISNUMBER(E45),ISNUMBER(F45)),E45-F45,"─") -> 0 | H45: =IF(ISNUMBER(G45),IF(ABS(G45)<='前提'!$E$178,"一致","不一致"),IF(E45=F45,"一致","不一致")) -> 一致 | I45: 拠点と売上 I22
A46: 売上 | B46: 売上 | C46: 8 | D46: 万円 | E46: ='拠点と売上'!$J$22 -> 51800 | F46: 51800 | G46: =IF(AND(ISNUMBER(E46),ISNUMBER(F46)),E46-F46,"─") -> 0 | H46: =IF(ISNUMBER(G46),IF(ABS(G46)<='前提'!$E$178,"一致","不一致"),IF(E46=F46,"一致","不一致")) -> 一致 | I46: 拠点と売上 J22
A47: 売上 | B47: 売上 | C47: 9 | D47: 万円 | E47: ='拠点と売上'!$K$22 -> 59100 | F47: 59100 | G47: =IF(AND(ISNUMBER(E47),ISNUMBER(F47)),E47-F47,"─") -> 0 | H47: =IF(ISNUMBER(G47),IF(ABS(G47)<='前提'!$E$178,"一致","不一致"),IF(E47=F47,"一致","不一致")) -> 一致 | I47: 拠点と売上 K22
A48: 売上 | B48: 売上 | C48: 10 | D48: 万円 | E48: ='拠点と売上'!$L$22 -> 65500 | F48: 65500 | G48: =IF(AND(ISNUMBER(E48),ISNUMBER(F48)),E48-F48,"─") -> 0 | H48: =IF(ISNUMBER(G48),IF(ABS(G48)<='前提'!$E$178,"一致","不一致"),IF(E48=F48,"一致","不一致")) -> 一致 | I48: 拠点と売上 L22
A49: 粗利 | B49: 粗利 | C49: 1 | D49: 万円 | E49: ='損益と現金'!$C$16 -> 314 | F49: 314 | G49: =IF(AND(ISNUMBER(E49),ISNUMBER(F49)),E49-F49,"─") -> 0 | H49: =IF(ISNUMBER(G49),IF(ABS(G49)<='前提'!$E$178,"一致","不一致"),IF(E49=F49,"一致","不一致")) -> 一致 | I49: 損益と現金 C16
A50: 粗利 | B50: 粗利 | C50: 2 | D50: 万円 | E50: ='損益と現金'!$D$16 -> 2401 | F50: 2401 | G50: =IF(AND(ISNUMBER(E50),ISNUMBER(F50)),E50-F50,"─") -> 0 | H50: =IF(ISNUMBER(G50),IF(ABS(G50)<='前提'!$E$178,"一致","不一致"),IF(E50=F50,"一致","不一致")) -> 一致 | I50: 損益と現金 D16
A51: 粗利 | B51: 粗利 | C51: 3 | D51: 万円 | E51: ='損益と現金'!$E$16 -> 5748.6667 | F51: 5748.6667 | G51: =IF(AND(ISNUMBER(E51),ISNUMBER(F51)),E51-F51,"─") -> 0 | H51: =IF(ISNUMBER(G51),IF(ABS(G51)<='前提'!$E$178,"一致","不一致"),IF(E51=F51,"一致","不一致")) -> 一致 | I51: 損益と現金 E16
A52: 粗利 | B52: 粗利 | C52: 4 | D52: 万円 | E52: ='損益と現金'!$F$16 -> 10308.333 | F52: 10308.333 | G52: =IF(AND(ISNUMBER(E52),ISNUMBER(F52)),E52-F52,"─") -> 0 | H52: =IF(ISNUMBER(G52),IF(ABS(G52)<='前提'!$E$178,"一致","不一致"),IF(E52=F52,"一致","不一致")) -> 一致 | I52: 損益と現金 F16
A53: 粗利 | B53: 粗利 | C53: 5 | D53: 万円 | E53: ='損益と現金'!$G$16 -> 16195.667 | F53: 16195.667 | G53: =IF(AND(ISNUMBER(E53),ISNUMBER(F53)),E53-F53,"─") -> 0 | H53: =IF(ISNUMBER(G53),IF(ABS(G53)<='前提'!$E$178,"一致","不一致"),IF(E53=F53,"一致","不一致")) -> 一致 | I53: 損益と現金 G16
A54: 粗利 | B54: 粗利 | C54: 6 | D54: 万円 | E54: ='損益と現金'!$H$16 -> 22113.333 | F54: 22113.333 | G54: =IF(AND(ISNUMBER(E54),ISNUMBER(F54)),E54-F54,"─") -> 0 | H54: =IF(ISNUMBER(G54),IF(ABS(G54)<='前提'!$E$178,"一致","不一致"),IF(E54=F54,"一致","不一致")) -> 一致 | I54: 損益と現金 H16
A55: 粗利 | B55: 粗利 | C55: 7 | D55: 万円 | E55: ='損益と現金'!$I$16 -> 27880.667 | F55: 27880.667 | G55: =IF(AND(ISNUMBER(E55),ISNUMBER(F55)),E55-F55,"─") -> 0 | H55: =IF(ISNUMBER(G55),IF(ABS(G55)<='前提'!$E$178,"一致","不一致"),IF(E55=F55,"一致","不一致")) -> 一致 | I55: 損益と現金 I16
A56: 粗利 | B56: 粗利 | C56: 8 | D56: 万円 | E56: ='損益と現金'!$J$16 -> 33432 | F56: 33432 | G56: =IF(AND(ISNUMBER(E56),ISNUMBER(F56)),E56-F56,"─") -> 0 | H56: =IF(ISNUMBER(G56),IF(ABS(G56)<='前提'!$E$178,"一致","不一致"),IF(E56=F56,"一致","不一致")) -> 一致 | I56: 損益と現金 J16
A57: 粗利 | B57: 粗利 | C57: 9 | D57: 万円 | E57: ='損益と現金'!$K$16 -> 38649.333 | F57: 38649.333 | G57: =IF(AND(ISNUMBER(E57),ISNUMBER(F57)),E57-F57,"─") -> 0 | H57: =IF(ISNUMBER(G57),IF(ABS(G57)<='前提'!$E$178,"一致","不一致"),IF(E57=F57,"一致","不一致")) -> 一致 | I57: 損益と現金 K16
A58: 粗利 | B58: 粗利 | C58: 10 | D58: 万円 | E58: ='損益と現金'!$L$16 -> 43218.667 | F58: 43218.667 | G58: =IF(AND(ISNUMBER(E58),ISNUMBER(F58)),E58-F58,"─") -> 0 | H58: =IF(ISNUMBER(G58),IF(ABS(G58)<='前提'!$E$178,"一致","不一致"),IF(E58=F58,"一致","不一致")) -> 一致 | I58: 損益と現金 L16
A59: 販管費 | B59: 販管費 | C59: 1 | D59: 万円 | E59: ='損益と現金'!$C$25 -> 5157.5 | F59: 5157.5 | G59: =IF(AND(ISNUMBER(E59),ISNUMBER(F59)),E59-F59,"─") -> 0 | H59: =IF(ISNUMBER(G59),IF(ABS(G59)<='前提'!$E$178,"一致","不一致"),IF(E59=F59,"一致","不一致")) -> 一致 | I59: 損益と現金 C25
A60: 販管費 | B60: 販管費 | C60: 2 | D60: 万円 | E60: ='損益と現金'!$D$25 -> 7163.5 | F60: 7163.5 | G60: =IF(AND(ISNUMBER(E60),ISNUMBER(F60)),E60-F60,"─") -> 0 | H60: =IF(ISNUMBER(G60),IF(ABS(G60)<='前提'!$E$178,"一致","不一致"),IF(E60=F60,"一致","不一致")) -> 一致 | I60: 損益と現金 D25
A61: 販管費 | B61: 販管費 | C61: 3 | D61: 万円 | E61: ='損益と現金'!$E$25 -> 9445.1667 | F61: 9445.1667 | G61: =IF(AND(ISNUMBER(E61),ISNUMBER(F61)),E61-F61,"─") -> 0 | H61: =IF(ISNUMBER(G61),IF(ABS(G61)<='前提'!$E$178,"一致","不一致"),IF(E61=F61,"一致","不一致")) -> 一致 | I61: 損益と現金 E25
A62: 販管費 | B62: 販管費 | C62: 4 | D62: 万円 | E62: ='損益と現金'!$F$25 -> 14165.333 | F62: 14165.333 | G62: =IF(AND(ISNUMBER(E62),ISNUMBER(F62)),E62-F62,"─") -> 0 | H62: =IF(ISNUMBER(G62),IF(ABS(G62)<='前提'!$E$178,"一致","不一致"),IF(E62=F62,"一致","不一致")) -> 一致 | I62: 損益と現金 F25
A63: 販管費 | B63: 販管費 | C63: 5 | D63: 万円 | E63: ='損益と現金'!$G$25 -> 17312.667 | F63: 17312.667 | G63: =IF(AND(ISNUMBER(E63),ISNUMBER(F63)),E63-F63,"─") -> 0 | H63: =IF(ISNUMBER(G63),IF(ABS(G63)<='前提'!$E$178,"一致","不一致"),IF(E63=F63,"一致","不一致")) -> 一致 | I63: 損益と現金 G25
A64: 販管費 | B64: 販管費 | C64: 6 | D64: 万円 | E64: ='損益と現金'!$H$25 -> 17591.333 | F64: 17591.333 | G64: =IF(AND(ISNUMBER(E64),ISNUMBER(F64)),E64-F64,"─") -> 0 | H64: =IF(ISNUMBER(G64),IF(ABS(G64)<='前提'!$E$178,"一致","不一致"),IF(E64=F64,"一致","不一致")) -> 一致 | I64: 損益と現金 H25
A65: 販管費 | B65: 販管費 | C65: 7 | D65: 万円 | E65: ='損益と現金'!$I$25 -> 19997.667 | F65: 19997.667 | G65: =IF(AND(ISNUMBER(E65),ISNUMBER(F65)),E65-F65,"─") -> 0 | H65: =IF(ISNUMBER(G65),IF(ABS(G65)<='前提'!$E$178,"一致","不一致"),IF(E65=F65,"一致","不一致")) -> 一致 | I65: 損益と現金 I25
A66: 販管費 | B66: 販管費 | C66: 8 | D66: 万円 | E66: ='損益と現金'!$J$25 -> 21426.5 | F66: 21426.5 | G66: =IF(AND(ISNUMBER(E66),ISNUMBER(F66)),E66-F66,"─") -> 0 | H66: =IF(ISNUMBER(G66),IF(ABS(G66)<='前提'!$E$178,"一致","不一致"),IF(E66=F66,"一致","不一致")) -> 一致 | I66: 損益と現金 J25
A67: 販管費 | B67: 販管費 | C67: 9 | D67: 万円 | E67: ='損益と現金'!$K$25 -> 22342.333 | F67: 22342.333 | G67: =IF(AND(ISNUMBER(E67),ISNUMBER(F67)),E67-F67,"─") -> 0 | H67: =IF(ISNUMBER(G67),IF(ABS(G67)<='前提'!$E$178,"一致","不一致"),IF(E67=F67,"一致","不一致")) -> 一致 | I67: 損益と現金 K25
A68: 販管費 | B68: 販管費 | C68: 10 | D68: 万円 | E68: ='損益と現金'!$L$25 -> 24238.167 | F68: 24238.167 | G68: =IF(AND(ISNUMBER(E68),ISNUMBER(F68)),E68-F68,"─") -> 0 | H68: =IF(ISNUMBER(G68),IF(ABS(G68)<='前提'!$E$178,"一致","不一致"),IF(E68=F68,"一致","不一致")) -> 一致 | I68: 損益と現金 L25
A69: 営業利益 | B69: 営業利益 | C69: 1 | D69: 万円 | E69: ='損益と現金'!$C$27 -> -4843.5 | F69: -4843.5 | G69: =IF(AND(ISNUMBER(E69),ISNUMBER(F69)),E69-F69,"─") -> 0 | H69: =IF(ISNUMBER(G69),IF(ABS(G69)<='前提'!$E$178,"一致","不一致"),IF(E69=F69,"一致","不一致")) -> 一致 | I69: 損益と現金 C27
A70: 営業利益 | B70: 営業利益 | C70: 2 | D70: 万円 | E70: ='損益と現金'!$D$27 -> -4762.5 | F70: -4762.5 | G70: =IF(AND(ISNUMBER(E70),ISNUMBER(F70)),E70-F70,"─") -> 0 | H70: =IF(ISNUMBER(G70),IF(ABS(G70)<='前提'!$E$178,"一致","不一致"),IF(E70=F70,"一致","不一致")) -> 一致 | I70: 損益と現金 D27
A71: 営業利益 | B71: 営業利益 | C71: 3 | D71: 万円 | E71: ='損益と現金'!$E$27 -> -3696.5 | F71: -3696.5 | G71: =IF(AND(ISNUMBER(E71),ISNUMBER(F71)),E71-F71,"─") -> 0 | H71: =IF(ISNUMBER(G71),IF(ABS(G71)<='前提'!$E$178,"一致","不一致"),IF(E71=F71,"一致","不一致")) -> 一致 | I71: 損益と現金 E27
A72: 営業利益 | B72: 営業利益 | C72: 4 | D72: 万円 | E72: ='損益と現金'!$F$27 -> -3857 | F72: -3857 | G72: =IF(AND(ISNUMBER(E72),ISNUMBER(F72)),E72-F72,"─") -> 0 | H72: =IF(ISNUMBER(G72),IF(ABS(G72)<='前提'!$E$178,"一致","不一致"),IF(E72=F72,"一致","不一致")) -> 一致 | I72: 損益と現金 F27
A73: 営業利益 | B73: 営業利益 | C73: 5 | D73: 万円 | E73: ='損益と現金'!$G$27 -> -1117 | F73: -1117 | G73: =IF(AND(ISNUMBER(E73),ISNUMBER(F73)),E73-F73,"─") -> 0 | H73: =IF(ISNUMBER(G73),IF(ABS(G73)<='前提'!$E$178,"一致","不一致"),IF(E73=F73,"一致","不一致")) -> 一致 | I73: 損益と現金 G27
A74: 営業利益 | B74: 営業利益 | C74: 6 | D74: 万円 | E74: ='損益と現金'!$H$27 -> 4522 | F74: 4522 | G74: =IF(AND(ISNUMBER(E74),ISNUMBER(F74)),E74-F74,"─") -> 0 | H74: =IF(ISNUMBER(G74),IF(ABS(G74)<='前提'!$E$178,"一致","不一致"),IF(E74=F74,"一致","不一致")) -> 一致 | I74: 損益と現金 H27
A75: 営業利益 | B75: 営業利益 | C75: 7 | D75: 万円 | E75: ='損益と現金'!$I$27 -> 7883 | F75: 7883 | G75: =IF(AND(ISNUMBER(E75),ISNUMBER(F75)),E75-F75,"─") -> 0 | H75: =IF(ISNUMBER(G75),IF(ABS(G75)<='前提'!$E$178,"一致","不一致"),IF(E75=F75,"一致","不一致")) -> 一致 | I75: 損益と現金 I27
A76: 営業利益 | B76: 営業利益 | C76: 8 | D76: 万円 | E76: ='損益と現金'!$J$27 -> 12005.5 | F76: 12005.5 | G76: =IF(AND(ISNUMBER(E76),ISNUMBER(F76)),E76-F76,"─") -> 0 | H76: =IF(ISNUMBER(G76),IF(ABS(G76)<='前提'!$E$178,"一致","不一致"),IF(E76=F76,"一致","不一致")) -> 一致 | I76: 損益と現金 J27
A77: 営業利益 | B77: 営業利益 | C77: 9 | D77: 万円 | E77: ='損益と現金'!$K$27 -> 16307 | F77: 16307 | G77: =IF(AND(ISNUMBER(E77),ISNUMBER(F77)),E77-F77,"─") -> 0 | H77: =IF(ISNUMBER(G77),IF(ABS(G77)<='前提'!$E$178,"一致","不一致"),IF(E77=F77,"一致","不一致")) -> 一致 | I77: 損益と現金 K27
A78: 営業利益 | B78: 営業利益 | C78: 10 | D78: 万円 | E78: ='損益と現金'!$L$27 -> 18980.5 | F78: 18980.5 | G78: =IF(AND(ISNUMBER(E78),ISNUMBER(F78)),E78-F78,"─") -> 0 | H78: =IF(ISNUMBER(G78),IF(ABS(G78)<='前提'!$E$178,"一致","不一致"),IF(E78=F78,"一致","不一致")) -> 一致 | I78: 損益と現金 L27
A79: 累計 | B79: 累計の営業損益 | C79: 1 | D79: 万円 | E79: ='損益と現金'!$C$28 -> -4843.5 | F79: -4843.5 | G79: =IF(AND(ISNUMBER(E79),ISNUMBER(F79)),E79-F79,"─") -> 0 | H79: =IF(ISNUMBER(G79),IF(ABS(G79)<='前提'!$E$178,"一致","不一致"),IF(E79=F79,"一致","不一致")) -> 一致 | I79: 損益と現金 C28
A80: 累計 | B80: 累計の営業損益 | C80: 2 | D80: 万円 | E80: ='損益と現金'!$D$28 -> -9606 | F80: -9606 | G80: =IF(AND(ISNUMBER(E80),ISNUMBER(F80)),E80-F80,"─") -> 0 | H80: =IF(ISNUMBER(G80),IF(ABS(G80)<='前提'!$E$178,"一致","不一致"),IF(E80=F80,"一致","不一致")) -> 一致 | I80: 損益と現金 D28
A81: 累計 | B81: 累計の営業損益 | C81: 3 | D81: 万円 | E81: ='損益と現金'!$E$28 -> -13302.5 | F81: -13302.5 | G81: =IF(AND(ISNUMBER(E81),ISNUMBER(F81)),E81-F81,"─") -> 0 | H81: =IF(ISNUMBER(G81),IF(ABS(G81)<='前提'!$E$178,"一致","不一致"),IF(E81=F81,"一致","不一致")) -> 一致 | I81: 損益と現金 E28
A82: 累計 | B82: 累計の営業損益 | C82: 4 | D82: 万円 | E82: ='損益と現金'!$F$28 -> -17159.5 | F82: -17159.5 | G82: =IF(AND(ISNUMBER(E82),ISNUMBER(F82)),E82-F82,"─") -> 0 | H82: =IF(ISNUMBER(G82),IF(ABS(G82)<='前提'!$E$178,"一致","不一致"),IF(E82=F82,"一致","不一致")) -> 一致 | I82: 損益と現金 F28
A83: 累計 | B83: 累計の営業損益 | C83: 5 | D83: 万円 | E83: ='損益と現金'!$G$28 -> -18276.5 | F83: -18276.5 | G83: =IF(AND(ISNUMBER(E83),ISNUMBER(F83)),E83-F83,"─") -> 0 | H83: =IF(ISNUMBER(G83),IF(ABS(G83)<='前提'!$E$178,"一致","不一致"),IF(E83=F83,"一致","不一致")) -> 一致 | I83: 損益と現金 G28
A84: 累計 | B84: 累計の営業損益 | C84: 6 | D84: 万円 | E84: ='損益と現金'!$H$28 -> -13754.5 | F84: -13754.5 | G84: =IF(AND(ISNUMBER(E84),ISNUMBER(F84)),E84-F84,"─") -> 0 | H84: =IF(ISNUMBER(G84),IF(ABS(G84)<='前提'!$E$178,"一致","不一致"),IF(E84=F84,"一致","不一致")) -> 一致 | I84: 損益と現金 H28
A85: 累計 | B85: 累計の営業損益 | C85: 7 | D85: 万円 | E85: ='損益と現金'!$I$28 -> -5871.5 | F85: -5871.5 | G85: =IF(AND(ISNUMBER(E85),ISNUMBER(F85)),E85-F85,"─") -> 0 | H85: =IF(ISNUMBER(G85),IF(ABS(G85)<='前提'!$E$178,"一致","不一致"),IF(E85=F85,"一致","不一致")) -> 一致 | I85: 損益と現金 I28
A86: 累計 | B86: 累計の営業損益 | C86: 8 | D86: 万円 | E86: ='損益と現金'!$J$28 -> 6134 | F86: 6134 | G86: =IF(AND(ISNUMBER(E86),ISNUMBER(F86)),E86-F86,"─") -> 0 | H86: =IF(ISNUMBER(G86),IF(ABS(G86)<='前提'!$E$178,"一致","不一致"),IF(E86=F86,"一致","不一致")) -> 一致 | I86: 損益と現金 J28
A87: 累計 | B87: 累計の営業損益 | C87: 9 | D87: 万円 | E87: ='損益と現金'!$K$28 -> 22441 | F87: 22441 | G87: =IF(AND(ISNUMBER(E87),ISNUMBER(F87)),E87-F87,"─") -> 0 | H87: =IF(ISNUMBER(G87),IF(ABS(G87)<='前提'!$E$178,"一致","不一致"),IF(E87=F87,"一致","不一致")) -> 一致 | I87: 損益と現金 K28
A88: 累計 | B88: 累計の営業損益 | C88: 10 | D88: 万円 | E88: ='損益と現金'!$L$28 -> 41421.5 | F88: 41421.5 | G88: =IF(AND(ISNUMBER(E88),ISNUMBER(F88)),E88-F88,"─") -> 0 | H88: =IF(ISNUMBER(G88),IF(ABS(G88)<='前提'!$E$178,"一致","不一致"),IF(E88=F88,"一致","不一致")) -> 一致 | I88: 損益と現金 L28
A89: 現金 | B89: 期末の現金 | C89: 1 | D89: 万円 | E89: ='損益と現金'!$C$30 -> 15156.5 | F89: 15156.5 | G89: =IF(AND(ISNUMBER(E89),ISNUMBER(F89)),E89-F89,"─") -> 0 | H89: =IF(ISNUMBER(G89),IF(ABS(G89)<='前提'!$E$178,"一致","不一致"),IF(E89=F89,"一致","不一致")) -> 一致 | I89: 損益と現金 C30
A90: 現金 | B90: 期末の現金 | C90: 2 | D90: 万円 | E90: ='損益と現金'!$D$30 -> 10394 | F90: 10394 | G90: =IF(AND(ISNUMBER(E90),ISNUMBER(F90)),E90-F90,"─") -> 0 | H90: =IF(ISNUMBER(G90),IF(ABS(G90)<='前提'!$E$178,"一致","不一致"),IF(E90=F90,"一致","不一致")) -> 一致 | I90: 損益と現金 D30
A91: 現金 | B91: 期末の現金 | C91: 3 | D91: 万円 | E91: ='損益と現金'!$E$30 -> 11697.5 | F91: 11697.5 | G91: =IF(AND(ISNUMBER(E91),ISNUMBER(F91)),E91-F91,"─") -> 0 | H91: =IF(ISNUMBER(G91),IF(ABS(G91)<='前提'!$E$178,"一致","不一致"),IF(E91=F91,"一致","不一致")) -> 一致 | I91: 損益と現金 E30
A92: 現金 | B92: 期末の現金 | C92: 4 | D92: 万円 | E92: ='損益と現金'!$F$30 -> 7840.5 | F92: 7840.5 | G92: =IF(AND(ISNUMBER(E92),ISNUMBER(F92)),E92-F92,"─") -> 0 | H92: =IF(ISNUMBER(G92),IF(ABS(G92)<='前提'!$E$178,"一致","不一致"),IF(E92=F92,"一致","不一致")) -> 一致 | I92: 損益と現金 F30
A93: 現金 | B93: 期末の現金 | C93: 5 | D93: 万円 | E93: ='損益と現金'!$G$30 -> 6723.5 | F93: 6723.5 | G93: =IF(AND(ISNUMBER(E93),ISNUMBER(F93)),E93-F93,"─") -> 0 | H93: =IF(ISNUMBER(G93),IF(ABS(G93)<='前提'!$E$178,"一致","不一致"),IF(E93=F93,"一致","不一致")) -> 一致 | I93: 損益と現金 G30
A94: 現金 | B94: 期末の現金 | C94: 6 | D94: 万円 | E94: ='損益と現金'!$H$30 -> 11245.5 | F94: 11245.5 | G94: =IF(AND(ISNUMBER(E94),ISNUMBER(F94)),E94-F94,"─") -> 0 | H94: =IF(ISNUMBER(G94),IF(ABS(G94)<='前提'!$E$178,"一致","不一致"),IF(E94=F94,"一致","不一致")) -> 一致 | I94: 損益と現金 H30
A95: 現金 | B95: 期末の現金 | C95: 7 | D95: 万円 | E95: ='損益と現金'!$I$30 -> 19128.5 | F95: 19128.5 | G95: =IF(AND(ISNUMBER(E95),ISNUMBER(F95)),E95-F95,"─") -> 0 | H95: =IF(ISNUMBER(G95),IF(ABS(G95)<='前提'!$E$178,"一致","不一致"),IF(E95=F95,"一致","不一致")) -> 一致 | I95: 損益と現金 I30
A96: 現金 | B96: 期末の現金 | C96: 8 | D96: 万円 | E96: ='損益と現金'!$J$30 -> 31134 | F96: 31134 | G96: =IF(AND(ISNUMBER(E96),ISNUMBER(F96)),E96-F96,"─") -> 0 | H96: =IF(ISNUMBER(G96),IF(ABS(G96)<='前提'!$E$178,"一致","不一致"),IF(E96=F96,"一致","不一致")) -> 一致 | I96: 損益と現金 J30
A97: 現金 | B97: 期末の現金 | C97: 9 | D97: 万円 | E97: ='損益と現金'!$K$30 -> 47441 | F97: 47441 | G97: =IF(AND(ISNUMBER(E97),ISNUMBER(F97)),E97-F97,"─") -> 0 | H97: =IF(ISNUMBER(G97),IF(ABS(G97)<='前提'!$E$178,"一致","不一致"),IF(E97=F97,"一致","不一致")) -> 一致 | I97: 損益と現金 K30
A98: 現金 | B98: 期末の現金 | C98: 10 | D98: 万円 | E98: ='損益と現金'!$L$30 -> 66421.5 | F98: 66421.5 | G98: =IF(AND(ISNUMBER(E98),ISNUMBER(F98)),E98-F98,"─") -> 0 | H98: =IF(ISNUMBER(G98),IF(ABS(G98)<='前提'!$E$178,"一致","不一致"),IF(E98=F98,"一致","不一致")) -> 一致 | I98: 損益と現金 L30
A99: 体制 | B99: 社員数 | C99: 1 | D99: 人 | E99: ='体制と人件費'!$C$46 -> 5 | F99: 5 | G99: =IF(AND(ISNUMBER(E99),ISNUMBER(F99)),E99-F99,"─") -> 0 | H99: =IF(ISNUMBER(G99),IF(ABS(G99)<='前提'!$E$178,"一致","不一致"),IF(E99=F99,"一致","不一致")) -> 一致 | I99: 体制と人件費 C46
A100: 体制 | B100: 社員数 | C100: 2 | D100: 人 | E100: ='体制と人件費'!$D$46 -> 8 | F100: 8 | G100: =IF(AND(ISNUMBER(E100),ISNUMBER(F100)),E100-F100,"─") -> 0 | H100: =IF(ISNUMBER(G100),IF(ABS(G100)<='前提'!$E$178,"一致","不一致"),IF(E100=F100,"一致","不一致")) -> 一致 | I100: 体制と人件費 D46
...
